Workbook
Name UPDATE: 'Data Sheet'!$E$1

Sheet Financials>

Sheet HistoricalFS
B2: ="Historical Financial Statement - "&'Data Sheet'!B1 -> Historical Financial Statement - HINDUSTAN UNILEVER LTD
B3: Years | C3: ='Data Sheet'!B16 -> 42460 | D3: ='Data Sheet'!C16 -> 42825 | E3: ='Data Sheet'!D16 -> 43190 | F3: ='Data Sheet'!E16 -> 43555 | G3: ='Data Sheet'!F16 -> 43921 | H3: ='Data Sheet'!G16 -> 44286 | I3: ='Data Sheet'!H16 -> 44651 | J3: ='Data Sheet'!I16 -> 45016 | ... L3: ='Data Sheet'!K16 -> 45747 | M3: LTM
A5: # | B5: Income Statement
B6: Sales | C6: ='Data Sheet'!B17 -> 32186 | D6: ='Data Sheet'!C17 -> 33162 | E6: ='Data Sheet'!D17 -> 35545 | F6: ='Data Sheet'!E17 -> 39310 | G6: ='Data Sheet'!F17 -> 39783 | H6: ='Data Sheet'!G17 -> 47028 | I6: ='Data Sheet'!H17 -> 52446 | J6: ='Data Sheet'!I17 -> 60580 | ... L6: ='Data Sheet'!K17 -> 63121 | M6: =IFERROR(SUM('Data Sheet'!H42:K42),0) -> 64243
B7: Sales Growth | C7: - | D7: =IFERROR(D6/C6-1,0) -> 0.030323743 | E7: =IFERROR(E6/D6-1,0) -> 0.071859357 | F7: =IFERROR(F6/E6-1,0) -> 0.10592207 | G7: =IFERROR(G6/F6-1,0) -> 0.012032562 | H7: =IFERROR(H6/G6-1,0) -> 0.18211296 | I7: =IFERROR(I6/H6-1,0) -> 0.11520796 | J7: =IFERROR(J6/I6-1,0) -> 0.15509286 | K7: =IFERROR(K6/J6-1,0) -> 0.021723341 | ... M7: =IFERROR(M6/L6-1,0) -> 0.017775384
B9: COGS | C9: =IFERROR(SUM('Data Sheet'!B18,'Data Sheet'!B20,'Data Sheet'!B21,'Data Sheet'!B22)-1*'Data Sheet'!B19,0) -> 18222 | D9: =IFERROR(SUM('Data Sheet'!C18,'Data Sheet'!C20,'Data Sheet'!C21,'Data Sheet'!C22)-1*'Data Sheet'!C19,0) -> 18675 | E9: =IFERROR(SUM('Data Sheet'!D18,'Data Sheet'!D20,'Data Sheet'!D21,'Data Sheet'!D22)-1*'Data Sheet'!D19,0) -> 19314 | F9: =IFERROR(SUM('Data Sheet'!E18,'Data Sheet'!E20,'Data Sheet'!E21,'Data Sheet'!E22)-1*'Data Sheet'!E19,0) -> 21081 | G9: =IFERROR(SUM('Data Sheet'!F18,'Data Sheet'!F20,'Data Sheet'!F21,'Data Sheet'!F22)-1*'Data Sheet'!F19,0) -> 20614 | H9: =IFERROR(SUM('Data Sheet'!G18,'Data Sheet'!G20,'Data Sheet'!G21,'Data Sheet'!G22)-1*'Data Sheet'!G19,0) -> 25301 | I9: =IFERROR(SUM('Data Sheet'!H18,'Data Sheet'!H20,'Data Sheet'!H21,'Data Sheet'!H22)-1*'Data Sheet'!H19,0) -> 29066 | J9: =IFERROR(SUM('Data Sheet'!I18,'Data Sheet'!I20,'Data Sheet'!I21,'Data Sheet'!I22)-1*'Data Sheet'!I19,0) -> 35381 | ... L9: =IFERROR(SUM('Data Sheet'!K18,'Data Sheet'!K20,'Data Sheet'!K21,'Data Sheet'!K22)-1*'Data Sheet'!K19,0) -> 34529 | M9: =IFERROR(SUM('Data Sheet'!H43:K43),0) -> 49487
B10: COSG % Sales | C10: =IFERROR(C9/C6,0) -> 0.56614677 | D10: =IFERROR(D9/D6,0) -> 0.56314456 | E10: =IFERROR(E9/E6,0) -> 0.54336756 | F10: =IFERROR(F9/F6,0) -> 0.53627576 | G10: =IFERROR(G9/G6,0) -> 0.51816102 | H10: =IFERROR(H9/H6,0) -> 0.53799864 | I10: =IFERROR(I9/I6,0) -> 0.55420814 | J10: =IFERROR(J9/J6,0) -> 0.58403764 | ... M10: =IFERROR(M9/M6,0) -> 0.77030961
B12: Gross Profit | C12: =C6-C9 -> 13964 | D12: =D6-D9 -> 14487 | E12: =E6-E9 -> 16231 | F12: =F6-F9 -> 18229 | G12: =G6-G9 -> 19169 | H12: =H6-H9 -> 21727 | I12: =I6-I9 -> 23380 | J12: =J6-J9 -> 25199 | ... M12: =M6-M9 -> 14756
B13: Gross Margins | C13: =IFERROR(C12/C6,0) -> 0.43385323 | D13: =IFERROR(D12/D6,0) -> 0.43685544 | E13: =IFERROR(E12/E6,0) -> 0.45663244 | F13: =IFERROR(F12/F6,0) -> 0.46372424 | G13: =IFERROR(G12/G6,0) -> 0.48183898 | H13: =IFERROR(H12/H6,0) -> 0.46200136 | I13: =IFERROR(I12/I6,0) -> 0.44579186 | J13: =IFERROR(J12/J6,0) -> 0.41596236 | ... M13: =IFERROR(M12/M6,0) -> 0.22969039
B15: Selling & General Expenses | C15: =IFERROR(SUM('Data Sheet'!B23:B24),0) -> 8054 | D15: =IFERROR(SUM('Data Sheet'!C23:C24),0) -> 8159 | E15: =IFERROR(SUM('Data Sheet'!D23:D24),0) -> 8732 | F15: =IFERROR(SUM('Data Sheet'!E23:E24),0) -> 9349 | G15: =IFERROR(SUM('Data Sheet'!F23:F24),0) -> 9308 | H15: =IFERROR(SUM('Data Sheet'!G23:G24),0) -> 10101 | I15: =IFERROR(SUM('Data Sheet'!H23:H24),0) -> 10523 | J15: =IFERROR(SUM('Data Sheet'!I23:I24),0) -> 11052 | ... M15: =IFERROR(SUM('Data Sheet'!L23:L24),0) -> 0
B16: S&G Exp % Sales | C16: =IFERROR(C15/C6,0) -> 0.25023302 | D16: =IFERROR(D15/D6,0) -> 0.24603462 | E16: =IFERROR(E15/E6,0) -> 0.24566043 | F16: =IFERROR(F15/F6,0) -> 0.23782752 | G16: =IFERROR(G15/G6,0) -> 0.23396928 | H16: =IFERROR(H15/H6,0) -> 0.21478694 | I16: =IFERROR(I15/I6,0) -> 0.20064447 | J16: =IFERROR(J15/J6,0) -> 0.18243645 | ... M16: =IFERROR(M15/M6,0) -> 0
B18: EBITDA | C18: =C12-C15 -> 5910 | D18: =D12-D15 -> 6328 | E18: =E12-E15 -> 7499 | F18: =F12-F15 -> 8880 | G18: =G12-G15 -> 9861 | H18: =H12-H15 -> 11626 | I18: =I12-I15 -> 12857 | J18: =J12-J15 -> 14147 | ... L18: =L12-L15 -> 14843 | M18: =IFERROR(SUM('Data Sheet'!H51:K51),0) -> 16035
B19: EBITDA Margins | C19: =IFERROR(C18/C6,0) -> 0.18362021 | D19: =IFERROR(D18/D6,0) -> 0.19082082 | E19: =IFERROR(E18/E6,0) -> 0.21097201 | F19: =IFERROR(F18/F6,0) -> 0.22589672 | G19: =IFERROR(G18/G6,0) -> 0.24786969 | H19: =IFERROR(H18/H6,0) -> 0.24721443 | I19: =IFERROR(I18/I6,0) -> 0.24514739 | J19: =IFERROR(J18/J6,0) -> 0.23352592 | ... M19: =IFERROR(M18/M6,0) -> 0.24959918
B21: Interest | C21: =IFERROR('Data Sheet'!B27,0) -> 17 | D21: =IFERROR('Data Sheet'!C27,0) -> 35 | E21: =IFERROR('Data Sheet'!D27,0) -> 26 | F21: =IFERROR('Data Sheet'!E27,0) -> 33 | G21: =IFERROR('Data Sheet'!F27,0) -> 118 | H21: =IFERROR('Data Sheet'!G27,0) -> 117 | I21: =IFERROR('Data Sheet'!H27,0) -> 106 | J21: =IFERROR('Data Sheet'!I27,0) -> 114 | ... L21: =IFERROR('Data Sheet'!K27,0) -> 395 | M21: =IFERROR(SUM('Data Sheet'!H46:K46),0) -> 448
B22: Interest % Sales | C22: =IFERROR(C21/C6,0) -> 0.00052817995 | D22: =IFERROR(D21/D6,0) -> 0.0010554249 | E22: =IFERROR(E21/E6,0) -> 0.00073146715 | F22: =IFERROR(F21/F6,0) -> 0.00083948105 | G22: =IFERROR(G21/G6,0) -> 0.002966091 | H22: =IFERROR(H21/H6,0) -> 0.0024878796 | I22: =IFERROR(I21/I6,0) -> 0.0020211265 | J22: =IFERROR(J21/J6,0) -> 0.0018818092 | ... M22: =IFERROR(M21/M6,0) -> 0.0069735224
B24: Depreciation | C24: =IFERROR('Data Sheet'!B26,0) -> 353 | D24: =IFERROR('Data Sheet'!C26,0) -> 432 | E24: =IFERROR('Data Sheet'!D26,0) -> 520 | F24: =IFERROR('Data Sheet'!E26,0) -> 565 | G24: =IFERROR('Data Sheet'!F26,0) -> 1002 | H24: =IFERROR('Data Sheet'!G26,0) -> 1074 | I24: =IFERROR('Data Sheet'!H26,0) -> 1091 | J24: =IFERROR('Data Sheet'!I26,0) -> 1137 | ... L24: =IFERROR('Data Sheet'!K26,0) -> 1355 | M24: =IFERROR(SUM('Data Sheet'!H45:K45),0) -> 1407
B25: Deprecaiton % Sales | C25: =IFERROR(C24/C6,0) -> 0.010967501 | D25: =IFERROR(D24/D6,0) -> 0.013026959 | E25: =IFERROR(E24/E6,0) -> 0.014629343 | F25: =IFERROR(F24/F6,0) -> 0.014372933 | G25: =IFERROR(G24/G6,0) -> 0.025186638 | H25: =IFERROR(H24/H6,0) -> 0.022837459 | I25: =IFERROR(I24/I6,0) -> 0.020802349 | J25: =IFERROR(J24/J6,0) -> 0.01876857 | ... M25: =IFERROR(M24/M6,0) -> 0.021901219
B27: Earnings Before Tax | C27: =IFERROR(C18-SUM(C21+C24),0) -> 5540 | D27: =IFERROR(D18-SUM(D21+D24),0) -> 5861 | E27: =IFERROR(E18-SUM(E21+E24),0) -> 6953 | F27: =IFERROR(F18-SUM(F21+F24),0) -> 8282 | G27: =IFERROR(G18-SUM(G21+G24),0) -> 8741 | H27: =IFERROR(H18-SUM(H21+H24),0) -> 10435 | I27: =IFERROR(I18-SUM(I21+I24),0) -> 11660 | J27: =IFERROR(J18-SUM(J21+J24),0) -> 12896 | ... M27: =IFERROR(M18-SUM(M21+M24),0) -> 14180
B28: EBT % Sales | C28: =IFERROR(C27/C6,0) -> 0.17212453 | D28: =IFERROR(D27/D6,0) -> 0.17673844 | E28: =IFERROR(E27/E6,0) -> 0.1956112 | F28: =IFERROR(F27/F6,0) -> 0.2106843 | G28: =IFERROR(G27/G6,0) -> 0.21971696 | H28: =IFERROR(H27/H6,0) -> 0.22188909 | I28: =IFERROR(I27/I6,0) -> 0.22232391 | J28: =IFERROR(J27/J6,0) -> 0.21287554 | ... M28: =IFERROR(M27/M6,0) -> 0.22072444
B30: Tax | C30: =IFERROR('Data Sheet'!B29,0) -> 1875 | D30: =IFERROR('Data Sheet'!C29,0) -> 1977 | E30: =IFERROR('Data Sheet'!D29,0) -> 2079 | F30: =IFERROR('Data Sheet'!E29,0) -> 2544 | G30: =IFERROR('Data Sheet'!F29,0) -> 2409 | H30: =IFERROR('Data Sheet'!G29,0) -> 2606 | I30: =IFERROR('Data Sheet'!H29,0) -> 2987 | J30: =IFERROR('Data Sheet'!I29,0) -> 3201 | ... L30: =IFERROR('Data Sheet'!K29,0) -> 3744 | M30: =IFERROR(SUM('Data Sheet'!H48:K48),0) -> 3291
B31: Effective Tax Rate | C31: =IFERROR(C30/C27,0) -> 0.33844765 | D31: =IFERROR(D30/D27,0) -> 0.33731445 | E31: =IFERROR(E30/E27,0) -> 0.29900762 | F31: =IFERROR(F30/F27,0) -> 0.30717218 | G31: =IFERROR(G30/G27,0) -> 0.27559776 | H31: =IFERROR(H30/H27,0) -> 0.24973646 | I31: =IFERROR(I30/I27,0) -> 0.25617496 | J31: =IFERROR(J30/J27,0) -> 0.2482165 | ... M31: =IFERROR(M30/M27,0) -> 0.23208745
B33: Net Profit | C33: =IFERROR(C27-C30,0) -> 3665 | D33: =IFERROR(D27-D30,0) -> 3884 | E33: =IFERROR(E27-E30,0) -> 4874 | F33: =IFERROR(F27-F30,0) -> 5738 | G33: =IFERROR(G27-G30,0) -> 6332 | H33: =IFERROR(H27-H30,0) -> 7829 | I33: =IFERROR(I27-I30,0) -> 8673 | J33: =IFERROR(J27-J30,0) -> 9695 | ... M33: =IFERROR(M27-M30,0) -> 10889
B34: Net Margins | C34: =IFERROR(C33/C6,0) -> 0.11386938 | D34: =IFERROR(D33/D6,0) -> 0.11712201 | E34: =IFERROR(E33/E6,0) -> 0.13712196 | F34: =IFERROR(F33/F6,0) -> 0.14596795 | G34: =IFERROR(G33/G6,0) -> 0.15916346 | H34: =IFERROR(H33/H6,0) -> 0.16647529 | I34: =IFERROR(I33/I6,0) -> 0.16537009 | J34: =IFERROR(J33/J6,0) -> 0.16003632 | ... M34: =IFERROR(M33/M6,0) -> 0.16949707
B36: No of Equity Shares | C36: =IFERROR('Data Sheet'!B93,0) -> 216.39 | D36: =IFERROR('Data Sheet'!C93,0) -> 216.43 | E36: =IFERROR('Data Sheet'!D93,0) -> 216.45 | F36: =IFERROR('Data Sheet'!E93,0) -> 216.47 | G36: =IFERROR('Data Sheet'!F93,0) -> 216.48 | H36: =IFERROR('Data Sheet'!G93,0) -> 234.96 | I36: =IFERROR('Data Sheet'!H93,0) -> 234.96 | J36: =IFERROR('Data Sheet'!I93,0) -> 234.96 | ... M36: =IFERROR('Data Sheet'!L93,0) -> 0
B38: Earnings per Share | C38: =IFERROR(C33/C36,0) -> 16.937012 | D38: =IFERROR(D33/D36,0) -> 17.945756 | E38: =IFERROR(E33/E36,0) -> 22.517903 | F38: =IFERROR(F33/F36,0) -> 26.507137 | G38: =IFERROR(G33/G36,0) -> 29.249815 | H38: =IFERROR(H33/H36,0) -> 33.320565 | I38: =IFERROR(I33/I36,0) -> 36.912666 | J38: =IFERROR(J33/J36,0) -> 41.262343 | ... M38: =IFERROR(M33/M36,0) -> 0
B39: EPS Growth % | D39: =IFERROR(D38/C38-1,0) -> 0.059558573 | E39: =E38/D38-1 -> 0.25477591 | F39: =F38/E38-1 -> 0.17715836 | G39: =G38/F38-1 -> 0.10346941 | H39: =H38/G38-1 -> 0.13917182 | I39: =I38/H38-1 -> 0.10780432 | J39: =J38/I38-1 -> 0.11783697 | K39: =K38/J38-1 -> -0.023723569 | L39: =L38/K38-1 -> -0.012255679 | M39: =M38/L38-1 -> -1
B41: Dividend per Share | C41: =IFERROR('Data Sheet'!B31/HistoricalFS!C36,0) -> 15.971163 | D41: =IFERROR('Data Sheet'!C31/HistoricalFS!D36,0) -> 16.966225 | E41: =IFERROR('Data Sheet'!D31/HistoricalFS!E36,0) -> 19.95842 | F41: =IFERROR('Data Sheet'!E31/HistoricalFS!F36,0) -> 21.952234 | G41: =IFERROR('Data Sheet'!F31/HistoricalFS!G36,0) -> 24.944568 | H41: =IFERROR('Data Sheet'!G31/HistoricalFS!H36,0) -> 40.506895 | I41: =IFERROR('Data Sheet'!H31/HistoricalFS!I36,0) -> 34.005788 | J41: =IFERROR('Data Sheet'!I31/HistoricalFS!J36,0) -> 39.006639 | ... M41: =IFERROR('Data Sheet'!L31/HistoricalFS!M36,0) -> 0
B42: Dividend Payout Ratio | C42: =IFERROR(C41/C38,0) -> 0.94297408 | D42: =IFERROR(D41/D38,0) -> 0.9454171 | E42: =IFERROR(E41/E38,0) -> 0.88633566 | F42: =IFERROR(F41/F38,0) -> 0.82816312 | G42: =IFERROR(G41/G38,0) -> 0.85281112 | H42: =IFERROR(H41/H38,0) -> 1.2156725 | I42: =IFERROR(I41/I38,0) -> 0.92124986 | J42: =IFERROR(J41/J38,0) -> 0.94533265 | ... M42: =IFERROR(M41/M38,0) -> 0
B44: Retained Earnings | C44: =IFERROR(IF(C38>C41,1-C42,0),0) -> 0.057025921 | D44: =IFERROR(IF(D38>D41,1-D42,0),0) -> 0.054582904 | E44: =IFERROR(IF(E38>E41,1-E42,0),0) -> 0.11366434 | F44: =IFERROR(IF(F38>F41,1-F42,0),0) -> 0.17183688 | G44: =IFERROR(IF(G38>G41,1-G42,0),0) -> 0.14718888 | H44: =IFERROR(IF(H38>H41,1-H42,0),0) -> 0 | I44: =IFERROR(IF(I38>I41,1-I42,0),0) -> 0.078750144 | J44: =IFERROR(IF(J38>J41,1-J42,0),0) -> 0.054667354 | ... M44: =IFERROR(IF(M38>M41,1-M42,0),0) -> 0
A46: # | B46: Balance Sheet
B47: Equity Share Capital | C47: =IFERROR('Data Sheet'!B57,0) -> 216 | D47: =IFERROR('Data Sheet'!C57,0) -> 216 | E47: =IFERROR('Data Sheet'!D57,0) -> 216 | F47: =IFERROR('Data Sheet'!E57,0) -> 216 | G47: =IFERROR('Data Sheet'!F57,0) -> 216 | H47: =IFERROR('Data Sheet'!G57,0) -> 235 | I47: =IFERROR('Data Sheet'!H57,0) -> 235 | J47: =IFERROR('Data Sheet'!I57,0) -> 235 | ... L47: =IFERROR('Data Sheet'!K57,0) -> 235
B48: Reserves | C48: =IFERROR('Data Sheet'!B58,0) -> 6357 | D48: =IFERROR('Data Sheet'!C58,0) -> 6528 | E48: =IFERROR('Data Sheet'!D58,0) -> 7065 | F48: =IFERROR('Data Sheet'!E58,0) -> 7651 | G48: =IFERROR('Data Sheet'!F58,0) -> 8013 | H48: =IFERROR('Data Sheet'!G58,0) -> 47439 | I48: =IFERROR('Data Sheet'!H58,0) -> 48826 | J48: =IFERROR('Data Sheet'!I58,0) -> 50069 | ... L48: =IFERROR('Data Sheet'!K58,0) -> 49167
B49: Borrowings | C49: =IFERROR('Data Sheet'!B59,0) -> 177 | D49: =IFERROR('Data Sheet'!C59,0) -> 277 | E49: =IFERROR('Data Sheet'!D59,0) -> 0 | F49: =IFERROR('Data Sheet'!E59,0) -> 99 | G49: =IFERROR('Data Sheet'!F59,0) -> 0 | H49: =IFERROR('Data Sheet'!G59,0) -> 0 | I49: =IFERROR('Data Sheet'!H59,0) -> 1043 | J49: =IFERROR('Data Sheet'!I59,0) -> 1219 | ... L49: =IFERROR('Data Sheet'!K59,0) -> 1648
B50: Other Liabilities | C50: =IFERROR('Data Sheet'!B60,0) -> 8043 | D50: =IFERROR('Data Sheet'!C60,0) -> 8685 | E50: =IFERROR('Data Sheet'!D60,0) -> 10581 | F50: =IFERROR('Data Sheet'!E60,0) -> 10663 | G50: =IFERROR('Data Sheet'!F60,0) -> 11924 | H50: =IFERROR('Data Sheet'!G60,0) -> 21066 | I50: =IFERROR('Data Sheet'!H60,0) -> 20402 | J50: =IFERROR('Data Sheet'!I60,0) -> 21554 | ... L50: =IFERROR('Data Sheet'!K60,0) -> 28813
B51: Total Laibilities | C51: =IFERROR('Data Sheet'!B61,0) -> 14793 | D51: =IFERROR('Data Sheet'!C61,0) -> 15706 | E51: =IFERROR('Data Sheet'!D61,0) -> 17862 | F51: =IFERROR('Data Sheet'!E61,0) -> 18629 | G51: =IFERROR('Data Sheet'!F61,0) -> 20153 | H51: =IFERROR('Data Sheet'!G61,0) -> 68740 | I51: =IFERROR('Data Sheet'!H61,0) -> 70506 | J51: =IFERROR('Data Sheet'!I61,0) -> 73077 | ... L51: =IFERROR('Data Sheet'!K61,0) -> 79863
B53: Fixed Asset Net Block | C53: =IFERROR('Data Sheet'!B62,0) -> 3258 | D53: =IFERROR('Data Sheet'!C62,0) -> 4419 | E53: =IFERROR('Data Sheet'!D62,0) -> 4528 | F53: =IFERROR('Data Sheet'!E62,0) -> 4715 | G53: =IFERROR('Data Sheet'!F62,0) -> 5479 | H53: =IFERROR('Data Sheet'!G62,0) -> 51443 | I53: =IFERROR('Data Sheet'!H62,0) -> 51473 | J53: =IFERROR('Data Sheet'!I62,0) -> 52678 | ... L53: =IFERROR('Data Sheet'!K62,0) -> 54335
B54: Capital Work in Progress | C54: =IFERROR('Data Sheet'!B63,0) -> 408 | D54: =IFERROR('Data Sheet'!C63,0) -> 229 | E54: =IFERROR('Data Sheet'!D63,0) -> 461 | F54: =IFERROR('Data Sheet'!E63,0) -> 406 | G54: =IFERROR('Data Sheet'!F63,0) -> 597 | H54: =IFERROR('Data Sheet'!G63,0) -> 745 | I54: =IFERROR('Data Sheet'!H63,0) -> 1313 | J54: =IFERROR('Data Sheet'!I63,0) -> 1132 | ... L54: =IFERROR('Data Sheet'!K63,0) -> 1009
B55: Investments | C55: =IFERROR('Data Sheet'!B64,0) -> 2592 | D55: =IFERROR('Data Sheet'!C64,0) -> 3794 | E55: =IFERROR('Data Sheet'!D64,0) -> 2873 | F55: =IFERROR('Data Sheet'!E64,0) -> 2716 | G55: =IFERROR('Data Sheet'!F64,0) -> 1255 | H55: =IFERROR('Data Sheet'!G64,0) -> 2709 | I55: =IFERROR('Data Sheet'!H64,0) -> 3521 | J55: =IFERROR('Data Sheet'!I64,0) -> 2882 | ... L55: =IFERROR('Data Sheet'!K64,0) -> 3810
B56: Other Assets | C56: =IFERROR('Data Sheet'!B65-(SUM('Data Sheet'!B67:B69)),0) -> 1536 | D56: =IFERROR('Data Sheet'!C65-(SUM('Data Sheet'!C67:C69)),0) -> 1810 | E56: =IFERROR('Data Sheet'!D65-(SUM('Data Sheet'!D67:D69)),0) -> 2692 | F56: =IFERROR('Data Sheet'!E65-(SUM('Data Sheet'!E67:E69)),0) -> 2645 | G56: =IFERROR('Data Sheet'!F65-(SUM('Data Sheet'!F67:F69)),0) -> 3793 | H56: =IFERROR('Data Sheet'!G65-(SUM('Data Sheet'!G67:G69)),0) -> 4035 | I56: =IFERROR('Data Sheet'!H65-(SUM('Data Sheet'!H67:H69)),0) -> 4021 | J56: =IFERROR('Data Sheet'!I65-(SUM('Data Sheet'!I67:I69)),0) -> 4377 | ... L56: =IFERROR('Data Sheet'!K65-(SUM('Data Sheet'!K67:K69)),0) -> 4921
B57: Total Non Current Assets | C57: =IFERROR(SUM(C53:C56),0) -> 7794 | D57: =IFERROR(SUM(D53:D56),0) -> 10252 | E57: =IFERROR(SUM(E53:E56),0) -> 10554 | F57: =IFERROR(SUM(F53:F56),0) -> 10482 | G57: =IFERROR(SUM(G53:G56),0) -> 11124 | H57: =IFERROR(SUM(H53:H56),0) -> 58932 | I57: =IFERROR(SUM(I53:I56),0) -> 60328 | J57: =IFERROR(SUM(J53:J56),0) -> 61069 | ... L57: =IFERROR(SUM(L53:L56),0) -> 64075
B59: Receivables | C59: =IFERROR('Data Sheet'!B67,0) -> 1264 | D59: =IFERROR('Data Sheet'!C67,0) -> 1085 | E59: =IFERROR('Data Sheet'!D67,0) -> 1310 | F59: =IFERROR('Data Sheet'!E67,0) -> 1816 | G59: =IFERROR('Data Sheet'!F67,0) -> 1149 | H59: =IFERROR('Data Sheet'!G67,0) -> 1758 | I59: =IFERROR('Data Sheet'!H67,0) -> 2236 | J59: =IFERROR('Data Sheet'!I67,0) -> 3079 | ... L59: =IFERROR('Data Sheet'!K67,0) -> 3819
B60: Inventory | C60: =IFERROR('Data Sheet'!B68,0) -> 2726 | D60: =IFERROR('Data Sheet'!C68,0) -> 2541 | E60: =IFERROR('Data Sheet'!D68,0) -> 2513 | F60: =IFERROR('Data Sheet'!E68,0) -> 2574 | G60: =IFERROR('Data Sheet'!F68,0) -> 2767 | H60: =IFERROR('Data Sheet'!G68,0) -> 3579 | I60: =IFERROR('Data Sheet'!H68,0) -> 4096 | J60: =IFERROR('Data Sheet'!I68,0) -> 4251 | ... L60: =IFERROR('Data Sheet'!K68,0) -> 4415
B61: Cash & Bank | C61: =IFERROR('Data Sheet'!B69,0) -> 3009 | D61: =IFERROR('Data Sheet'!C69,0) -> 1828 | E61: =IFERROR('Data Sheet'!D69,0) -> 3485 | F61: =IFERROR('Data Sheet'!E69,0) -> 3757 | G61: =IFERROR('Data Sheet'!F69,0) -> 5113 | H61: =IFERROR('Data Sheet'!G69,0) -> 4471 | I61: =IFERROR('Data Sheet'!H69,0) -> 3846 | J61: =IFERROR('Data Sheet'!I69,0) -> 4678 | ... L61: =IFERROR('Data Sheet'!K69,0) -> 7554
B62: Total Current Assets | C62: =IFERROR(SUM(C59:C61),0) -> 6999 | D62: =IFERROR(SUM(D59:D61),0) -> 5454 | E62: =IFERROR(SUM(E59:E61),0) -> 7308 | F62: =IFERROR(SUM(F59:F61),0) -> 8147 | G62: =IFERROR(SUM(G59:G61),0) -> 9029 | H62: =IFERROR(SUM(H59:H61),0) -> 9808 | I62: =IFERROR(SUM(I59:I61),0) -> 10178 | J62: =IFERROR(SUM(J59:J61),0) -> 12008 | ... L62: =IFERROR(SUM(L59:L61),0) -> 15788
B64: Total Assets | C64: =IFERROR(SUM(C57+C62),0) -> 14793 | D64: =IFERROR(SUM(D57+D62),0) -> 15706 | E64: =IFERROR(SUM(E57+E62),0) -> 17862 | F64: =IFERROR(SUM(F57+F62),0) -> 18629 | G64: =IFERROR(SUM(G57+G62),0) -> 20153 | H64: =IFERROR(SUM(H57+H62),0) -> 68740 | I64: =IFERROR(SUM(I57+I62),0) -> 70506 | J64: =IFERROR(SUM(J57+J62),0) -> 73077 | ... L64: =IFERROR(SUM(L57+L62),0) -> 79863
B66: Check | C66: =C64=C51 -> TRUE | D66: =D64=D51 -> TRUE | E66: =E64=E51 -> TRUE | F66: =F64=F51 -> TRUE | G66: =G64=G51 -> TRUE | H66: =H64=H51 -> TRUE | I66: =I64=I51 -> TRUE | J66: =J64=J51 -> TRUE | ... L66: =L64=L51 -> TRUE
A68: # | B68: Cash Flow Statements
B69: Operating Activities
B70: Profit from operations | C70: =IFERROR('Cash Flow Data'!E4,0) -> 6025 | D70: =IFERROR('Cash Flow Data'!F4,0) -> 6512 | E70: =IFERROR('Cash Flow Data'!G4,0) -> 7485 | F70: =IFERROR('Cash Flow Data'!H4,0) -> 8909 | G70: =IFERROR('Cash Flow Data'!I4,0) -> 9723 | H70: =IFERROR('Cash Flow Data'!J4,0) -> 11672 | I70: =IFERROR('Cash Flow Data'!K4,0) -> 12829 | J70: =IFERROR('Cash Flow Data'!L4,0) -> 14089 | ... L70: =IFERROR('Cash Flow Data'!N4,0) -> 14942
B71: Receivables | C71: =IFERROR('Cash Flow Data'!E5,0) -> -257 | D71: =IFERROR('Cash Flow Data'!F5,0) -> 173 | E71: =IFERROR('Cash Flow Data'!G5,0) -> 0 | F71: =IFERROR('Cash Flow Data'!H5,0) -> 0 | G71: =IFERROR('Cash Flow Data'!I5,0) -> 0 | H71: =IFERROR('Cash Flow Data'!J5,0) -> 0 | I71: =IFERROR('Cash Flow Data'!K5,0) -> 0 | J71: =IFERROR('Cash Flow Data'!L5,0) -> 0 | ... L71: =IFERROR('Cash Flow Data'!N5,0) -> 0
B72: Inventory | C72: =IFERROR('Cash Flow Data'!E6,0) -> 89 | D72: =IFERROR('Cash Flow Data'!F6,0) -> 37 | E72: =IFERROR('Cash Flow Data'!G6,0) -> -146 | F72: =IFERROR('Cash Flow Data'!H6,0) -> -195 | G72: =IFERROR('Cash Flow Data'!I6,0) -> -331 | H72: =IFERROR('Cash Flow Data'!J6,0) -> -543 | I72: =IFERROR('Cash Flow Data'!K6,0) -> -758 | J72: =IFERROR('Cash Flow Data'!L6,0) -> -339 | ... L72: =IFERROR('Cash Flow Data'!N6,0) -> -584
B73: Payables | C73: =IFERROR('Cash Flow Data'!E7,0) -> 164 | D73: =IFERROR('Cash Flow Data'!F7,0) -> 501 | E73: =IFERROR('Cash Flow Data'!G7,0) -> 0 | F73: =IFERROR('Cash Flow Data'!H7,0) -> 0 | G73: =IFERROR('Cash Flow Data'!I7,0) -> 0 | H73: =IFERROR('Cash Flow Data'!J7,0) -> 0 | I73: =IFERROR('Cash Flow Data'!K7,0) -> 0 | J73: =IFERROR('Cash Flow Data'!L7,0) -> 0 | ... L73: =IFERROR('Cash Flow Data'!N7,0) -> 0
B74: Loans Advances | C74: =IFERROR('Cash Flow Data'!E8,0) -> 0 | D74: =IFERROR('Cash Flow Data'!F8,0) -> 0 | E74: =IFERROR('Cash Flow Data'!G8,0) -> 0 | F74: =IFERROR('Cash Flow Data'!H8,0) -> 0 | G74: =IFERROR('Cash Flow Data'!I8,0) -> 0 | H74: =IFERROR('Cash Flow Data'!J8,0) -> 0 | I74: =IFERROR('Cash Flow Data'!K8,0) -> 0 | J74: =IFERROR('Cash Flow Data'!L8,0) -> 0 | ... L74: =IFERROR('Cash Flow Data'!N8,0) -> 0
B75: Operating Deposits | C75: =IFERROR('Cash Flow Data'!E9,0) -> 0 | D75: =IFERROR('Cash Flow Data'!F9,0) -> -46 | E75: =IFERROR('Cash Flow Data'!G9,0) -> 0 | F75: =IFERROR('Cash Flow Data'!H9,0) -> 0 | G75: =IFERROR('Cash Flow Data'!I9,0) -> 0 | H75: =IFERROR('Cash Flow Data'!J9,0) -> 0 | I75: =IFERROR('Cash Flow Data'!K9,0) -> 0 | J75: =IFERROR('Cash Flow Data'!L9,0) -> 0 | ... L75: =IFERROR('Cash Flow Data'!N9,0) -> 0
B76: Other WC items | C76: =IFERROR('Cash Flow Data'!E10,0) -> -77 | D76: =IFERROR('Cash Flow Data'!F10,0) -> -99 | E76: =IFERROR('Cash Flow Data'!G10,0) -> 982 | F76: =IFERROR('Cash Flow Data'!H10,0) -> -147 | G76: =IFERROR('Cash Flow Data'!I10,0) -> 742 | H76: =IFERROR('Cash Flow Data'!J10,0) -> 442 | I76: =IFERROR('Cash Flow Data'!K10,0) -> -242 | J76: =IFERROR('Cash Flow Data'!L10,0) -> -621 | ... L76: =IFERROR('Cash Flow Data'!N10,0) -> -204
B77: Working capital changes | C77: =IFERROR('Cash Flow Data'!E11,0) -> -81 | D77: =IFERROR('Cash Flow Data'!F11,0) -> 566 | E77: =IFERROR('Cash Flow Data'!G11,0) -> 836 | F77: =IFERROR('Cash Flow Data'!H11,0) -> -342 | G77: =IFERROR('Cash Flow Data'!I11,0) -> 411 | H77: =IFERROR('Cash Flow Data'!J11,0) -> -101 | I77: =IFERROR('Cash Flow Data'!K11,0) -> -1000 | J77: =IFERROR('Cash Flow Data'!L11,0) -> -960 | ... L77: =IFERROR('Cash Flow Data'!N11,0) -> -788
B78: Direct taxes | C78: =IFERROR('Cash Flow Data'!E12,0) -> -1765 | D78: =IFERROR('Cash Flow Data'!F12,0) -> -1859 | E78: =IFERROR('Cash Flow Data'!G12,0) -> -2264 | F78: =IFERROR('Cash Flow Data'!H12,0) -> -2767 | G78: =IFERROR('Cash Flow Data'!I12,0) -> -2505 | H78: =IFERROR('Cash Flow Data'!J12,0) -> -2407 | I78: =IFERROR('Cash Flow Data'!K12,0) -> -2784 | J78: =IFERROR('Cash Flow Data'!L12,0) -> -3138 | ... L78: =IFERROR('Cash Flow Data'!N12,0) -> -2268
B79: Other operating items | C79: =IFERROR('Cash Flow Data'!E13,0) -> -8 | D79: =IFERROR('Cash Flow Data'!F13,0) -> -21 | E79: =IFERROR('Cash Flow Data'!G13,0) -> 0 | F79: =IFERROR('Cash Flow Data'!H13,0) -> 0 | G79: =IFERROR('Cash Flow Data'!I13,0) -> 0 | H79: =IFERROR('Cash Flow Data'!J13,0) -> 0 | I79: =IFERROR('Cash Flow Data'!K13,0) -> 0 | J79: =IFERROR('Cash Flow Data'!L13,0) -> 0 | ... L79: =IFERROR('Cash Flow Data'!N13,0) -> 0
B80: Exceptional CF items | C80: =IFERROR('Cash Flow Data'!E14,0) -> 0 | D80: =IFERROR('Cash Flow Data'!F14,0) -> -13 | E80: =IFERROR('Cash Flow Data'!G14,0) -> 2 | F80: =IFERROR('Cash Flow Data'!H14,0) -> 0 | G80: =IFERROR('Cash Flow Data'!I14,0) -> -6 | H80: =IFERROR('Cash Flow Data'!J14,0) -> -1 | I80: =IFERROR('Cash Flow Data'!K14,0) -> 3 | J80: =IFERROR('Cash Flow Data'!L14,0) -> 0 | ... L80: =IFERROR('Cash Flow Data'!N14,0) -> 0
B81: Cash From Operating Activities | C81: =IFERROR(SUM(C70+C77+C78+C79+C80),0) -> 4171 | D81: =IFERROR(SUM(D70+D77+D78+D79+D80),0) -> 5185 | E81: =IFERROR(SUM(E70+E77+E78+E79+E80),0) -> 6059 | F81: =IFERROR(SUM(F70+F77+F78+F79+F80),0) -> 5800 | G81: =IFERROR(SUM(G70+G77+G78+G79+G80),0) -> 7623 | H81: =IFERROR(SUM(H70+H77+H78+H79+H80),0) -> 9163 | I81: =IFERROR(SUM(I70+I77+I78+I79+I80),0) -> 9048 | J81: =IFERROR(SUM(J70+J77+J78+J79+J80),0) -> 9991 | ... L81: =IFERROR(SUM(L70+L77+L78+L79+L80),0) -> 11886
B83: Investing Activities
B84: Fixed assets purchased | C84: =IFERROR('Cash Flow Data'!E16,0) -> -810 | D84: =IFERROR('Cash Flow Data'!F16,0) -> -1113 | E84: =IFERROR('Cash Flow Data'!G16,0) -> -895 | F84: =IFERROR('Cash Flow Data'!H16,0) -> -767 | G84: =IFERROR('Cash Flow Data'!I16,0) -> -862 | H84: =IFERROR('Cash Flow Data'!J16,0) -> -4163 | I84: =IFERROR('Cash Flow Data'!K16,0) -> -1228 | J84: =IFERROR('Cash Flow Data'!L16,0) -> -1192 | ... L84: =IFERROR('Cash Flow Data'!N16,0) -> -1275
B85: Fixed assets sold | C85: =IFERROR('Cash Flow Data'!E17,0) -> 99 | D85: =IFERROR('Cash Flow Data'!F17,0) -> 176 | E85: =IFERROR('Cash Flow Data'!G17,0) -> 32 | F85: =IFERROR('Cash Flow Data'!H17,0) -> 13 | G85: =IFERROR('Cash Flow Data'!I17,0) -> 52 | H85: =IFERROR('Cash Flow Data'!J17,0) -> 97 | I85: =IFERROR('Cash Flow Data'!K17,0) -> 175 | J85: =IFERROR('Cash Flow Data'!L17,0) -> 181 | ... L85: =IFERROR('Cash Flow Data'!N17,0) -> 13
B86: Investments purchased | C86: =IFERROR('Cash Flow Data'!E18,0) -> -20666 | D86: =IFERROR('Cash Flow Data'!F18,0) -> -31214 | E86: =IFERROR('Cash Flow Data'!G18,0) -> -51855 | F86: =IFERROR('Cash Flow Data'!H18,0) -> -74365 | G86: =IFERROR('Cash Flow Data'!I18,0) -> -36090 | H86: =IFERROR('Cash Flow Data'!J18,0) -> -39920 | I86: =IFERROR('Cash Flow Data'!K18,0) -> -48522 | J86: =IFERROR('Cash Flow Data'!L18,0) -> -22649 | ... L86: =IFERROR('Cash Flow Data'!N18,0) -> -22957
B87: Investments sold | C87: =IFERROR('Cash Flow Data'!E19,0) -> 20937 | D87: =IFERROR('Cash Flow Data'!F19,0) -> 30083 | E87: =IFERROR('Cash Flow Data'!G19,0) -> 52897 | F87: =IFERROR('Cash Flow Data'!H19,0) -> 74691 | G87: =IFERROR('Cash Flow Data'!I19,0) -> 37690 | H87: =IFERROR('Cash Flow Data'!J19,0) -> 38486 | I87: =IFERROR('Cash Flow Data'!K19,0) -> 47786 | J87: =IFERROR('Cash Flow Data'!L19,0) -> 23462 | ... L87: =IFERROR('Cash Flow Data'!N19,0) -> 23987
B88: Interest received | C88: =IFERROR('Cash Flow Data'!E20,0) -> 315 | D88: =IFERROR('Cash Flow Data'!F20,0) -> 264 | E88: =IFERROR('Cash Flow Data'!G20,0) -> 297 | F88: =IFERROR('Cash Flow Data'!H20,0) -> 289 | G88: =IFERROR('Cash Flow Data'!I20,0) -> 351 | H88: =IFERROR('Cash Flow Data'!J20,0) -> 277 | I88: =IFERROR('Cash Flow Data'!K20,0) -> 161 | J88: =IFERROR('Cash Flow Data'!L20,0) -> 259 | ... L88: =IFERROR('Cash Flow Data'!N20,0) -> 835
B89: Dividends received | C89: =IFERROR('Cash Flow Data'!E21,0) -> 33 | D89: =IFERROR('Cash Flow Data'!F21,0) -> 14 | E89: =IFERROR('Cash Flow Data'!G21,0) -> 0 | F89: =IFERROR('Cash Flow Data'!H21,0) -> 1 | G89: =IFERROR('Cash Flow Data'!I21,0) -> 1 | H89: =IFERROR('Cash Flow Data'!J21,0) -> 1 | I89: =IFERROR('Cash Flow Data'!K21,0) -> 1 | J89: =IFERROR('Cash Flow Data'!L21,0) -> 2 | ... L89: =IFERROR('Cash Flow Data'!N21,0) -> 0
B90: Invest in subsidiaries | C90: =IFERROR('Cash Flow Data'!E22,0) -> 0 | D90: =IFERROR('Cash Flow Data'!F22,0) -> 0 | E90: =IFERROR('Cash Flow Data'!G22,0) -> 0 | F90: =IFERROR('Cash Flow Data'!H22,0) -> 0 | G90: =IFERROR('Cash Flow Data'!I22,0) -> 0 | H90: =IFERROR('Cash Flow Data'!J22,0) -> 0 | I90: =IFERROR('Cash Flow Data'!K22,0) -> 0 | J90: =IFERROR('Cash Flow Data'!L22,0) -> 0 | ... L90: =IFERROR('Cash Flow Data'!N22,0) -> 0
B91: Loans to subsidiaries | C91: =IFERROR('Cash Flow Data'!E23,0) -> 0 | D91: =IFERROR('Cash Flow Data'!F23,0) -> 0 | E91: =IFERROR('Cash Flow Data'!G23,0) -> 0 | F91: =IFERROR('Cash Flow Data'!H23,0) -> 0 | G91: =IFERROR('Cash Flow Data'!I23,0) -> 0 | H91: =IFERROR('Cash Flow Data'!J23,0) -> 0 | I91: =IFERROR('Cash Flow Data'!K23,0) -> 0 | J91: =IFERROR('Cash Flow Data'!L23,0) -> 0 | ... L91: =IFERROR('Cash Flow Data'!N23,0) -> 0
B92: Redemp n Canc of Shares | C92: =IFERROR('Cash Flow Data'!E24,0) -> 161 | D92: =IFERROR('Cash Flow Data'!F24,0) -> 20 | E92: =IFERROR('Cash Flow Data'!G24,0) -> 73 | F92: =IFERROR('Cash Flow Data'!H24,0) -> 0 | G92: =IFERROR('Cash Flow Data'!I24,0) -> 0 | H92: =IFERROR('Cash Flow Data'!J24,0) -> 0 | I92: =IFERROR('Cash Flow Data'!K24,0) -> 0 | J92: =IFERROR('Cash Flow Data'!L24,0) -> 0 | ... L92: =IFERROR('Cash Flow Data'!N24,0) -> 0
B93: Acquisition of companies | C93: =IFERROR('Cash Flow Data'!E25,0) -> 0 | D93: =IFERROR('Cash Flow Data'!F25,0) -> 0 | E93: =IFERROR('Cash Flow Data'!G25,0) -> 0 | F93: =IFERROR('Cash Flow Data'!H25,0) -> 0 | G93: =IFERROR('Cash Flow Data'!I25,0) -> 0 | H93: =IFERROR('Cash Flow Data'!J25,0) -> 0 | I93: =IFERROR('Cash Flow Data'!K25,0) -> 0 | J93: =IFERROR('Cash Flow Data'!L25,0) -> -334 | ... L93: =IFERROR('Cash Flow Data'!N25,0) -> 0
B94: Other investing items | C94: =IFERROR('Cash Flow Data'!E26,0) -> -351 | D94: =IFERROR('Cash Flow Data'!F26,0) -> 597 | E94: =IFERROR('Cash Flow Data'!G26,0) -> -1612 | F94: =IFERROR('Cash Flow Data'!H26,0) -> -300 | G94: =IFERROR('Cash Flow Data'!I26,0) -> 649 | H94: =IFERROR('Cash Flow Data'!J26,0) -> 3994 | I94: =IFERROR('Cash Flow Data'!K26,0) -> -101 | J94: =IFERROR('Cash Flow Data'!L26,0) -> -1213 | ... L94: =IFERROR('Cash Flow Data'!N26,0) -> 5870
B95: Cash From Investing Activities | C95: =IFERROR(SUM(C84:C94),0) -> -282 | D95: =IFERROR(SUM(D84:D94),0) -> -1173 | E95: =IFERROR(SUM(E84:E94),0) -> -1063 | F95: =IFERROR(SUM(F84:F94),0) -> -438 | G95: =IFERROR(SUM(G84:G94),0) -> 1791 | H95: =IFERROR(SUM(H84:H94),0) -> -1228 | I95: =IFERROR(SUM(I84:I94),0) -> -1728 | J95: =IFERROR(SUM(J84:J94),0) -> -1484 | ... L95: =IFERROR(SUM(L84:L94),0) -> 6473
B97: Financing Activties
B98: Proceeds from shares | C98: =IFERROR('Cash Flow Data'!E28,0) -> 0 | D98: =IFERROR('Cash Flow Data'!F28,0) -> 0 | E98: =IFERROR('Cash Flow Data'!G28,0) -> 0 | F98: =IFERROR('Cash Flow Data'!H28,0) -> 0 | G98: =IFERROR('Cash Flow Data'!I28,0) -> 0 | H98: =IFERROR('Cash Flow Data'!J28,0) -> 0 | I98: =IFERROR('Cash Flow Data'!K28,0) -> 0 | J98: =IFERROR('Cash Flow Data'!L28,0) -> 0 | ... L98: =IFERROR('Cash Flow Data'!N28,0) -> 0
B99: Proceeds from borrowings | C99: =IFERROR('Cash Flow Data'!E29,0) -> 177 | D99: =IFERROR('Cash Flow Data'!F29,0) -> 460 | E99: =IFERROR('Cash Flow Data'!G29,0) -> 0 | F99: =IFERROR('Cash Flow Data'!H29,0) -> 99 | G99: =IFERROR('Cash Flow Data'!I29,0) -> 0 | H99: =IFERROR('Cash Flow Data'!J29,0) -> 188 | I99: =IFERROR('Cash Flow Data'!K29,0) -> 55 | J99: =IFERROR('Cash Flow Data'!L29,0) -> 286 | ... L99: =IFERROR('Cash Flow Data'!N29,0) -> 0
B100: Repayment of borrowings | C100: =IFERROR('Cash Flow Data'!E30,0) -> 0 | D100: =IFERROR('Cash Flow Data'!F30,0) -> -360 | E100: =IFERROR('Cash Flow Data'!G30,0) -> -277 | F100: =IFERROR('Cash Flow Data'!H30,0) -> 0 | G100: =IFERROR('Cash Flow Data'!I30,0) -> -99 | H100: =IFERROR('Cash Flow Data'!J30,0) -> -188 | I100: =IFERROR('Cash Flow Data'!K30,0) -> -55 | J100: =IFERROR('Cash Flow Data'!L30,0) -> -208 | ... L100: =IFERROR('Cash Flow Data'!N30,0) -> 0
B101: Interest paid fin | C101: =IFERROR('Cash Flow Data'!E31,0) -> -2 | D101: =IFERROR('Cash Flow Data'!F31,0) -> -14 | E101: =IFERROR('Cash Flow Data'!G31,0) -> -6 | F101: =IFERROR('Cash Flow Data'!H31,0) -> -7 | G101: =IFERROR('Cash Flow Data'!I31,0) -> -90 | H101: =IFERROR('Cash Flow Data'!J31,0) -> -92 | I101: =IFERROR('Cash Flow Data'!K31,0) -> -82 | J101: =IFERROR('Cash Flow Data'!L31,0) -> -88 | ... L101: =IFERROR('Cash Flow Data'!N31,0) -> -130
B102: Dividends paid | C102: =IFERROR('Cash Flow Data'!E32,0) -> -3354 | D102: =IFERROR('Cash Flow Data'!F32,0) -> -3572 | E102: =IFERROR('Cash Flow Data'!G32,0) -> -3911 | F102: =IFERROR('Cash Flow Data'!H32,0) -> -4554 | G102: =IFERROR('Cash Flow Data'!I32,0) -> -5196 | H102: =IFERROR('Cash Flow Data'!J32,0) -> -8811 | I102: =IFERROR('Cash Flow Data'!K32,0) -> -7526 | J102: =IFERROR('Cash Flow Data'!L32,0) -> -8474 | ... L102: =IFERROR('Cash Flow Data'!N32,0) -> -12473
B103: Financial liabilities | C103: =IFERROR('Cash Flow Data'!E33,0) -> 0 | D103: =IFERROR('Cash Flow Data'!F33,0) -> 0 | E103: =IFERROR('Cash Flow Data'!G33,0) -> 0 | F103: =IFERROR('Cash Flow Data'!H33,0) -> 0 | G103: =IFERROR('Cash Flow Data'!I33,0) -> -373 | H103: =IFERROR('Cash Flow Data'!J33,0) -> -406 | I103: =IFERROR('Cash Flow Data'!K33,0) -> -407 | J103: =IFERROR('Cash Flow Data'!L33,0) -> -467 | ... L103: =IFERROR('Cash Flow Data'!N33,0) -> -498
B104: Other financing items | C104: =IFERROR('Cash Flow Data'!E34,0) -> -685 | D104: =IFERROR('Cash Flow Data'!F34,0) -> -728 | E104: =IFERROR('Cash Flow Data'!G34,0) -> -781 | F104: =IFERROR('Cash Flow Data'!H34,0) -> -928 | G104: =IFERROR('Cash Flow Data'!I34,0) -> -1061 | H104: =IFERROR('Cash Flow Data'!J34,0) -> 0 | I104: =IFERROR('Cash Flow Data'!K34,0) -> 0 | J104: =IFERROR('Cash Flow Data'!L34,0) -> -2 | ... L104: =IFERROR('Cash Flow Data'!N34,0) -> 0
B105: Cash From Financing Activities | C105: =IFERROR(SUM(C98:C104),0) -> -3864 | D105: =IFERROR(SUM(D98:D104),0) -> -4214 | E105: =IFERROR(SUM(E98:E104),0) -> -4975 | F105: =IFERROR(SUM(F98:F104),0) -> -5390 | G105: =IFERROR(SUM(G98:G104),0) -> -6819 | H105: =IFERROR(SUM(H98:H104),0) -> -9309 | I105: =IFERROR(SUM(I98:I104),0) -> -8015 | J105: =IFERROR(SUM(J98:J104),0) -> -8953 | ... L105: =IFERROR(SUM(L98:L104),0) -> -13101
B107: Net Cash Flow | C107: =IFERROR(SUM(C81+C95+C105),0) -> 25 | D107: =IFERROR(SUM(D81+D95+D105),0) -> -202 | E107: =IFERROR(SUM(E81+E95+E105),0) -> 21 | F107: =IFERROR(SUM(F81+F95+F105),0) -> -28 | G107: =IFERROR(SUM(G81+G95+G105),0) -> 2595 | H107: =IFERROR(SUM(H81+H95+H105),0) -> -1374 | I107: =IFERROR(SUM(I81+I95+I105),0) -> -695 | J107: =IFERROR(SUM(J81+J95+J105),0) -> -446 | ... L107: =IFERROR(SUM(L81+L95+L105),0) -> 5258

Sheet Forecasting 
B2: ='Data Sheet'!$B$1&" - "&'Data Sheet'!A17&" Forecasting" -> HINDUSTAN UNILEVER LTD - Sales Forecasting | G2: ='Data Sheet'!$B$1&" - "&HistoricalFS!B18&" Forecasting" -> HINDUSTAN UNILEVER LTD - EBITDA Forecasting | L2: ='Data Sheet'!$B$1&" - "&HistoricalFS!B38&" Forecasting" -> HINDUSTAN UNILEVER LTD - Earnings per Share Forecasting
B3: Year Weight | C3: Year | D3: Sales | E3: Sales Growth | G3: Year Weight | H3: Year | I3: EBITDA | J3: EBITDA Growth | L3: Year Weight | M3: Year | N3: EPS | O3: EPS Growth
B4: 1 | C4: ='Data Sheet'!$B$16 -> 42460 | D4: {=TRANSPOSE('Data Sheet'!B17:K17)} -> 32186 | G4: 1 | H4: ='Data Sheet'!$B$16 -> 42460 | I4: {=TRANSPOSE('Data Sheet'!B33:K33)} -> 6396 | L4: 1 | M4: ='Data Sheet'!$B$16 -> 42460 | N4: {=TRANSPOSE(HistoricalFS!C38:L38)} -> 16.937012
B5: =B4+1 -> 2 | C5: =C4+365 -> 42825 | D5: 33162 | E5: =D5/D4-1 -> 0.030323743 | G5: =G4+1 -> 2 | H5: =H4+365 -> 42825 | I5: 6920 | J5: =I5/I4-1 -> 0.081926204 | L5: =L4+1 -> 2 | M5: =M4+365 -> 42825 | N5: 17.945756 | O5: =N5/N4-1 -> 0.059558573
B6: =B5+1 -> 3 | C6: =C5+365 -> 43190 | D6: 35545 | E6: =D6/D5-1 -> 0.071859357 | G6: =G5+1 -> 3 | H6: =H5+365 -> 43190 | I6: 7839 | J6: =I6/I5-1 -> 0.13280347 | L6: =L5+1 -> 3 | M6: =M5+365 -> 43190 | N6: 22.517903 | O6: =N6/N5-1 -> 0.25477591
B7: =B6+1 -> 4 | C7: =C6+365 -> 43555 | D7: 39310 | E7: =D7/D6-1 -> 0.10592207 | G7: =G6+1 -> 4 | H7: =H6+365 -> 43555 | I7: 9196 | J7: =I7/I6-1 -> 0.17310881 | L7: =L6+1 -> 4 | M7: =M6+365 -> 43555 | N7: 26.507137 | O7: =N7/N6-1 -> 0.17715836
B8: =B7+1 -> 5 | C8: =C7+365 -> 43920 | D8: 39783 | E8: =D8/D7-1 -> 0.012032562 | G8: =G7+1 -> 5 | H8: =H7+365 -> 43920 | I8: 10277 | J8: =I8/I7-1 -> 0.11755111 | L8: =L7+1 -> 5 | M8: =M7+365 -> 43920 | N8: 29.249815 | O8: =N8/N7-1 -> 0.10346941
B9: =B8+1 -> 6 | C9: =C8+365 -> 44285 | D9: 47028 | E9: =D9/D8-1 -> 0.18211296 | G9: =G8+1 -> 6 | H9: =H8+365 -> 44285 | I9: 11792 | J9: =I9/I8-1 -> 0.14741656 | L9: =L8+1 -> 6 | M9: =M8+365 -> 44285 | N9: 33.320565 | O9: =N9/N8-1 -> 0.13917182
B10: =B9+1 -> 7 | C10: =C9+365 -> 44650 | D10: 52446 | E10: =D10/D9-1 -> 0.11520796 | G10: =G9+1 -> 7 | H10: =H9+365 -> 44650 | I10: 13063 | J10: =I10/I9-1 -> 0.10778494 | L10: =L9+1 -> 7 | M10: =M9+365 -> 44650 | N10: 36.912666 | O10: =N10/N9-1 -> 0.10780432
B11: =B10+1 -> 8 | C11: =C10+365 -> 45015 | D11: 60580 | E11: =D11/D10-1 -> 0.15509286 | G11: =G10+1 -> 8 | H11: =H10+365 -> 45015 | I11: 14572 | J11: =I11/I10-1 -> 0.11551711 | L11: =L10+1 -> 8 | M11: =M10+365 -> 45015 | N11: 41.262343 | O11: =N11/N10-1 -> 0.11783697
B12: =B11+1 -> 9 | C12: =C11+365 -> 45380 | D12: 61896 | E12: =D12/D11-1 -> 0.021723341 | G12: =G11+1 -> 9 | H12: =H11+365 -> 45380 | I12: 15471 | J12: =I12/I11-1 -> 0.061693659 | L12: =L11+1 -> 9 | M12: =M11+365 -> 45380 | N12: 40.283453 | O12: =N12/N11-1 -> -0.023723569
B13: =B12+1 -> 10 | C13: =C12+365 -> 45745 | D13: 63121 | E13: =D13/D12-1 -> 0.019791263 | G13: =G12+1 -> 10 | H13: =H12+365 -> 45745 | I13: 16143 | J13: =I13/I12-1 -> 0.043436106 | L13: =L12+1 -> 10 | M13: =M12+365 -> 45745 | N13: 39.789751 | O13: =N13/N12-1 -> -0.012255679
B14: =B13+1 -> 11 | C14: =C13+365 -> 46110 | D14: =FORECAST(B14,$D$4:$D$13,$B$4:$B$13) -> 68218.4 | E14: =D14/D13-1 -> 0.080756008 | G14: =G13+1 -> 11 | H14: =H13+365 -> 46110 | I14: =FORECAST(G14,$I$4:$I$13,$G$4:$G$13) -> 17645.6 | J14: =I14/I13-1 -> 0.093080592 | L14: =L13+1 -> 11 | M14: =M13+365 -> 46110 | N14: =FORECAST(L14,$N$4:$N$13,$L$4:$L$13) -> 46.840909 | O14: =N14/N13-1 -> 0.17721039
B15: =B14+1 -> 12 | C15: =C14+365 -> 46475 | D15: =FORECAST(B15,$D$4:$D$13,$B$4:$B$13) -> 72166.164 | E15: =D15/D14-1 -> 0.057869484 | G15: =G14+1 -> 12 | H15: =H14+365 -> 46475 | I15: =FORECAST(G15,$I$4:$I$13,$G$4:$G$13) -> 18823.545 | J15: =I15/I14-1 -> 0.066755761 | L15: =L14+1 -> 12 | M15: =M14+365 -> 46475 | N15: =FORECAST(L15,$N$4:$N$13,$L$4:$L$13) -> 49.816958 | O15: =N15/N14-1 -> 0.063535251
B16: =B15+1 -> 13 | C16: =C15+365 -> 46840 | D16: =FORECAST(B16,$D$4:$D$13,$B$4:$B$13) -> 76113.927 | E16: =D16/D15-1 -> 0.054703804 | G16: =G15+1 -> 13 | H16: =H15+365 -> 46840 | I16: =FORECAST(G16,$I$4:$I$13,$G$4:$G$13) -> 20001.491 | J16: =I16/I15-1 -> 0.062578299 | L16: =L15+1 -> 13 | M16: =M15+365 -> 46840 | N16: =FORECAST(L16,$N$4:$N$13,$L$4:$L$13) -> 52.793007 | O16: =N16/N15-1 -> 0.059739675
B17: =B16+1 -> 14 | C17: =C16+365 -> 47205 | D17: =FORECAST(B17,$D$4:$D$13,$B$4:$B$13) -> 80061.691 | E17: =D17/D16-1 -> 0.051866508 | G17: =G16+1 -> 14 | H17: =H16+365 -> 47205 | I17: =FORECAST(G17,$I$4:$I$13,$G$4:$G$13) -> 21179.436 | J17: =I17/I16-1 -> 0.058892883 | L17: =L16+1 -> 14 | M17: =M16+365 -> 47205 | N17: =FORECAST(L17,$N$4:$N$13,$L$4:$L$13) -> 55.769056 | O17: =N17/N16-1 -> 0.056372029
B18: =B17+1 -> 15 | C18: =C17+365 -> 47570 | D18: =FORECAST(B18,$D$4:$D$13,$B$4:$B$13) -> 84009.455 | E18: =D18/D17-1 -> 0.049309021 | G18: =G17+1 -> 15 | H18: =H17+365 -> 47570 | I18: =FORECAST(G18,$I$4:$I$13,$G$4:$G$13) -> 22357.382 | J18: =I18/I17-1 -> 0.055617413 | L18: =L17+1 -> 15 | M18: =M17+365 -> 47570 | N18: =FORECAST(L18,$N$4:$N$13,$L$4:$L$13) -> 58.745105 | O18: =N18/N17-1 -> 0.053363803

Sheet Ratio Analysis 
B2: ="Ratio Analysis - "&'Data Sheet'!B1 -> Ratio Analysis - HINDUSTAN UNILEVER LTD
B3: Years | C3: ='Data Sheet'!B16 -> 42460 | D3: ='Data Sheet'!C16 -> 42825 | E3: ='Data Sheet'!D16 -> 43190 | F3: ='Data Sheet'!E16 -> 43555 | G3: ='Data Sheet'!F16 -> 43921 | H3: ='Data Sheet'!G16 -> 44286 | I3: ='Data Sheet'!H16 -> 44651 | J3: ='Data Sheet'!I16 -> 45016 | ... L3: ='Data Sheet'!K16 -> 45747 | M3: Trend | N3: Mean | O3: Median
B5: SalesGrowth | D5: =HistoricalFS!D7 -> 0.030323743 | E5: =HistoricalFS!E7 -> 0.071859357 | F5: =HistoricalFS!F7 -> 0.10592207 | G5: =HistoricalFS!G7 -> 0.012032562 | H5: =HistoricalFS!H7 -> 0.18211296 | I5: =HistoricalFS!I7 -> 0.11520796 | J5: =HistoricalFS!J7 -> 0.15509286 | K5: =HistoricalFS!K7 -> 0.021723341 | L5: =HistoricalFS!L7 -> 0.019791263 | N5: =IFERROR(AVERAGE(D5:L5),0) -> 0.07934068 | O5: =IFERROR(MEDIAN(C5:L5),0) -> 0.071859357
B6: EBITDA Growth | D6: =IFERROR(HistoricalFS!D18/HistoricalFS!C18-1,0) -> 0.07072758 | E6: =IFERROR(HistoricalFS!E18/HistoricalFS!D18-1,0) -> 0.18505057 | F6: =IFERROR(HistoricalFS!F18/HistoricalFS!E18-1,0) -> 0.18415789 | G6: =IFERROR(HistoricalFS!G18/HistoricalFS!F18-1,0) -> 0.11047297 | H6: =IFERROR(HistoricalFS!H18/HistoricalFS!G18-1,0) -> 0.17898793 | I6: =IFERROR(HistoricalFS!I18/HistoricalFS!H18-1,0) -> 0.10588336 | J6: =IFERROR(HistoricalFS!J18/HistoricalFS!I18-1,0) -> 0.10033445 | K6: =IFERROR(HistoricalFS!K18/HistoricalFS!J18-1,0) -> 0.036191419 | L6: =IFERROR(HistoricalFS!L18/HistoricalFS!K18-1,0) -> 0.012552016 | N6: =IFERROR(AVERAGE(D6:L6),0) -> 0.10937313 | O6: =IFERROR(MEDIAN(C6:L6),0) -> 0.10588336
B7: EBIT Growth | D7: =IFERROR(HistoricalFS!D27/HistoricalFS!C27-1,0) -> 0.057942238 | E7: =IFERROR(HistoricalFS!E27/HistoricalFS!D27-1,0) -> 0.18631633 | F7: =IFERROR(HistoricalFS!F27/HistoricalFS!E27-1,0) -> 0.19114051 | G7: =IFERROR(HistoricalFS!G27/HistoricalFS!F27-1,0) -> 0.055421396 | H7: =IFERROR(HistoricalFS!H27/HistoricalFS!G27-1,0) -> 0.19379934 | I7: =IFERROR(HistoricalFS!I27/HistoricalFS!H27-1,0) -> 0.11739339 | J7: =IFERROR(HistoricalFS!J27/HistoricalFS!I27-1,0) -> 0.10600343 | K7: =IFERROR(HistoricalFS!K27/HistoricalFS!J27-1,0) -> 0.016516749 | L7: =IFERROR(HistoricalFS!L27/HistoricalFS!K27-1,0) -> -0.0012205355 | N7: =IFERROR(AVERAGE(D7:L7),0) -> 0.10259032 | O7: =IFERROR(MEDIAN(C7:L7),0) -> 0.10600343
B8: Net Profit Growth | D8: =IFERROR(HistoricalFS!D33/HistoricalFS!C33-1,0) -> 0.059754434 | E8: =IFERROR(HistoricalFS!E33/HistoricalFS!D33-1,0) -> 0.25489186 | F8: =IFERROR(HistoricalFS!F33/HistoricalFS!E33-1,0) -> 0.17726713 | G8: =IFERROR(HistoricalFS!G33/HistoricalFS!F33-1,0) -> 0.10352039 | H8: =IFERROR(HistoricalFS!H33/HistoricalFS!G33-1,0) -> 0.23641819 | I8: =IFERROR(HistoricalFS!I33/HistoricalFS!H33-1,0) -> 0.10780432 | J8: =IFERROR(HistoricalFS!J33/HistoricalFS!I33-1,0) -> 0.11783697 | K8: =IFERROR(HistoricalFS!K33/HistoricalFS!J33-1,0) -> -0.023723569 | L8: =IFERROR(HistoricalFS!L33/HistoricalFS!K33-1,0) -> -0.012255679 | N8: =IFERROR(AVERAGE(D8:L8),0) -> 0.11350156 | O8: =IFERROR(MEDIAN(C8:L8),0) -> 0.10780432
B9: Dividend Growth | D9: =IFERROR(HistoricalFS!D41/HistoricalFS!C41-1,0) -> 0.062303632 | E9: =IFERROR(HistoricalFS!E41/HistoricalFS!D41-1,0) -> 0.17636188 | F9: =IFERROR(HistoricalFS!F41/HistoricalFS!E41-1,0) -> 0.099898369 | G9: =IFERROR(HistoricalFS!G41/HistoricalFS!F41-1,0) -> 0.13631114 | H9: =IFERROR(HistoricalFS!H41/HistoricalFS!G41-1,0) -> 0.6238764 | I9: =IFERROR(HistoricalFS!I41/HistoricalFS!H41-1,0) -> -0.16049383 | J9: =IFERROR(HistoricalFS!J41/HistoricalFS!I41-1,0) -> 0.14705882 | K9: =IFERROR(HistoricalFS!K41/HistoricalFS!J41-1,0) -> 0.076923077 | L9: =IFERROR(HistoricalFS!L41/HistoricalFS!K41-1,0) -> 0.26190476 | N9: =IFERROR(AVERAGE(D9:L9),0) -> 0.15823825 | O9: =IFERROR(MEDIAN(C9:L9),0) -> 0.13631114
B11: Gross Margin | C11: =HistoricalFS!C13 -> 0.43385323 | D11: =HistoricalFS!D13 -> 0.43685544 | E11: =HistoricalFS!E13 -> 0.45663244 | F11: =HistoricalFS!F13 -> 0.46372424 | G11: =HistoricalFS!G13 -> 0.48183898 | H11: =HistoricalFS!H13 -> 0.46200136 | I11: =HistoricalFS!I13 -> 0.44579186 | J11: =HistoricalFS!J13 -> 0.41596236 | ... L11: =HistoricalFS!L13 -> 0.45297128 | N11: =IFERROR(AVERAGE(C11:L11),0) -> 0.45059612 | O11: =IFERROR(MEDIAN(C11:L11),0) -> 0.45465063
B12: EBITDA Margin | C12: =HistoricalFS!C19 -> 0.18362021 | D12: =HistoricalFS!D19 -> 0.19082082 | E12: =HistoricalFS!E19 -> 0.21097201 | F12: =HistoricalFS!F19 -> 0.22589672 | G12: =HistoricalFS!G19 -> 0.24786969 | H12: =HistoricalFS!H19 -> 0.24721443 | I12: =HistoricalFS!I19 -> 0.24514739 | J12: =HistoricalFS!J19 -> 0.23352592 | ... L12: =HistoricalFS!L19 -> 0.23515153 | N12: =IFERROR(AVERAGE(C12:L12),0) -> 0.22570515 | O12: =IFERROR(MEDIAN(C12:L12),0) -> 0.23433873
B13: EBIT Margin | C13: =IFERROR((HistoricalFS!C18-HistoricalFS!C24)/HistoricalFS!C6,0) -> 0.17265271 | D13: =IFERROR((HistoricalFS!D18-HistoricalFS!D24)/HistoricalFS!D6,0) -> 0.17779386 | E13: =IFERROR((HistoricalFS!E18-HistoricalFS!E24)/HistoricalFS!E6,0) -> 0.19634266 | F13: =IFERROR((HistoricalFS!F18-HistoricalFS!F24)/HistoricalFS!F6,0) -> 0.21152379 | G13: =IFERROR((HistoricalFS!G18-HistoricalFS!G24)/HistoricalFS!G6,0) -> 0.22268306 | H13: =IFERROR((HistoricalFS!H18-HistoricalFS!H24)/HistoricalFS!H6,0) -> 0.22437697 | I13: =IFERROR((HistoricalFS!I18-HistoricalFS!I24)/HistoricalFS!I6,0) -> 0.22434504 | J13: =IFERROR((HistoricalFS!J18-HistoricalFS!J24)/HistoricalFS!J6,0) -> 0.21475735 | ... L13: =IFERROR((HistoricalFS!L18-HistoricalFS!L24)/HistoricalFS!L6,0) -> 0.21368483 | N13: =IFERROR(AVERAGE(C13:L13),0) -> 0.20753471 | O13: =IFERROR(MEDIAN(C13:L13),0) -> 0.21422109
B14: EBT Margin | C14: =HistoricalFS!C28 -> 0.17212453 | D14: =HistoricalFS!D28 -> 0.17673844 | E14: =HistoricalFS!E28 -> 0.1956112 | F14: =HistoricalFS!F28 -> 0.2106843 | G14: =HistoricalFS!G28 -> 0.21971696 | H14: =HistoricalFS!H28 -> 0.22188909 | I14: =HistoricalFS!I28 -> 0.22232391 | J14: =HistoricalFS!J28 -> 0.21287554 | ... L14: =HistoricalFS!L28 -> 0.20742701 | N14: =IFERROR(AVERAGE(C14:L14),0) -> 0.20511817 | O14: =IFERROR(MEDIAN(C14:L14),0) -> 0.21123753
B15: Net Profit Margin | C15: =HistoricalFS!C34 -> 0.11386938 | D15: =HistoricalFS!D34 -> 0.11712201 | E15: =HistoricalFS!E34 -> 0.13712196 | F15: =HistoricalFS!F34 -> 0.14596795 | G15: =HistoricalFS!G34 -> 0.15916346 | H15: =HistoricalFS!H34 -> 0.16647529 | I15: =HistoricalFS!I34 -> 0.16537009 | J15: =HistoricalFS!J34 -> 0.16003632 | ... L15: =HistoricalFS!L34 -> 0.14811236 | N15: =IFERROR(AVERAGE(C15:L15),0) -> 0.14661566 | O15: =IFERROR(MEDIAN(C15:L15),0) -> 0.15051508
B17: SalesExpenses%Sales | C17: =HistoricalFS!C16 -> 0.25023302 | D17: =HistoricalFS!D16 -> 0.24603462 | E17: =HistoricalFS!E16 -> 0.24566043 | F17: =HistoricalFS!F16 -> 0.23782752 | G17: =HistoricalFS!G16 -> 0.23396928 | H17: =HistoricalFS!H16 -> 0.21478694 | I17: =HistoricalFS!I16 -> 0.20064447 | J17: =HistoricalFS!J16 -> 0.18243645 | ... L17: =HistoricalFS!L16 -> 0.21781974 | N17: =IFERROR(AVERAGE(C17:L17),0) -> 0.22489097 | O17: =IFERROR(MEDIAN(C17:L17),0) -> 0.22673325
B18: Depreciation%Sales | C18: =HistoricalFS!C25 -> 0.010967501 | D18: =HistoricalFS!D25 -> 0.013026959 | E18: =HistoricalFS!E25 -> 0.014629343 | F18: =HistoricalFS!F25 -> 0.014372933 | G18: =HistoricalFS!G25 -> 0.025186638 | H18: =HistoricalFS!H25 -> 0.022837459 | I18: =HistoricalFS!I25 -> 0.020802349 | J18: =HistoricalFS!J25 -> 0.01876857 | ... L18: =HistoricalFS!L25 -> 0.021466707 | N18: =IFERROR(AVERAGE(C18:L18),0) -> 0.018170432 | O18: =IFERROR(MEDIAN(C18:L18),0) -> 0.019207214
B19: OperatingIncome%Sales | C19: =C13 -> 0.17265271 | D19: =D13 -> 0.17779386 | E19: =E13 -> 0.19634266 | F19: =F13 -> 0.21152379 | G19: =G13 -> 0.22268306 | H19: =H13 -> 0.22437697 | I19: =I13 -> 0.22434504 | J19: =J13 -> 0.21475735 | ... L19: =L13 -> 0.21368483 | N19: =IFERROR(AVERAGE(C19:L19),0) -> 0.20753471 | O19: =IFERROR(MEDIAN(C19:L19),0) -> 0.21422109
B21: Return on Capital Employed | C21: =IFERROR((HistoricalFS!C18-HistoricalFS!C24)/(SUM(HistoricalFS!C47:C49)),0) -> 0.82325926 | D21: =IFERROR((HistoricalFS!D18-HistoricalFS!D24)/(SUM(HistoricalFS!D47:D49)),0) -> 0.83976642 | E21: =IFERROR((HistoricalFS!E18-HistoricalFS!E24)/(SUM(HistoricalFS!E47:E49)),0) -> 0.95852218 | F21: =IFERROR((HistoricalFS!F18-HistoricalFS!F24)/(SUM(HistoricalFS!F47:F49)),0) -> 1.0438112 | G21: =IFERROR((HistoricalFS!G18-HistoricalFS!G24)/(SUM(HistoricalFS!G47:G49)),0) -> 1.0765585 | H21: =IFERROR((HistoricalFS!H18-HistoricalFS!H24)/(SUM(HistoricalFS!H47:H49)),0) -> 0.22133658 | I21: =IFERROR((HistoricalFS!I18-HistoricalFS!I24)/(SUM(HistoricalFS!I47:I49)),0) -> 0.23483155 | J21: =IFERROR((HistoricalFS!J18-HistoricalFS!J24)/(SUM(HistoricalFS!J47:J49)),0) -> 0.25250859 | ... L21: =IFERROR((HistoricalFS!L18-HistoricalFS!L24)/(SUM(HistoricalFS!L47:L49)),0) -> 0.26421156 | N21: =IFERROR(AVERAGE(C21:L21),0) -> 0.59698815 | O21: =IFERROR(MEDIAN(C21:L21),0) -> 0.54373541
B22: Retained Earnings% | C22: =HistoricalFS!C44 -> 0.057025921 | D22: =HistoricalFS!D44 -> 0.054582904 | E22: =HistoricalFS!E44 -> 0.11366434 | F22: =HistoricalFS!F44 -> 0.17183688 | G22: =HistoricalFS!G44 -> 0.14718888 | H22: =HistoricalFS!H44 -> 0 | I22: =HistoricalFS!I44 -> 0.078750144 | J22: =HistoricalFS!J44 -> 0.054667354 | ... L22: =HistoricalFS!L44 -> 0 | N22: =IFERROR(AVERAGE(C22:L22),0) -> 0.067771642 | O22: =IFERROR(MEDIAN(C22:L22),0) -> 0.055846638
B23: Return on Equity% | C23: =IFERROR(HistoricalFS!C33/SUM(HistoricalFS!C47:C48),0) -> 0.55758406 | D23: =IFERROR(HistoricalFS!D33/SUM(HistoricalFS!D47:D48),0) -> 0.57591934 | E23: =IFERROR(HistoricalFS!E33/SUM(HistoricalFS!E47:E48),0) -> 0.66941354 | F23: =IFERROR(HistoricalFS!F33/SUM(HistoricalFS!F47:F48),0) -> 0.72937587 | G23: =IFERROR(HistoricalFS!G33/SUM(HistoricalFS!G47:G48),0) -> 0.76947381 | H23: =IFERROR(HistoricalFS!H33/SUM(HistoricalFS!H47:H48),0) -> 0.16421949 | I23: =IFERROR(HistoricalFS!I33/SUM(HistoricalFS!I47:I48),0) -> 0.17677993 | J23: =IFERROR(HistoricalFS!J33/SUM(HistoricalFS!J47:J48),0) -> 0.19272821 | ... L23: =IFERROR(HistoricalFS!L33/SUM(HistoricalFS!L47:L48),0) -> 0.18924335 | N23: =IFERROR(AVERAGE(C23:L23),0) -> 0.42095359 | O23: =IFERROR(MEDIAN(C23:L23),0) -> 0.37515613
B24: Self Sustained Growth Rate | C24: =IFERROR(C22*C23,0) -> 0.031796744 | D24: =IFERROR(D22*D23,0) -> 0.03143535 | E24: =IFERROR(E22*E23,0) -> 0.076088449 | F24: =IFERROR(F22*F23,0) -> 0.12533367 | G24: =IFERROR(G22*G23,0) -> 0.11325799 | H24: =IFERROR(H22*H23,0) -> 0 | I24: =IFERROR(I22*I23,0) -> 0.013921445 | J24: =IFERROR(J22*J23,0) -> 0.010535941 | ... L24: =IFERROR(L22*L23,0) -> 0 | N24: =IFERROR(AVERAGE(C24:L24),0) -> 0.040236959 | O24: =IFERROR(MEDIAN(C24:L24),0) -> 0.022678397
B25: Interest Coverage Ratio | C25: =IFERROR((HistoricalFS!C18-HistoricalFS!C24)/HistoricalFS!C21,0) -> 326.88235 | D25: =IFERROR((HistoricalFS!D18-HistoricalFS!D24)/HistoricalFS!D21,0) -> 168.45714 | E25: =IFERROR((HistoricalFS!E18-HistoricalFS!E24)/HistoricalFS!E21,0) -> 268.42308 | F25: =IFERROR((HistoricalFS!F18-HistoricalFS!F24)/HistoricalFS!F21,0) -> 251.9697 | G25: =IFERROR((HistoricalFS!G18-HistoricalFS!G24)/HistoricalFS!G21,0) -> 75.076271 | H25: =IFERROR((HistoricalFS!H18-HistoricalFS!H24)/HistoricalFS!H21,0) -> 90.188034 | I25: =IFERROR((HistoricalFS!I18-HistoricalFS!I24)/HistoricalFS!I21,0) -> 111 | J25: =IFERROR((HistoricalFS!J18-HistoricalFS!J24)/HistoricalFS!J21,0) -> 114.12281 | ... L25: =IFERROR((HistoricalFS!L18-HistoricalFS!L24)/HistoricalFS!L21,0) -> 34.146835 | N25: =IFERROR(AVERAGE(C25:L25),0) -> 148.05147 | O25: =IFERROR(MEDIAN(C25:L25),0) -> 112.5614
B27: Debtor Turnover Ratio | C27: =IFERROR(HistoricalFS!C6/HistoricalFS!C59,0) -> 25.463608 | D27: =IFERROR(HistoricalFS!D6/HistoricalFS!D59,0) -> 30.564055 | E27: =IFERROR(HistoricalFS!E6/HistoricalFS!E59,0) -> 27.133588 | F27: =IFERROR(HistoricalFS!F6/HistoricalFS!F59,0) -> 21.646476 | G27: =IFERROR(HistoricalFS!G6/HistoricalFS!G59,0) -> 34.624021 | H27: =IFERROR(HistoricalFS!H6/HistoricalFS!H59,0) -> 26.750853 | I27: =IFERROR(HistoricalFS!I6/HistoricalFS!I59,0) -> 23.455277 | J27: =IFERROR(HistoricalFS!J6/HistoricalFS!J59,0) -> 19.675219 | ... L27: =IFERROR(HistoricalFS!L6/HistoricalFS!L59,0) -> 16.528149 | N27: =IFERROR(AVERAGE(C27:L27),0) -> 24.64939 | O27: =IFERROR(MEDIAN(C27:L27),0) -> 24.459442
B28: Creditor Turnover Ratio | C28: =IFERROR(HistoricalFS!C6/HistoricalFS!C50,0) -> 4.0017406 | D28: =IFERROR(HistoricalFS!D6/HistoricalFS!D50,0) -> 3.8183074 | E28: =IFERROR(HistoricalFS!E6/HistoricalFS!E50,0) -> 3.3593233 | F28: =IFERROR(HistoricalFS!F6/HistoricalFS!F50,0) -> 3.6865798 | G28: =IFERROR(HistoricalFS!G6/HistoricalFS!G50,0) -> 3.3363804 | H28: =IFERROR(HistoricalFS!H6/HistoricalFS!H50,0) -> 2.2324124 | I28: =IFERROR(HistoricalFS!I6/HistoricalFS!I50,0) -> 2.5706303 | J28: =IFERROR(HistoricalFS!J6/HistoricalFS!J50,0) -> 2.8106152 | ... L28: =IFERROR(HistoricalFS!L6/HistoricalFS!L50,0) -> 2.1907125 | N28: =IFERROR(AVERAGE(C28:L28),0) -> 3.0406981 | O28: =IFERROR(MEDIAN(C28:L28),0) -> 3.0734978
B29: Inventory Turnover | C29: =IFERROR(HistoricalFS!C6/HistoricalFS!C60,0) -> 11.807043 | D29: =IFERROR(HistoricalFS!D6/HistoricalFS!D60,0) -> 13.050767 | E29: =IFERROR(HistoricalFS!E6/HistoricalFS!E60,0) -> 14.144449 | F29: =IFERROR(HistoricalFS!F6/HistoricalFS!F60,0) -> 15.27195 | G29: =IFERROR(HistoricalFS!G6/HistoricalFS!G60,0) -> 14.377665 | H29: =IFERROR(HistoricalFS!H6/HistoricalFS!H60,0) -> 13.139983 | I29: =IFERROR(HistoricalFS!I6/HistoricalFS!I60,0) -> 12.804199 | J29: =IFERROR(HistoricalFS!J6/HistoricalFS!J60,0) -> 14.250765 | ... L29: =IFERROR(HistoricalFS!L6/HistoricalFS!L60,0) -> 14.296942 | N29: =IFERROR(AVERAGE(C29:L29),0) -> 13.853312 | O29: =IFERROR(MEDIAN(C29:L29),0) -> 14.197607
B30: Fixed Asset Turnover | C30: =IFERROR(HistoricalFS!C6/HistoricalFS!C53,0) -> 9.8790669 | D30: =IFERROR(HistoricalFS!D6/HistoricalFS!D53,0) -> 7.5044128 | E30: =IFERROR(HistoricalFS!E6/HistoricalFS!E53,0) -> 7.8500442 | F30: =IFERROR(HistoricalFS!F6/HistoricalFS!F53,0) -> 8.3372216 | G30: =IFERROR(HistoricalFS!G6/HistoricalFS!G53,0) -> 7.2609965 | H30: =IFERROR(HistoricalFS!H6/HistoricalFS!H53,0) -> 0.91417686 | I30: =IFERROR(HistoricalFS!I6/HistoricalFS!I53,0) -> 1.0189031 | J30: =IFERROR(HistoricalFS!J6/HistoricalFS!J53,0) -> 1.1500057 | ... L30: =IFERROR(HistoricalFS!L6/HistoricalFS!L53,0) -> 1.1617006 | N30: =IFERROR(AVERAGE(C30:L30),0) -> 4.622821 | O30: =IFERROR(MEDIAN(C30:L30),0) -> 4.2113485
B31: Capital Turnover Ratio | C31: =IFERROR(HistoricalFS!C6/SUM(HistoricalFS!C47:C48),0) -> 4.8966986 | D31: =IFERROR(HistoricalFS!D6/SUM(HistoricalFS!D47:D48),0) -> 4.9172598 | E31: =IFERROR(HistoricalFS!E6/SUM(HistoricalFS!E47:E48),0) -> 4.8818844 | F31: =IFERROR(HistoricalFS!F6/SUM(HistoricalFS!F47:F48),0) -> 4.9968222 | G31: =IFERROR(HistoricalFS!G6/SUM(HistoricalFS!G47:G48),0) -> 4.8344878 | H31: =IFERROR(HistoricalFS!H6/SUM(HistoricalFS!H47:H48),0) -> 0.98644964 | I31: =IFERROR(HistoricalFS!I6/SUM(HistoricalFS!I47:I48),0) -> 1.0689957 | J31: =IFERROR(HistoricalFS!J6/SUM(HistoricalFS!J47:J48),0) -> 1.204278 | ... L31: =IFERROR(HistoricalFS!L6/SUM(HistoricalFS!L47:L48),0) -> 1.2777013 | N31: =IFERROR(AVERAGE(C31:L31),0) -> 3.0273059 | O31: =IFERROR(MEDIAN(C31:L31),0) -> 3.0560945
B33: Debtor Days | C33: =IFERROR(365/C27,0) -> 14.334183 | D33: =IFERROR(365/D27,0) -> 11.942133 | E33: =IFERROR(365/E27,0) -> 13.451962 | F33: =IFERROR(365/F27,0) -> 16.861867 | G33: =IFERROR(365/G27,0) -> 10.541814 | H33: =IFERROR(365/H27,0) -> 13.644425 | I33: =IFERROR(365/I27,0) -> 15.56153 | J33: =IFERROR(365/J27,0) -> 18.551255 | ... L33: =IFERROR(365/L27,0) -> 22.083538 | N33: =IFERROR(AVERAGE(C33:L33),0) -> 15.464598 | O33: =IFERROR(MEDIAN(C33:L33),0) -> 14.947856
B34: Payable Days | C34: =IFERROR(365/C28,0) -> 91.210309 | D34: =IFERROR(365/D28,0) -> 95.592093 | E34: =IFERROR(365/E28,0) -> 108.65283 | F34: =IFERROR(365/F28,0) -> 99.007759 | G34: =IFERROR(365/G28,0) -> 109.39999 | H34: =IFERROR(365/H28,0) -> 163.50026 | I34: =IFERROR(365/I28,0) -> 141.98852 | J34: =IFERROR(365/J28,0) -> 129.86481 | ... L34: =IFERROR(365/L28,0) -> 166.61246 | N34: =IFERROR(AVERAGE(C34:L34),0) -> 125.78947 | O34: =IFERROR(MEDIAN(C34:L34),0) -> 119.6324
B35: Inventory Days | C35: =IFERROR(365/C29,0) -> 30.913751 | D35: =IFERROR(365/D29,0) -> 27.967704 | E35: =IFERROR(365/E29,0) -> 25.805177 | F35: =IFERROR(365/F29,0) -> 23.900025 | G35: =IFERROR(365/G29,0) -> 25.386597 | H35: =IFERROR(365/H29,0) -> 27.777813 | I35: =IFERROR(365/I29,0) -> 28.506273 | J35: =IFERROR(365/J29,0) -> 25.612661 | ... L35: =IFERROR(365/L29,0) -> 25.529935 | N35: =IFERROR(AVERAGE(C35:L35),0) -> 26.511762 | O35: =IFERROR(MEDIAN(C35:L35),0) -> 25.708919
B36: Cash Conversion Cycle (in days) | C36: =IFERROR(SUM(C33,C35)-C34,0) -> -45.962375 | D36: =IFERROR(SUM(D33,D35)-D34,0) -> -55.682257 | E36: =IFERROR(SUM(E33,E35)-E34,0) -> -69.395696 | F36: =IFERROR(SUM(F33,F35)-F34,0) -> -58.245866 | G36: =IFERROR(SUM(G33,G35)-G34,0) -> -73.471583 | H36: =IFERROR(SUM(H33,H35)-H34,0) -> -122.07802 | I36: =IFERROR(SUM(I33,I35)-I34,0) -> -97.920718 | J36: =IFERROR(SUM(J33,J35)-J34,0) -> -85.700891 | ... L36: =IFERROR(SUM(L33,L35)-L34,0) -> -118.99899 | N36: =IFERROR(AVERAGE(C36:L36),0) -> -83.813107 | O36: =IFERROR(MEDIAN(C36:L36),0) -> -79.586237
B38: CFO/Sales | C38: =IFERROR(HistoricalFS!C81/HistoricalFS!C6,0) -> 0.12959051 | D38: =IFERROR(HistoricalFS!D81/HistoricalFS!D6,0) -> 0.15635366 | E38: =IFERROR(HistoricalFS!E81/HistoricalFS!E6,0) -> 0.17045998 | F38: =IFERROR(HistoricalFS!F81/HistoricalFS!F6,0) -> 0.14754515 | G38: =IFERROR(HistoricalFS!G81/HistoricalFS!G6,0) -> 0.19161451 | H38: =IFERROR(HistoricalFS!H81/HistoricalFS!H6,0) -> 0.19484137 | I38: =IFERROR(HistoricalFS!I81/HistoricalFS!I6,0) -> 0.17252031 | J38: =IFERROR(HistoricalFS!J81/HistoricalFS!J6,0) -> 0.16492242 | ... L38: =IFERROR(HistoricalFS!L81/HistoricalFS!L6,0) -> 0.188305 | N38: =IFERROR(AVERAGE(C38:L38),0) -> 0.17660721 | O38: =IFERROR(MEDIAN(C38:L38),0) -> 0.17149014
B39: CFO/Total Assets | C39: =IFERROR(HistoricalFS!C81/HistoricalFS!C64,0) -> 0.28195768 | D39: =IFERROR(HistoricalFS!D81/HistoricalFS!D64,0) -> 0.33012861 | E39: =IFERROR(HistoricalFS!E81/HistoricalFS!E64,0) -> 0.33921173 | F39: =IFERROR(HistoricalFS!F81/HistoricalFS!F64,0) -> 0.31134253 | G39: =IFERROR(HistoricalFS!G81/HistoricalFS!G64,0) -> 0.37825634 | H39: =IFERROR(HistoricalFS!H81/HistoricalFS!H64,0) -> 0.13329939 | I39: =IFERROR(HistoricalFS!I81/HistoricalFS!I64,0) -> 0.1283295 | J39: =IFERROR(HistoricalFS!J81/HistoricalFS!J64,0) -> 0.1367188 | ... L39: =IFERROR(HistoricalFS!L81/HistoricalFS!L64,0) -> 0.14882987 | N39: =IFERROR(AVERAGE(C39:L39),0) -> 0.23851594 | O39: =IFERROR(MEDIAN(C39:L39),0) -> 0.23952131
B40: CFO/Total Debt | C40: =IFERROR(HistoricalFS!C81/HistoricalFS!C49,0) -> 23.564972 | D40: =IFERROR(HistoricalFS!D81/HistoricalFS!D49,0) -> 18.718412 | E40: =IFERROR(HistoricalFS!E81/HistoricalFS!E49,0) -> 0 | F40: =IFERROR(HistoricalFS!F81/HistoricalFS!F49,0) -> 58.585859 | G40: =IFERROR(HistoricalFS!G81/HistoricalFS!G49,0) -> 0 | H40: =IFERROR(HistoricalFS!H81/HistoricalFS!H49,0) -> 0 | I40: =IFERROR(HistoricalFS!I81/HistoricalFS!I49,0) -> 8.674976 | J40: =IFERROR(HistoricalFS!J81/HistoricalFS!J49,0) -> 8.1960623 | ... L40: =IFERROR(HistoricalFS!L81/HistoricalFS!L49,0) -> 7.2123786 | N40: =IFERROR(AVERAGE(C40:L40),0) -> 13.537651 | O40: =IFERROR(MEDIAN(C40:L40),0) -> 8.4355192

Sheet Common Size Statement 
B2: ="Common Size Income Statement"&" "&"- "&'Data Sheet'!$B$1 -> Common Size Income Statement - HINDUSTAN UNILEVER LTD
B4: Particulars | C4: ='Data Sheet'!B16 -> 42460 | D4: ='Data Sheet'!C16 -> 42825 | E4: ='Data Sheet'!D16 -> 43190 | F4: ='Data Sheet'!E16 -> 43555 | G4: ='Data Sheet'!F16 -> 43921 | H4: ='Data Sheet'!G16 -> 44286 | I4: ='Data Sheet'!H16 -> 44651 | J4: ='Data Sheet'!I16 -> 45016 | ... L4: ='Data Sheet'!K16 -> 45747
B6: ='Data Sheet'!A17 -> Sales | C6: ='Data Sheet'!B17/'Data Sheet'!B$17 -> 1 | D6: ='Data Sheet'!C17/'Data Sheet'!C$17 -> 1 | E6: ='Data Sheet'!D17/'Data Sheet'!D$17 -> 1 | F6: ='Data Sheet'!E17/'Data Sheet'!E$17 -> 1 | G6: ='Data Sheet'!F17/'Data Sheet'!F$17 -> 1 | H6: ='Data Sheet'!G17/'Data Sheet'!G$17 -> 1 | I6: ='Data Sheet'!H17/'Data Sheet'!H$17 -> 1 | J6: ='Data Sheet'!I17/'Data Sheet'!I$17 -> 1 | ... L6: ='Data Sheet'!K17/'Data Sheet'!K$17 -> 1
B7: ='Data Sheet'!A18 -> Raw Material Cost | C7: ='Data Sheet'!B18/'Data Sheet'!B$17 -> 0.40961909 | D7: ='Data Sheet'!C18/'Data Sheet'!C$17 -> 0.41028888 | E7: ='Data Sheet'!D18/'Data Sheet'!D$17 -> 0.400422 | F7: ='Data Sheet'!E18/'Data Sheet'!E$17 -> 0.4030781 | G7: ='Data Sheet'!F18/'Data Sheet'!F$17 -> 0.39456552 | H7: ='Data Sheet'!G18/'Data Sheet'!G$17 -> 0.42827677 | I7: ='Data Sheet'!H18/'Data Sheet'!H$17 -> 0.43608664 | J7: ='Data Sheet'!I18/'Data Sheet'!I$17 -> 0.46924728 | ... L7: ='Data Sheet'!K18/'Data Sheet'!K$17 -> 0.43319973
B8: ='Data Sheet'!A19 -> Change in Inventory | C8: ='Data Sheet'!B19/'Data Sheet'!B$17 -> -0.002578761 | D8: ='Data Sheet'!C19/'Data Sheet'!C$17 -> -0.0043423195 | E8: ='Data Sheet'!D19/'Data Sheet'!D$17 -> 0.0020256014 | F8: ='Data Sheet'!E19/'Data Sheet'!E$17 -> -0.00030526584 | G8: ='Data Sheet'!F19/'Data Sheet'!F$17 -> 0.0027147274 | H8: ='Data Sheet'!G19/'Data Sheet'!G$17 -> 0.0086118908 | I8: ='Data Sheet'!H19/'Data Sheet'!H$17 -> 0.00041947908 | J8: ='Data Sheet'!I19/'Data Sheet'!I$17 -> 0.0012380324 | ... L8: ='Data Sheet'!K19/'Data Sheet'!K$17 -> 0.002423916
B9: ='Data Sheet'!A20 -> Power and Fuel | C9: ='Data Sheet'!B20/'Data Sheet'!B$17 -> 0.0096004474 | D9: ='Data Sheet'!C20/'Data Sheet'!C$17 -> 0.008895724 | E9: ='Data Sheet'!D20/'Data Sheet'!D$17 -> 0.0082993389 | F9: ='Data Sheet'!E20/'Data Sheet'!E$17 -> 0.0078351564 | G9: ='Data Sheet'!F20/'Data Sheet'!F$17 -> 0.0075157731 | H9: ='Data Sheet'!G20/'Data Sheet'!G$17 -> 0.0072084715 | I9: ='Data Sheet'!H20/'Data Sheet'!H$17 -> 0.0060633795 | J9: ='Data Sheet'!I20/'Data Sheet'!I$17 -> 0.0063387257 | ... L9: ='Data Sheet'!K20/'Data Sheet'!K$17 -> 0.0067647851
B10: ='Data Sheet'!A21 -> Other Mfr. Exp | C10: ='Data Sheet'!B21/'Data Sheet'!B$17 -> 0.092151867 | D10: ='Data Sheet'!C21/'Data Sheet'!C$17 -> 0.087057475 | E10: ='Data Sheet'!D21/'Data Sheet'!D$17 -> 0.08434379 | F10: ='Data Sheet'!E21/'Data Sheet'!E$17 -> 0.077359451 | G10: ='Data Sheet'!F21/'Data Sheet'!F$17 -> 0.073046276 | H10: ='Data Sheet'!G21/'Data Sheet'!G$17 -> 0.060984945 | I10: ='Data Sheet'!H21/'Data Sheet'!H$17 -> 0.063951493 | J10: ='Data Sheet'!I21/'Data Sheet'!I$17 -> 0.062578409 | ... L10: ='Data Sheet'!K21/'Data Sheet'!K$17 -> 0.060740483
B11: ='Data Sheet'!A22 -> Employee Cost | C11: ='Data Sheet'!B22/'Data Sheet'!B$17 -> 0.052196607 | D11: ='Data Sheet'!C22/'Data Sheet'!C$17 -> 0.052560159 | E11: ='Data Sheet'!D22/'Data Sheet'!D$17 -> 0.052328035 | F11: ='Data Sheet'!E22/'Data Sheet'!E$17 -> 0.047697787 | G11: ='Data Sheet'!F22/'Data Sheet'!F$17 -> 0.045748184 | H11: ='Data Sheet'!G22/'Data Sheet'!G$17 -> 0.050140342 | I11: ='Data Sheet'!H22/'Data Sheet'!H$17 -> 0.048526103 | J11: ='Data Sheet'!I22/'Data Sheet'!I$17 -> 0.047111258 | ... L11: ='Data Sheet'!K22/'Data Sheet'!K$17 -> 0.048747643
B12: ='Data Sheet'!A23 -> Selling and admin | C12: ='Data Sheet'!B23/'Data Sheet'!B$17 -> 0.20943889 | D12: ='Data Sheet'!C23/'Data Sheet'!C$17 -> 0.20170677 | E12: ='Data Sheet'!D23/'Data Sheet'!D$17 -> 0.20402307 | F12: ='Data Sheet'!E23/'Data Sheet'!E$17 -> 0.19832104 | G12: ='Data Sheet'!F23/'Data Sheet'!F$17 -> 0.1915391 | H12: ='Data Sheet'!G23/'Data Sheet'!G$17 -> 0.16811261 | I12: ='Data Sheet'!H23/'Data Sheet'!H$17 -> 0.15566487 | J12: ='Data Sheet'!I23/'Data Sheet'!I$17 -> 0.14501486 | ... L12: ='Data Sheet'!K23/'Data Sheet'!K$17 -> 0.16940479
B13: ='Data Sheet'!A24 -> Other Expenses | C13: ='Data Sheet'!B24/'Data Sheet'!B$17 -> 0.040794134 | D13: ='Data Sheet'!C24/'Data Sheet'!C$17 -> 0.044327845 | E13: ='Data Sheet'!D24/'Data Sheet'!D$17 -> 0.041637361 | F13: ='Data Sheet'!E24/'Data Sheet'!E$17 -> 0.039506487 | G13: ='Data Sheet'!F24/'Data Sheet'!F$17 -> 0.042430184 | H13: ='Data Sheet'!G24/'Data Sheet'!G$17 -> 0.046674322 | I13: ='Data Sheet'!H24/'Data Sheet'!H$17 -> 0.044979598 | J13: ='Data Sheet'!I24/'Data Sheet'!I$17 -> 0.037421591 | ... L13: ='Data Sheet'!K24/'Data Sheet'!K$17 -> 0.048414949
B14: ='Data Sheet'!A25 -> Other Income | C14: ='Data Sheet'!B25/'Data Sheet'!B$17 -> 0.015099733 | D14: ='Data Sheet'!C25/'Data Sheet'!C$17 -> 0.018273928 | E14: ='Data Sheet'!D25/'Data Sheet'!D$17 -> 0.0099310733 | F14: ='Data Sheet'!E25/'Data Sheet'!E$17 -> 0.0081912999 | G14: ='Data Sheet'!F25/'Data Sheet'!F$17 -> 0.010657819 | H14: ='Data Sheet'!G25/'Data Sheet'!G$17 -> 0.0036148677 | I14: ='Data Sheet'!H25/'Data Sheet'!H$17 -> 0.0041757236 | J14: ='Data Sheet'!I25/'Data Sheet'!I$17 -> 0.0073951799 | ... L14: ='Data Sheet'!K25/'Data Sheet'!K$17 -> 0.020943901
B15: ='Data Sheet'!A26 -> Depreciation | C15: ='Data Sheet'!B26/'Data Sheet'!B$17 -> 0.010967501 | D15: ='Data Sheet'!C26/'Data Sheet'!C$17 -> 0.013026959 | E15: ='Data Sheet'!D26/'Data Sheet'!D$17 -> 0.014629343 | F15: ='Data Sheet'!E26/'Data Sheet'!E$17 -> 0.014372933 | G15: ='Data Sheet'!F26/'Data Sheet'!F$17 -> 0.025186638 | H15: ='Data Sheet'!G26/'Data Sheet'!G$17 -> 0.022837459 | I15: ='Data Sheet'!H26/'Data Sheet'!H$17 -> 0.020802349 | J15: ='Data Sheet'!I26/'Data Sheet'!I$17 -> 0.01876857 | ... L15: ='Data Sheet'!K26/'Data Sheet'!K$17 -> 0.021466707
B16: ='Data Sheet'!A27 -> Interest | C16: ='Data Sheet'!B27/'Data Sheet'!B$17 -> 0.00052817995 | D16: ='Data Sheet'!C27/'Data Sheet'!C$17 -> 0.0010554249 | E16: ='Data Sheet'!D27/'Data Sheet'!D$17 -> 0.00073146715 | F16: ='Data Sheet'!E27/'Data Sheet'!E$17 -> 0.00083948105 | G16: ='Data Sheet'!F27/'Data Sheet'!F$17 -> 0.002966091 | H16: ='Data Sheet'!G27/'Data Sheet'!G$17 -> 0.0024878796 | I16: ='Data Sheet'!H27/'Data Sheet'!H$17 -> 0.0020211265 | J16: ='Data Sheet'!I27/'Data Sheet'!I$17 -> 0.0018818092 | ... L16: ='Data Sheet'!K27/'Data Sheet'!K$17 -> 0.0062578223
B17: ='Data Sheet'!A28 -> Profit before tax | C17: ='Data Sheet'!B28/'Data Sheet'!B$17 -> 0.18722426 | D17: ='Data Sheet'!C28/'Data Sheet'!C$17 -> 0.19501236 | E17: ='Data Sheet'!D28/'Data Sheet'!D$17 -> 0.20554227 | F17: ='Data Sheet'!E28/'Data Sheet'!E$17 -> 0.2188756 | G17: ='Data Sheet'!F28/'Data Sheet'!F$17 -> 0.23037478 | H17: ='Data Sheet'!G28/'Data Sheet'!G$17 -> 0.22550396 | I17: ='Data Sheet'!H28/'Data Sheet'!H$17 -> 0.22649964 | J17: ='Data Sheet'!I28/'Data Sheet'!I$17 -> 0.22027072 | ... L17: ='Data Sheet'!K28/'Data Sheet'!K$17 -> 0.22837091
... B20: ='Data Sheet'!A31 -> Dividend Amount | C20: ='Data Sheet'!B31/'Data Sheet'!B$17 -> 0.10737588 | D20: ='Data Sheet'!C31/'Data Sheet'!C$17 -> 0.11072915 | E20: ='Data Sheet'!D31/'Data Sheet'!D$17 -> 0.12153608 | F20: ='Data Sheet'!E31/'Data Sheet'!E$17 -> 0.12088527 | G20: ='Data Sheet'!F31/'Data Sheet'!F$17 -> 0.13573637 | H20: ='Data Sheet'!G31/'Data Sheet'!G$17 -> 0.20237943 | I20: ='Data Sheet'!H31/'Data Sheet'!H$17 -> 0.15234718 | J20: ='Data Sheet'!I31/'Data Sheet'!I$17 -> 0.15128755 | ... L20: ='Data Sheet'!K31/'Data Sheet'!K$17 -> 0.19731943
B21: ='Data Sheet'!A33 -> EBITDA | C21: ='Data Sheet'!B33/'Data Sheet'!B$17 -> 0.19871994 | D21: ='Data Sheet'!C33/'Data Sheet'!C$17 -> 0.20867258 | E21: ='Data Sheet'!D33/'Data Sheet'!D$17 -> 0.22053735 | F21: ='Data Sheet'!E33/'Data Sheet'!E$17 -> 0.23393539 | G21: ='Data Sheet'!F33/'Data Sheet'!F$17 -> 0.25832642 | H21: ='Data Sheet'!G33/'Data Sheet'!G$17 -> 0.25074424 | I21: ='Data Sheet'!H33/'Data Sheet'!H$17 -> 0.24907524 | J21: ='Data Sheet'!I33/'Data Sheet'!I$17 -> 0.24054143 | ... L21: ='Data Sheet'!K33/'Data Sheet'!K$17 -> 0.2557469
B23: ="Common Size Balance Sheet"&" "&"- "&'Data Sheet'!$B$1 -> Common Size Balance Sheet - HINDUSTAN UNILEVER LTD
B25: Particulars | C25: =C4 -> 42460 | D25: =D4 -> 42825 | E25: =E4 -> 43190 | F25: =F4 -> 43555 | G25: =G4 -> 43921 | H25: =H4 -> 44286 | I25: =I4 -> 44651 | J25: =J4 -> 45016 | ... L25: =L4 -> 45747
B27: Total Liabilities | C27: ='Data Sheet'!B61/'Data Sheet'!B$61 -> 1 | D27: ='Data Sheet'!C61/'Data Sheet'!C$61 -> 1 | E27: ='Data Sheet'!D61/'Data Sheet'!D$61 -> 1 | F27: ='Data Sheet'!E61/'Data Sheet'!E$61 -> 1 | G27: ='Data Sheet'!F61/'Data Sheet'!F$61 -> 1 | H27: ='Data Sheet'!G61/'Data Sheet'!G$61 -> 1 | I27: ='Data Sheet'!H61/'Data Sheet'!H$61 -> 1 | J27: ='Data Sheet'!I61/'Data Sheet'!I$61 -> 1 | ... L27: ='Data Sheet'!K61/'Data Sheet'!K$61 -> 1
B28: ='Data Sheet'!A57 -> Equity Share Capital | C28: ='Data Sheet'!B57/'Data Sheet'!B$61 -> 0.014601501 | D28: ='Data Sheet'!C57/'Data Sheet'!C$61 -> 0.013752706 | E28: ='Data Sheet'!D57/'Data Sheet'!D$61 -> 0.012092711 | F28: ='Data Sheet'!E57/'Data Sheet'!E$61 -> 0.011594825 | G28: ='Data Sheet'!F57/'Data Sheet'!F$61 -> 0.010718007 | H28: ='Data Sheet'!G57/'Data Sheet'!G$61 -> 0.0034186791 | I28: ='Data Sheet'!H57/'Data Sheet'!H$61 -> 0.0033330497 | J28: ='Data Sheet'!I57/'Data Sheet'!I$61 -> 0.0032157861 | ... L28: ='Data Sheet'!K57/'Data Sheet'!K$61 -> 0.0029425391
B29: ='Data Sheet'!A58 -> Reserves | C29: ='Data Sheet'!B58/'Data Sheet'!B$61 -> 0.42973028 | D29: ='Data Sheet'!C58/'Data Sheet'!C$61 -> 0.41563734 | E29: ='Data Sheet'!D58/'Data Sheet'!D$61 -> 0.39553242 | F29: ='Data Sheet'!E58/'Data Sheet'!E$61 -> 0.41070374 | G29: ='Data Sheet'!F58/'Data Sheet'!F$61 -> 0.3976083 | H29: ='Data Sheet'!G58/'Data Sheet'!G$61 -> 0.6901222 | I29: ='Data Sheet'!H58/'Data Sheet'!H$61 -> 0.69250844 | J29: ='Data Sheet'!I58/'Data Sheet'!I$61 -> 0.68515402 | ... L29: ='Data Sheet'!K58/'Data Sheet'!K$61 -> 0.61564179
B30: ='Data Sheet'!A59 -> Borrowings | C30: ='Data Sheet'!B59/'Data Sheet'!B$61 -> 0.011965119 | D30: ='Data Sheet'!C59/'Data Sheet'!C$61 -> 0.017636572 | E30: ='Data Sheet'!D59/'Data Sheet'!D$61 -> 0 | F30: ='Data Sheet'!E59/'Data Sheet'!E$61 -> 0.0053142949 | G30: ='Data Sheet'!F59/'Data Sheet'!F$61 -> 0 | H30: ='Data Sheet'!G59/'Data Sheet'!G$61 -> 0 | I30: ='Data Sheet'!H59/'Data Sheet'!H$61 -> 0.014793067 | J30: ='Data Sheet'!I59/'Data Sheet'!I$61 -> 0.016681035 | ... L30: ='Data Sheet'!K59/'Data Sheet'!K$61 -> 0.020635338
B31: ='Data Sheet'!A60 -> Other Liabilities | C31: ='Data Sheet'!B60/'Data Sheet'!B$61 -> 0.5437031 | D31: ='Data Sheet'!C60/'Data Sheet'!C$61 -> 0.55297339 | E31: ='Data Sheet'!D60/'Data Sheet'!D$61 -> 0.59237487 | F31: ='Data Sheet'!E60/'Data Sheet'!E$61 -> 0.57238714 | G31: ='Data Sheet'!F60/'Data Sheet'!F$61 -> 0.5916737 | H31: ='Data Sheet'!G60/'Data Sheet'!G$61 -> 0.30645912 | I31: ='Data Sheet'!H60/'Data Sheet'!H$61 -> 0.28936544 | J31: ='Data Sheet'!I60/'Data Sheet'!I$61 -> 0.29494916 | ... L31: ='Data Sheet'!K60/'Data Sheet'!K$61 -> 0.36078034
B33: Total Assets | C33: ='Data Sheet'!B76/'Data Sheet'!B$76 -> 1 | D33: ='Data Sheet'!C76/'Data Sheet'!C$76 -> 1 | E33: ='Data Sheet'!D76/'Data Sheet'!D$76 -> 1 | F33: ='Data Sheet'!E76/'Data Sheet'!E$76 -> 1 | G33: ='Data Sheet'!F76/'Data Sheet'!F$76 -> 1 | H33: ='Data Sheet'!G76/'Data Sheet'!G$76 -> 1 | I33: ='Data Sheet'!H76/'Data Sheet'!H$76 -> 1 | J33: ='Data Sheet'!I76/'Data Sheet'!I$76 -> 1 | ... L33: ='Data Sheet'!K76/'Data Sheet'!K$76 -> 1
B34: ='Data Sheet'!A62 -> Net Block | C34: ='Data Sheet'!B62/'Data Sheet'!B$76 -> 0.2202393 | D34: ='Data Sheet'!C62/'Data Sheet'!C$76 -> 0.28135744 | E34: ='Data Sheet'!D62/'Data Sheet'!D$76 -> 0.25349905 | F34: ='Data Sheet'!E62/'Data Sheet'!E$76 -> 0.25310001 | G34: ='Data Sheet'!F62/'Data Sheet'!F$76 -> 0.27187019 | H34: ='Data Sheet'!G62/'Data Sheet'!G$76 -> 0.74837067 | I34: ='Data Sheet'!H62/'Data Sheet'!H$76 -> 0.73005134 | J34: ='Data Sheet'!I62/'Data Sheet'!I$76 -> 0.72085608 | ... L34: ='Data Sheet'!K62/'Data Sheet'!K$76 -> 0.6803526
B35: ='Data Sheet'!A63 -> Capital Work in Progress | C35: ='Data Sheet'!B63/'Data Sheet'!B$76 -> 0.027580612 | D35: ='Data Sheet'!C63/'Data Sheet'!C$76 -> 0.014580415 | E35: ='Data Sheet'!D63/'Data Sheet'!D$76 -> 0.02580898 | F35: ='Data Sheet'!E63/'Data Sheet'!E$76 -> 0.021793977 | G35: ='Data Sheet'!F63/'Data Sheet'!F$76 -> 0.029623381 | H35: ='Data Sheet'!G63/'Data Sheet'!G$76 -> 0.01083794 | I35: ='Data Sheet'!H63/'Data Sheet'!H$76 -> 0.018622529 | J35: ='Data Sheet'!I63/'Data Sheet'!I$76 -> 0.01549051 | ... L35: ='Data Sheet'!K63/'Data Sheet'!K$76 -> 0.012634136
B36: ='Data Sheet'!A64 -> Investments | C36: ='Data Sheet'!B64/'Data Sheet'!B$76 -> 0.17521801 | D36: ='Data Sheet'!C64/'Data Sheet'!C$76 -> 0.24156373 | E36: ='Data Sheet'!D64/'Data Sheet'!D$76 -> 0.16084425 | F36: ='Data Sheet'!E64/'Data Sheet'!E$76 -> 0.14579419 | G36: ='Data Sheet'!F64/'Data Sheet'!F$76 -> 0.062273607 | H36: ='Data Sheet'!G64/'Data Sheet'!G$76 -> 0.039409369 | I36: ='Data Sheet'!H64/'Data Sheet'!H$76 -> 0.049939012 | J36: ='Data Sheet'!I64/'Data Sheet'!I$76 -> 0.039437853 | ... L36: ='Data Sheet'!K64/'Data Sheet'!K$76 -> 0.047706698
B37: ='Data Sheet'!A65 -> Other Assets | C37: ='Data Sheet'!B74/'Data Sheet'!B$76 -> 0.10383289 | D37: ='Data Sheet'!C74/'Data Sheet'!C$76 -> 0.11524258 | E37: ='Data Sheet'!D74/'Data Sheet'!D$76 -> 0.15071101 | F37: ='Data Sheet'!E74/'Data Sheet'!E$76 -> 0.14198293 | G37: ='Data Sheet'!F74/'Data Sheet'!F$76 -> 0.18821019 | H37: ='Data Sheet'!G74/'Data Sheet'!G$76 -> 0.058699447 | I37: ='Data Sheet'!H74/'Data Sheet'!H$76 -> 0.057030607 | J37: ='Data Sheet'!I74/'Data Sheet'!I$76 -> 0.059895726 | ... L37: ='Data Sheet'!K74/'Data Sheet'!K$76 -> 0.061618021
B38: ='Data Sheet'!A67 -> Receivables | C38: ='Data Sheet'!B67/'Data Sheet'!B$76 -> 0.085445819 | D38: ='Data Sheet'!C67/'Data Sheet'!C$76 -> 0.06908188 | E38: ='Data Sheet'!D67/'Data Sheet'!D$76 -> 0.073340052 | F38: ='Data Sheet'!E67/'Data Sheet'!E$76 -> 0.09748242 | G38: ='Data Sheet'!F67/'Data Sheet'!F$76 -> 0.057013844 | H38: ='Data Sheet'!G67/'Data Sheet'!G$76 -> 0.025574629 | I38: ='Data Sheet'!H67/'Data Sheet'!H$76 -> 0.031713613 | J38: ='Data Sheet'!I67/'Data Sheet'!I$76 -> 0.04213364 | ... L38: ='Data Sheet'!K67/'Data Sheet'!K$76 -> 0.047819391
B39: ='Data Sheet'!A68 -> Inventory | C39: ='Data Sheet'!B68/'Data Sheet'!B$76 -> 0.18427635 | D39: ='Data Sheet'!C68/'Data Sheet'!C$76 -> 0.1617853 | E39: ='Data Sheet'!D68/'Data Sheet'!D$76 -> 0.14068973 | F39: ='Data Sheet'!E68/'Data Sheet'!E$76 -> 0.13817167 | G39: ='Data Sheet'!F68/'Data Sheet'!F$76 -> 0.13729966 | H39: ='Data Sheet'!G68/'Data Sheet'!G$76 -> 0.052065755 | I39: ='Data Sheet'!H68/'Data Sheet'!H$76 -> 0.058094347 | J39: ='Data Sheet'!I68/'Data Sheet'!I$76 -> 0.058171518 | ... L39: ='Data Sheet'!K68/'Data Sheet'!K$76 -> 0.055282171
B40: ='Data Sheet'!A69 -> Cash & Bank | C40: ='Data Sheet'!B69/'Data Sheet'!B$76 -> 0.20340702 | D40: ='Data Sheet'!C69/'Data Sheet'!C$76 -> 0.11638864 | E40: ='Data Sheet'!D69/'Data Sheet'!D$76 -> 0.19510693 | F40: ='Data Sheet'!E69/'Data Sheet'!E$76 -> 0.20167481 | G40: ='Data Sheet'!F69/'Data Sheet'!F$76 -> 0.25370913 | H40: ='Data Sheet'!G69/'Data Sheet'!G$76 -> 0.065042188 | I40: ='Data Sheet'!H69/'Data Sheet'!H$76 -> 0.054548549 | J40: ='Data Sheet'!I69/'Data Sheet'!I$76 -> 0.064014669 | ... L40: ='Data Sheet'!K69/'Data Sheet'!K$76 -> 0.09458698

Sheet Data>

Sheet Data Sheet
A1: COMPANY NAME | B1: HINDUSTAN UNILEVER LTD | E1: =IF(B2<>B3, "A NEW VERSION OF THE WORKSHEET IS AVAILABLE", "")
A2: LATEST VERSION | B2: 2.1 | E2: PLEASE DO NOT MAKE ANY CHANGES TO THIS SHEET
A3: CURRENT VERSION | B3: 2.1
A5: META
A6: Number of shares | B6: =IF(B9>0, B9/B8, 0) -> 234.95912
A7: Face Value | B7: 1
A8: Current Price | B8: 2409.5
A9: Market Capitalization | B9: 566134.01
A15: PROFIT & LOSS
A16: Report Date | B16: 42460 | C16: 42825 | D16: 43190 | E16: 43555 | F16: 43921 | G16: 44286 | H16: 44651 | I16: 45016 | J16: 45382 | K16: 45747
A17: Sales | B17: 32186 | C17: 33162 | D17: 35545 | E17: 39310 | F17: 39783 | G17: 47028 | H17: 52446 | I17: 60580 | J17: 61896 | K17: 63121
A18: Raw Material Cost | B18: 13184 | C18: 13606 | D18: 14233 | E18: 15845 | F18: 15697 | G18: 20141 | H18: 22871 | I18: 28427 | J18: 26822 | K18: 27344
A19: Change in Inventory | B19: -83 | C19: -144 | D19: 72 | E19: -12 | F19: 108 | G19: 405 | H19: 22 | I19: 75 | J19: 11 | K19: 153
A20: Power and Fuel | B20: 309 | C20: 295 | D20: 295 | E20: 308 | F20: 299 | G20: 339 | H20: 318 | I20: 384 | J20: 446 | K20: 427
A21: Other Mfr. Exp | B21: 2966 | C21: 2887 | D21: 2998 | E21: 3041 | F21: 2906 | G21: 2868 | H21: 3354 | I21: 3791 | J21: 3385 | K21: 3834
A22: Employee Cost | B22: 1680 | C22: 1743 | D22: 1860 | E22: 1875 | F22: 1820 | G22: 2358 | H22: 2545 | I22: 2854 | J22: 3009 | K22: 3077
A23: Selling and admin | B23: 6741 | C23: 6689 | D23: 7252 | E23: 7796 | F23: 7620 | G23: 7906 | H23: 8164 | I23: 8785 | J23: 10780 | K23: 10693
A24: Other Expenses | B24: 1313 | C24: 1470 | D24: 1480 | E24: 1553 | F24: 1688 | G24: 2195 | H24: 2359 | I24: 2267 | J24: 2806 | K24: 3056
A25: Other Income | B25: 486 | C25: 606 | D25: 353 | E25: 322 | F25: 424 | G25: 170 | H25: 219 | I25: 448 | J25: 817 | K25: 1322
A26: Depreciation | B26: 353 | C26: 432 | D26: 520 | E26: 565 | F26: 1002 | G26: 1074 | H26: 1091 | I26: 1137 | J26: 1216 | K26: 1355
A27: Interest | B27: 17 | C27: 35 | D27: 26 | E27: 33 | F27: 118 | G27: 117 | H27: 106 | I27: 114 | J27: 334 | K27: 395
... A31: Dividend Amount | B31: 3456 | C31: 3672 | D31: 4320 | E31: 4752 | F31: 5400 | G31: 9517.5 | H31: 7990 | I31: 9165 | J31: 9870 | K31: 12455
A33: EBITDA | B33: =B30+B29+B27+B26 -> 6396 | C33: =C30+C29+C27+C26 -> 6920 | D33: =D30+D29+D27+D26 -> 7839 | E33: =E30+E29+E27+E26 -> 9196 | F33: =F30+F29+F27+F26 -> 10277 | G33: =G30+G29+G27+G26 -> 11792 | H33: =H30+H29+H27+H26 -> 13063 | I33: =I30+I29+I27+I26 -> 14572 | ... K33: =K30+K29+K27+K26 -> 16143
A40: Quarters
A41: Report Date | B41: 45107 | C41: 45199 | D41: 45291 | E41: 45382 | F41: 45473 | G41: 45565 | H41: 45657 | I41: 45747 | J41: 45838 | K41: 45930
A42: Sales | B42: 15496 | C42: 15623 | D42: 15567 | E42: 15210 | F42: 15707 | G42: 15926 | H42: 15818 | I42: 15670 | J42: 16514 | K42: 16241
A43: Expenses | B43: 11832 | C43: 11828 | D43: 11902 | E43: 11675 | F43: 11965 | G43: 12139 | H43: 12123 | I43: 12052 | J43: 12797 | K43: 12515
A44: Other Income | B44: 146 | C44: 178 | D44: 184 | E44: 309 | F44: 209 | G44: 203 | H44: 740 | I44: 171 | J44: 74 | K44: 331
A45: Depreciation | B45: 286 | C45: 297 | D45: 313 | E45: 320 | F45: 329 | G45: 338 | H45: 341 | I45: 347 | J45: 361 | K45: 358
A46: Interest | B46: 50 | C46: 88 | D46: 91 | E46: 105 | F46: 93 | G46: 110 | H46: 112 | I46: 80 | J46: 127 | K46: 129
A47: Profit before tax | B47: 3474 | C47: 3588 | D47: 3445 | E47: 3419 | F47: 3529 | G47: 3542 | H47: 3982 | I47: 3362 | J47: 3303 | K47: 3570
A48: Tax | B48: 918 | C48: 931 | D48: 937 | E48: 858 | F48: 917 | G48: 947 | H48: 993 | I48: 887 | J48: 535 | K48: 876
A49: Net profit | B49: 2554 | C49: 2656 | D49: 2509 | E49: 2558 | F49: 2610 | G49: 2591 | H49: 2984 | I49: 2464 | J49: 2756 | K49: 2685
A50: Operating Profit | B50: 3664 | C50: 3795 | D50: 3665 | E50: 3535 | F50: 3742 | G50: 3787 | H50: 3695 | I50: 3618 | J50: 3717 | K50: 3726
A51: EBITDA | B51: =B49+B48+B46+B45 -> 3808 | C51: =C49+C48+C46+C45 -> 3972 | D51: =D49+D48+D46+D45 -> 3850 | E51: =E49+E48+E46+E45 -> 3841 | F51: =F49+F48+F46+F45 -> 3949 | G51: =G49+G48+G46+G45 -> 3986 | H51: =H49+H48+H46+H45 -> 4430 | I51: =I49+I48+I46+I45 -> 3778 | ... K51: =K49+K48+K46+K45 -> 4048
A55: BALANCE SHEET
A56: Report Date | B56: 42460 | C56: 42825 | D56: 43190 | E56: 43555 | F56: 43921 | G56: 44286 | H56: 44651 | I56: 45016 | J56: 45382 | K56: 45747
A57: Equity Share Capital | B57: 216 | C57: 216 | D57: 216 | E57: 216 | F57: 216 | G57: 235 | H57: 235 | I57: 235 | J57: 235 | K57: 235
A58: Reserves | B58: 6357 | C58: 6528 | D58: 7065 | E58: 7651 | F58: 8013 | G58: 47439 | H58: 48826 | I58: 50069 | J58: 50983 | K58: 49167
A59: Borrowings | B59: 177 | C59: 277 | E59: 99 | H59: 1043 | I59: 1219 | J59: 1484 | K59: 1648
A60: Other Liabilities | B60: 8043 | C60: 8685 | D60: 10581 | E60: 10663 | F60: 11924 | G60: 21066 | H60: 20402 | I60: 21554 | J60: 25787 | K60: 28813
A61: Total | B61: 14793 | C61: 15706 | D61: 17862 | E61: 18629 | F61: 20153 | G61: 68740 | H61: 70506 | I61: 73077 | J61: 78489 | K61: 79863
A62: Net Block | B62: 3258 | C62: 4419 | D62: 4528 | E62: 4715 | F62: 5479 | G62: 51443 | H62: 51473 | I62: 52678 | J62: 53744 | K62: 54335
A63: Capital Work in Progress | B63: 408 | C63: 229 | D63: 461 | E63: 406 | F63: 597 | G63: 745 | H63: 1313 | I63: 1132 | J63: 1025 | K63: 1009
A64: Investments | B64: 2592 | C64: 3794 | D64: 2873 | E64: 2716 | F64: 1255 | G64: 2709 | H64: 3521 | I64: 2882 | J64: 4625 | K64: 3810
A65: Other Assets | B65: 8535 | C65: 7264 | D65: 10000 | E65: 10792 | F65: 12822 | G65: 13843 | H65: 14199 | I65: 16385 | J65: 19095 | K65: 20709
A66: Total | B66: 14793 | C66: 15706 | D66: 17862 | E66: 18629 | F66: 20153 | G66: 68740 | H66: 70506 | I66: 73077 | J66: 78489 | K66: 79863
A67: Receivables | B67: 1264 | C67: 1085 | D67: 1310 | E67: 1816 | F67: 1149 | G67: 1758 | H67: 2236 | I67: 3079 | J67: 2997 | K67: 3819
A68: Inventory | B68: 2726 | C68: 2541 | D68: 2513 | E68: 2574 | F68: 2767 | G68: 3579 | H68: 4096 | I68: 4251 | J68: 4022 | K68: 4415
A69: Cash & Bank | B69: 3009 | C69: 1828 | D69: 3485 | E69: 3757 | F69: 5113 | G69: 4471 | H69: 3846 | I69: 4678 | J69: 7559 | K69: 7554
A70: No. of Equity Shares | B70: 2163936971 | C70: 2164349639 | D70: 2164528777 | E70: 2164704405 | F70: 2164704405 | G70: 2349567819 | H70: 2349591262 | I70: 2349591262 | J70: 2349591262 | K70: 2349591262
A71: New Bonus Shares
A72: Face value | B72: 1 | C72: 1 | D72: 1 | E72: 1 | F72: 1 | G72: 1 | H72: 1 | I72: 1 | J72: 1 | K72: 1
A74: Other Asset | B74: =B65-SUM(B67:B69) -> 1536 | C74: =C65-SUM(C67:C69) -> 1810 | D74: =D65-SUM(D67:D69) -> 2692 | E74: =E65-SUM(E67:E69) -> 2645 | F74: =F65-SUM(F67:F69) -> 3793 | G74: =G65-SUM(G67:G69) -> 4035 | H74: =H65-SUM(H67:H69) -> 4021 | I74: =I65-SUM(I67:I69) -> 4377 | ... K74: =K65-SUM(K67:K69) -> 4921
A76: Total Asset | B76: =B61 -> 14793 | C76: =C61 -> 15706 | D76: =D61 -> 17862 | E76: =E61 -> 18629 | F76: =F61 -> 20153 | G76: =G61 -> 68740 | H76: =H61 -> 70506 | I76: =I61 -> 73077 | ... K76: =K61 -> 79863
A80: CASH FLOW:
A81: Report Date | B81: 42460 | C81: 42825 | D81: 43190 | E81: 43555 | F81: 43921 | G81: 44286 | H81: 44651 | I81: 45016 | J81: 45382 | K81: 45747
A82: Cash from Operating Activity | B82: 4171 | C82: 5185 | D82: 6059 | E82: 5800 | F82: 7623 | G82: 9163 | H82: 9048 | I82: 9991 | J82: 15469 | K82: 11886
A83: Cash from Investing Activity | B83: -282 | C83: -1173 | D83: -1063 | E83: -438 | F83: 1791 | G83: -1228 | H83: -1728 | I83: -1484 | J83: -5324 | K83: 6473
A84: Cash from Financing Activity | B84: -3864 | C84: -4214 | D84: -4975 | E84: -5390 | F84: -6819 | G84: -9309 | H84: -8015 | I84: -8953 | J84: -10034 | K84: -13101
A85: Net Cash Flow | B85: 25 | C85: -202 | D85: 21 | E85: -28 | F85: 2595 | G85: -1374 | H85: -695 | I85: -446 | J85: 111 | K85: 5258
A90: PRICE: | B90: 832.17 | C90: 872.61 | D90: 1276.11 | E90: 1633.53 | F90: 2199.83 | G90: 2327.12 | H90: 1960.7 | I90: 2450.44 | J90: 2167.14 | K90: 2161.88
A92: DERIVED:
A93: Adjusted Equity Shares in Cr | B93: 216.39 | C93: 216.43 | D93: 216.45 | E93: 216.47 | F93: 216.48 | G93: 234.96 | H93: 234.96 | I93: 234.96 | J93: 234.96 | K93: 234.96

Sheet Cash Flow Data
C2: 41699 | D2: 42064 | E2: 42430 | F2: 42795 | G2: 43160 | H2: 43525 | I2: 43891 | J2: 44256 | K2: 44621 | L2: 44986 | M2: 45352 | N2: 45717
B3: Cash from Operating Activity - | C3: 3818 | D3: 3292 | E3: 4171 | F3: 5185 | G3: 6059 | H3: 5800 | I3: 7623 | J3: 9163 | K3: 9048 | L3: 9991 | M3: 15469 | N3: 11886
B4: Profit from operations | C4: 4802 | D4: 5510 | E4: 6025 | F4: 6512 | G4: 7485 | H4: 8909 | I4: 9723 | J4: 11672 | K4: 12829 | L4: 14089 | M4: 14537 | N4: 14942
B5: Receivables | C5: -17 | D5: 3 | E5: -257 | F5: 173 | G5: 0 | H5: 0 | I5: 0 | J5: 0 | K5: 0 | L5: 0 | M5: 0 | N5: 0
B6: Inventory | C6: -201 | D6: 91 | E6: 89 | F6: 37 | G6: -146 | H6: -195 | I6: -331 | J6: -543 | K6: -758 | L6: -339 | M6: 74 | N6: -584
B7: Payables | C7: 546 | D7: -327 | E7: 164 | F7: 501 | G7: 0 | H7: 0 | I7: 0 | J7: 0 | K7: 0 | L7: 0 | M7: 0 | N7: 0
B8: Loans Advances | C8: -4 | D8: -148 | E8: 0 | F8: 0 | G8: 0 | H8: 0 | I8: 0 | J8: 0 | K8: 0 | L8: 0 | M8: 0 | N8: 0
B9: Operating Deposits | C9: 0 | D9: 0 | E9: 0 | F9: -46 | G9: 0 | H9: 0 | I9: 0 | J9: 0 | K9: 0 | L9: 0 | M9: 0 | N9: 0
B10: Other WC items | C10: 81 | D10: 38 | E10: -77 | F10: -99 | G10: 982 | H10: -147 | I10: 742 | J10: 442 | K10: -242 | L10: -621 | M10: 1239 | N10: -204
B11: Working capital changes | C11: 405 | D11: -342 | E11: -81 | F11: 566 | G11: 836 | H11: -342 | I11: 411 | J11: -101 | K11: -1000 | L11: -960 | M11: 1313 | N11: -788
B12: Direct taxes | C12: -1384 | D12: -1862 | E12: -1765 | F12: -1859 | G12: -2264 | H12: -2767 | I12: -2505 | J12: -2407 | K12: -2784 | L12: -3138 | M12: -381 | N12: -2268
B13: Other operating items | C13: -5 | D13: -14 | E13: -8 | F13: -21 | G13: 0 | H13: 0 | I13: 0 | J13: 0 | K13: 0 | L13: 0 | M13: 0 | N13: 0
B14: Exceptional CF items | C14: 0 | D14: 0 | E14: 0 | F14: -13 | G14: 2 | H14: 0 | I14: -6 | J14: -1 | K14: 3 | L14: 0 | M14: 0 | N14: 0
... B35: Net Cash Flow | C35: 383 | D35: -33 | E35: 25 | F35: -202 | G35: 21 | H35: -28 | I35: 2595 | J35: -1374 | K35: -695 | L35: -446 | M35: 111 | N35: 5258
