Workbook

Sheet Comps_Val
B2: Amount in crores
B3: Comparable Company Valuation
D5: Market Data | K5: Financials | O5: Valuation
B6: Company | C6: Ticker | D6: Share Price | E6: Share Outstanding | F6: Equity Value | G6: Net Debt | H6: Enterprise Value | K6: Revenue | L6: EBITDA | M6: Net Income | O6: EV/Revenue | P6: EV/EBITDA | Q6: P/E
B8: =Data!C4 -> Infosys | D8: =Data!D4 -> 1249.8 | E8: =Data!E4 -> 405.54 | F8: =D8*E8 -> 506843.89 | G8: =Data!I4 -> -15659 | H8: =Data!J4 -> 473592.89 | K8: =Data!K4 -> 173173 | L8: =Data!L4 -> 43293.25 | M8: =Data!M4 -> 28003 | O8: =$H8/K8 -> 2.7347964 | P8: =$H8/L8 -> 10.939185 | Q8: =F8/M8 -> 18.099628
B9: =Data!C3 -> TCS | D9: =Data!D3 -> 2409.2 | E9: =Data!E3 -> 361.81 | F9: =D9*E9 -> 871672.65 | G9: =Data!I3 -> -4531 | H9: =Data!J3 -> 845277.65 | K9: =Data!K3 -> 260802 | L9: =Data!L3 -> 70416.54 | M9: =Data!M3 -> 47963 | O9: =$H9/K9 -> 3.2410704 | P9: =$H9/L9 -> 12.003965 | Q9: =F9/M9 -> 18.173856
B10: =Data!C5 -> HCL Technologies | D10: =Data!D5 -> 1328.6 | E10: =Data!E5 -> 271.37 | F10: =D10*E10 -> 360542.18 | G10: =Data!I5 -> -14509 | H10: =Data!J5 -> 332473.18 | K10: =Data!K5 -> 126409 | L10: =Data!L5 -> 27809.98 | M10: =Data!M5 -> 16471 | O10: =$H10/K10 -> 2.6301385 | P10: =$H10/L10 -> 11.955175 | Q10: =F10/M10 -> 21.889514
B11: =Data!C6 -> Wipro | D11: =Data!D6 -> 195.11 | E11: =Data!E6 -> 1048.8 | F11: =D11*E11 -> 204631.37 | G11: =Data!I6 -> 3966.3 | H11: =Data!J6 -> 176270.27 | K11: =Data!K6 -> 90891.9 | L11: =Data!L6 -> 21814.056 | M11: =Data!M6 -> 13332 | O11: =$H11/K11 -> 1.9393397 | P11: =$H11/L11 -> 8.080582 | Q11: =F11/M11 -> 15.348887
B12: =Data!C7 -> Tech Mahindra | D12: =Data!D7 -> 1334.95 | E12: =Data!E7 -> 97.98 | F12: =D12*E12 -> 130798.4 | G12: =Data!I7 -> -2587.8 | H12: =Data!J7 -> 124301.8 | K12: =Data!K7 -> 55123.3 | L12: =Data!L7 -> 8268.495 | M12: =Data!M7 -> 4591 | O12: =$H12/K12 -> 2.2549775 | P12: =$H12/L12 -> 15.033183 | Q12: =F12/M12 -> 28.490177
B13: =Data!C8 -> LTIMindtree | D13: =Data!D8 -> 4182.9 | E13: =Data!E8 -> 29.65 | F13: =D13*E13 -> 124022.98 | G13: =Data!I8 -> -1205.6 | H13: =Data!J8 -> 118052.18 | K13: =Data!K8 -> 40787.6 | L13: =Data!L8 -> 7749.644 | M13: =Data!M8 -> 4724 | O13: =$H13/K13 -> 2.8943156 | P13: =$H13/L13 -> 15.23324 | Q13: =F13/M13 -> 26.253807
B14: =Data!C9 -> Persistent Systems | D14: =Data!D9 -> 4643.85 | E14: =Data!E9 -> 15.78 | F14: =D14*E14 -> 73279.953 | G14: =Data!I9 -> -621.53 | H14: =Data!J9 -> 71850.543 | K14: =Data!K9 -> 13934.63 | L14: =Data!L9 -> 2647.5797 | M14: =Data!M9 -> 1731.62 | O14: =$H14/K14 -> 5.1562577 | P14: =$H14/L14 -> 27.138198 | Q14: =F14/M14 -> 42.318726
B15: =Data!C10 -> Mphasis | D15: =Data!D10 -> 2079.8 | E15: =Data!E10 -> 19.07 | F15: =D15*E15 -> 39661.786 | G15: =Data!I10 -> 366.45 | H15: =Data!J10 -> 36070.176 | K15: =Data!K10 -> 15347.02 | L15: =Data!L10 -> 3069.404 | M15: =Data!M10 -> 1799.45 | O15: =$H15/K15 -> 2.3503049 | P15: =$H15/L15 -> 11.751524 | Q15: =F15/M15 -> 22.04106
B16: =Data!C11 -> Coforge | D16: =Data!D11 -> 1080.85 | E16: =Data!E11 -> 33.58 | F16: =D16*E16 -> 36294.943 | G16: =Data!I11 -> 88.3 | H16: =Data!J11 -> 34440.243 | K16: =Data!K11 -> 15272.3 | L16: =Data!L11 -> 2596.291 | M16: =Data!M11 -> 1385.8 | O16: =$H16/K16 -> 2.255079 | P16: =$H16/L16 -> 13.265171 | Q16: =F16/M16 -> 26.190607
B17: =Data!C12 -> Tata Elxsi | D17: =Data!D12 -> 4202.2 | E17: =Data!E12 -> 6.23 | F17: =D17*E17 -> 26179.706 | G17: =Data!I12 -> -1437.29 | H17: =Data!J12 -> 24404.216 | K17: =Data!K12 -> 3672.01 | L17: =Data!L12 -> 881.2824 | M17: =Data!M12 -> 580.5 | O17: =$H17/K17 -> 6.6460102 | P17: =$H17/L17 -> 27.691709 | Q17: =F17/M17 -> 45.098546
B19: High | O19: =MAX(O8:O17) -> 6.6460102 | P19: =MAX(P8:P17) -> 27.691709 | Q19: =MAX(Q8:Q17) -> 45.098546
B20: 75th Percentile | O20: =QUARTILE(O8:O17,3) -> 3.1543817 | P20: =QUARTILE(P8:P17,3) -> 15.183226 | Q20: =QUARTILE(Q8:Q17,3) -> 27.931084
B21: Average | O21: =AVERAGE(O8:O17) -> 3.210229 | P21: =AVERAGE(P8:P17) -> 15.309193 | Q21: =AVERAGE(Q8:Q17) -> 26.390481
B22: Median | O22: =MEDIAN(O8:O17) -> 2.6824675 | P22: =MEDIAN(P8:P17) -> 12.634568 | Q22: =MEDIAN(Q8:Q17) -> 24.115834
B23: 25th Percentile | O23: =QUARTILE(O8:O17,1) -> 2.2788855 | P23: =QUARTILE(P8:P17,1) -> 11.802437 | Q23: =QUARTILE(Q8:Q17,1) -> 19.10277
B24: Low | O24: =MIN(O8:O17) -> 1.9393397 | P24: =MIN(P8:P17) -> 8.080582 | Q24: =MIN(Q8:Q17) -> 15.348887
B26: Cipla Comparable Valuation | O26: EV/Revenue | P26: EV/EBITDA | Q26: P/E
B28: Implied Enterprise Value | O28: =O22*K8 -> 464530.94 | P28: =P22*L8 -> 546991.49 | Q28: =Q30+Q29 -> 659656.69
B29: Net Debt | O29: =$G$8 -> -15659 | P29: =$G$8 -> -15659 | Q29: =$G$8 -> -15659
B30: Implied Market Value | O30: =O28+O29 -> 448871.94 | P30: =P28+P29 -> 531332.49 | Q30: =Q22*M8 -> 675315.69
B31: Shares Outstanding | O31: =$E$8 -> 405.54 | P31: =$E$8 -> 405.54 | Q31: =$E$8 -> 405.54
B33: Implied Value per Share | O33: =O30/O31 -> 1106.85 | P33: =P30/P31 -> 1310.1852 | Q33: =Q30/Q31 -> 1665.2258
B35: Source: The Valuation School, Screener.in
O36: =IF(O33>$D$8,"Undervalued","Overvalued") -> Overvalued | P36: =IF(P33>$D$8,"Undervalued","Overvalued") -> Undervalued | Q36: =IF(Q33>$D$8,"Undervalued","Overvalued") -> Undervalued

Sheet Data
B2: S.No. | C2: Name | D2: CMP Rs. | E2: No. Eq. Shares Cr. | F2: Market Cap | G2: Debt Rs.Cr. | H2: Cash End Rs.Cr. | I2: Net Debt | J2: EV | K2: Sales Rs.Cr. | L2: EBITDA | M2: NP 12M Rs.Cr.
B3: 1 | C3: TCS | D3: 2409.2 | E3: 361.81 | F3: =D3*E3 -> 871672.65 | G3: 10932 | H3: 15463 | I3: =G3-H3 -> -4531 | J3: =F3-G3-H3 -> 845277.65 | K3: 260802 | L3: 70416.54 | M3: 47963
B4: 2 | C4: Infosys | D4: 1249.8 | E4: 405.54 | F4: =D4*E4 -> 506843.89 | G4: 8796 | H4: 24455 | I4: =G4-H4 -> -15659 | J4: =F4-G4-H4 -> 473592.89 | K4: 173173 | L4: 43293.25 | M4: 28003
B5: 3 | C5: HCL Technologies | D5: 1328.6 | E5: 271.37 | F5: =D5*E5 -> 360542.18 | G5: 6780 | H5: 21289 | I5: =G5-H5 -> -14509 | J5: =F5-G5-H5 -> 332473.18 | K5: 126409 | L5: 27809.98 | M5: 16471
B6: 4 | C6: Wipro | D6: 195.11 | E6: 1048.8 | F6: =D6*E6 -> 204631.37 | G6: 16163.7 | H6: 12197.4 | I6: =G6-H6 -> 3966.3 | J6: =F6-G6-H6 -> 176270.27 | K6: 90891.9 | L6: 21814.056 | M6: 13332
B7: 5 | C7: Tech Mahindra | D7: 1334.95 | E7: 97.98 | F7: =D7*E7 -> 130798.4 | G7: 1954.4 | H7: 4542.2 | I7: =G7-H7 -> -2587.8 | J7: =F7-G7-H7 -> 124301.8 | K7: 55123.3 | L7: 8268.495 | M7: 4591
B8: 6 | C8: LTIMindtree | D8: 4182.9 | E8: 29.65 | F8: =D8*E8 -> 124022.98 | G8: 2382.6 | H8: 3588.2 | I8: =G8-H8 -> -1205.6 | J8: =F8-G8-H8 -> 118052.18 | K8: 40787.6 | L8: 7749.644 | M8: 4724
B9: 7 | C9: Persistent Systems | D9: 4643.85 | E9: 15.78 | F9: =D9*E9 -> 73279.953 | G9: 403.94 | H9: 1025.47 | I9: =G9-H9 -> -621.53 | J9: =F9-G9-H9 -> 71850.543 | K9: 13934.63 | L9: 2647.5797 | M9: 1731.62
B10: 8 | C10: Mphasis | D10: 2079.8 | E10: 19.07 | F10: =D10*E10 -> 39661.786 | G10: 1979.03 | H10: 1612.58 | I10: =G10-H10 -> 366.45 | J10: =F10-G10-H10 -> 36070.176 | K10: 15347.02 | L10: 3069.404 | M10: 1799.45
B11: 9 | C11: Coforge | D11: 1080.85 | E11: 33.58 | F11: =D11*E11 -> 36294.943 | G11: 971.5 | H11: 883.2 | I11: =G11-H11 -> 88.3 | J11: =F11-G11-H11 -> 34440.243 | K11: 15272.3 | L11: 2596.291 | M11: 1385.8
B12: 10 | C12: Tata Elxsi | D12: 4202.2 | E12: 6.23 | F12: =D12*E12 -> 26179.706 | G12: 169.1 | H12: 1606.39 | I12: =G12-H12 -> -1437.29 | J12: =F12-G12-H12 -> 24404.216 | K12: 3672.01 | L12: 881.2824 | M12: 580.5
