Workbook
Name UPDATE: 'Data Sheet'!$E$1

Sheet Financials>

Sheet HistoricalFS
B2: ="Historical Financial Statements - "&'Data Sheet'!B1 -> Historical Financial Statements - TATA CONSULTANCY SERVICES LTD
B3: Years | C3: ='Data Sheet'!B16 -> 42825 | D3: ='Data Sheet'!C16 -> 43190 | E3: ='Data Sheet'!D16 -> 43555 | F3: ='Data Sheet'!E16 -> 43921 | G3: ='Data Sheet'!F16 -> 44286 | H3: ='Data Sheet'!G16 -> 44651 | I3: ='Data Sheet'!H16 -> 45016 | J3: ='Data Sheet'!I16 -> 45382 | ... L3: ='Data Sheet'!K16 -> 46112
A5: # | B5: Income Statement
B6: Sales | C6: =IFERROR('Data Sheet'!B17,0) -> 117966 | D6: =IFERROR('Data Sheet'!C17,0) -> 123104 | E6: =IFERROR('Data Sheet'!D17,0) -> 146463 | F6: =IFERROR('Data Sheet'!E17,0) -> 156949 | G6: =IFERROR('Data Sheet'!F17,0) -> 164177 | H6: =IFERROR('Data Sheet'!G17,0) -> 191754 | I6: =IFERROR('Data Sheet'!H17,0) -> 225458 | J6: =IFERROR('Data Sheet'!I17,0) -> 240893 | ... L6: =IFERROR('Data Sheet'!K17,0) -> 267021
B7: Sales Growth | C7: - | D7: =IFERROR((D6/C6-1),0) -> 0.043554923 | E7: =IFERROR((E6/D6-1),0) -> 0.18975013 | F7: =IFERROR((F6/E6-1),0) -> 0.071594874 | G7: =IFERROR((G6/F6-1),0) -> 0.046053177 | H7: =IFERROR((H6/G6-1),0) -> 0.16797115 | I7: =IFERROR((I6/H6-1),0) -> 0.17576687 | J7: =IFERROR((J6/I6-1),0) -> 0.068460645 | K7: =IFERROR((K6/J6-1),0) -> 0.059906265 | L7: =IFERROR((L6/K6-1),0) -> 0.04581238
B9: COGS | C9: ='Data Sheet'!B21+'Data Sheet'!B22 -> 64336 | D9: ='Data Sheet'!C21+'Data Sheet'!C22 -> 69010 | E9: ='Data Sheet'!D21+'Data Sheet'!D22 -> 80476 | F9: ='Data Sheet'!E21+'Data Sheet'!E22 -> 87839 | G9: ='Data Sheet'!F21+'Data Sheet'!F22 -> 93262 | H9: ='Data Sheet'!G21+'Data Sheet'!G22 -> 108688 | I9: ='Data Sheet'!H21+'Data Sheet'!H22 -> 129366 | J9: ='Data Sheet'!I21+'Data Sheet'!I22 -> 143791 | ... L9: ='Data Sheet'!K21+'Data Sheet'!K22 -> 159350
B10: COGS % Sales | C10: =IFERROR((C9/C6),0) -> 0.54537748 | D10: =IFERROR((D9/D6),0) -> 0.56058292 | E10: =IFERROR((E9/E6),0) -> 0.549463 | F10: =IFERROR((F9/F6),0) -> 0.55966588 | G10: =IFERROR((G9/G6),0) -> 0.56805765 | H10: =IFERROR((H9/H6),0) -> 0.56680956 | I10: =IFERROR((I9/I6),0) -> 0.57379201 | J10: =IFERROR((J9/J6),0) -> 0.59690817 | ... L10: =IFERROR((L9/L6),0) -> 0.59676954
B12: Gross Profit | C12: =IFERROR((C6-C9),0) -> 53630 | D12: =IFERROR((D6-D9),0) -> 54094 | E12: =IFERROR((E6-E9),0) -> 65987 | F12: =IFERROR((F6-F9),0) -> 69110 | G12: =IFERROR((G6-G9),0) -> 70915 | H12: =IFERROR((H6-H9),0) -> 83066 | I12: =IFERROR((I6-I9),0) -> 96092 | J12: =IFERROR((J6-J9),0) -> 97102 | ... L12: =IFERROR((L6-L9),0) -> 107671
B13: Gross Margins | C13: =IFERROR((C12/C6),0) -> 0.45462252 | D13: =IFERROR((D12/D6),0) -> 0.43941708 | E13: =IFERROR((E12/E6),0) -> 0.450537 | F13: =IFERROR((F12/F6),0) -> 0.44033412 | G13: =IFERROR((G12/G6),0) -> 0.43194235 | H13: =IFERROR((H12/H6),0) -> 0.43319044 | I13: =IFERROR((I12/I6),0) -> 0.42620799 | J13: =IFERROR((J12/J6),0) -> 0.40309183 | ... L13: =IFERROR((L12/L6),0) -> 0.40323046
B15: Selling, General and Administrative Expenses | C15: =IFERROR(('Data Sheet'!B23+'Data Sheet'!B24),0) -> 21226 | D15: =IFERROR(('Data Sheet'!C23+'Data Sheet'!C24),0) -> 21492 | E15: =IFERROR(('Data Sheet'!D23+'Data Sheet'!D24),0) -> 26441 | F15: =IFERROR(('Data Sheet'!E23+'Data Sheet'!E24),0) -> 26983 | G15: =IFERROR(('Data Sheet'!F23+'Data Sheet'!F24),0) -> 24355 | H15: =IFERROR(('Data Sheet'!G23+'Data Sheet'!G24),0) -> 29980 | I15: =IFERROR(('Data Sheet'!H23+'Data Sheet'!H24),0) -> 36796 | J15: =IFERROR(('Data Sheet'!I23+'Data Sheet'!I24),0) -> 32764 | ... L15: =IFERROR(('Data Sheet'!K23+'Data Sheet'!K24),0) -> 35230
B16: SG&A Exp % Sales | C16: =IFERROR((C15/C6),0) -> 0.1799332 | D16: =IFERROR((D15/D6),0) -> 0.17458409 | E16: =IFERROR((E15/E6),0) -> 0.18053024 | F16: =IFERROR((F15/F6),0) -> 0.17192209 | G16: =IFERROR((G15/G6),0) -> 0.14834599 | H16: =IFERROR((H15/H6),0) -> 0.15634615 | I16: =IFERROR((I15/I6),0) -> 0.16320556 | J16: =IFERROR((J15/J6),0) -> 0.13601059 | ... L16: =IFERROR((L15/L6),0) -> 0.13193719
B18: EBITDA | C18: =IFERROR((C12-C15),0) -> 32404 | D18: =IFERROR((D12-D15),0) -> 32602 | E18: =IFERROR((E12-E15),0) -> 39546 | F18: =IFERROR((F12-F15),0) -> 42127 | G18: =IFERROR((G12-G15),0) -> 46560 | H18: =IFERROR((H12-H15),0) -> 53086 | I18: =IFERROR((I12-I15),0) -> 59296 | J18: =IFERROR((J12-J15),0) -> 64338 | ... L18: =IFERROR((L12-L15),0) -> 72441
B19: EBITDA Margins | C19: =IFERROR((C18/C6),0) -> 0.27468932 | D19: =IFERROR((D18/D6),0) -> 0.26483299 | E19: =IFERROR((E18/E6),0) -> 0.27000676 | F19: =IFERROR((F18/F6),0) -> 0.26841203 | G19: =IFERROR((G18/G6),0) -> 0.28359636 | H19: =IFERROR((H18/H6),0) -> 0.27684429 | I19: =IFERROR((I18/I6),0) -> 0.26300242 | J19: =IFERROR((J18/J6),0) -> 0.26708124 | ... L19: =IFERROR((L18/L6),0) -> 0.27129327
B21: Interest | C21: =IFERROR('Data Sheet'!B27,0) -> 32 | D21: =IFERROR('Data Sheet'!C27,0) -> 52 | E21: =IFERROR('Data Sheet'!D27,0) -> 198 | F21: =IFERROR('Data Sheet'!E27,0) -> 924 | G21: =IFERROR('Data Sheet'!F27,0) -> 637 | H21: =IFERROR('Data Sheet'!G27,0) -> 784 | I21: =IFERROR('Data Sheet'!H27,0) -> 779 | J21: =IFERROR('Data Sheet'!I27,0) -> 778 | ... L21: =IFERROR('Data Sheet'!K27,0) -> 1227
B22: Interest % Sales | C22: =IFERROR((C21/C6),0) -> 0.0002712646 | D22: =IFERROR((D21/D6),0) -> 0.00042240707 | E22: =IFERROR((E21/E6),0) -> 0.0013518773 | F22: =IFERROR((F21/F6),0) -> 0.0058872627 | G22: =IFERROR((G21/G6),0) -> 0.0038799588 | H22: =IFERROR((H21/H6),0) -> 0.0040885718 | I22: =IFERROR((I21/I6),0) -> 0.003455189 | J22: =IFERROR((J21/J6),0) -> 0.0032296497 | ... L22: =IFERROR((L21/L6),0) -> 0.0045951442
B24: Depreciation | C24: =IFERROR('Data Sheet'!B26,0) -> 1987 | D24: =IFERROR('Data Sheet'!C26,0) -> 2014 | E24: =IFERROR('Data Sheet'!D26,0) -> 2056 | F24: =IFERROR('Data Sheet'!E26,0) -> 3529 | G24: =IFERROR('Data Sheet'!F26,0) -> 4065 | H24: =IFERROR('Data Sheet'!G26,0) -> 4604 | I24: =IFERROR('Data Sheet'!H26,0) -> 5022 | J24: =IFERROR('Data Sheet'!I26,0) -> 4985 | ... L24: =IFERROR('Data Sheet'!K26,0) -> 5560
B25: Depreciation % Sales | C25: =IFERROR((C24/C6),0) -> 0.016843836 | D25: =IFERROR((D24/D6),0) -> 0.016360151 | E25: =IFERROR((E24/E6),0) -> 0.014037675 | F25: =IFERROR((F24/F6),0) -> 0.022485011 | G25: =IFERROR((G24/G6),0) -> 0.024759863 | H25: =IFERROR((H24/H6),0) -> 0.024009929 | I25: =IFERROR((I24/I6),0) -> 0.022274659 | J25: =IFERROR((J24/J6),0) -> 0.020693835 | ... L25: =IFERROR((L24/L6),0) -> 0.020822332
B27: Earnings Before Tax | C27: =IFERROR((C18-SUM(C21+C24)),0) -> 30385 | D27: =IFERROR((D18-SUM(D21+D24)),0) -> 30536 | E27: =IFERROR((E18-SUM(E21+E24)),0) -> 37292 | F27: =IFERROR((F18-SUM(F21+F24)),0) -> 37674 | G27: =IFERROR((G18-SUM(G21+G24)),0) -> 41858 | H27: =IFERROR((H18-SUM(H21+H24)),0) -> 47698 | I27: =IFERROR((I18-SUM(I21+I24)),0) -> 53495 | J27: =IFERROR((J18-SUM(J21+J24)),0) -> 58575 | ... L27: =IFERROR((L18-SUM(L21+L24)),0) -> 65654
B28: EBT % Sales | C28: =IFERROR((C27/C6),0) -> 0.25757422 | D28: =IFERROR((D27/D6),0) -> 0.24805043 | E28: =IFERROR((E27/E6),0) -> 0.25461721 | F28: =IFERROR((F27/F6),0) -> 0.24003976 | G28: =IFERROR((G27/G6),0) -> 0.25495654 | H28: =IFERROR((H27/H6),0) -> 0.24874579 | I28: =IFERROR((I27/I6),0) -> 0.23727257 | J28: =IFERROR((J27/J6),0) -> 0.24315775 | ... L28: =IFERROR((L27/L6),0) -> 0.24587579
B30: Tax | C30: =IFERROR('Data Sheet'!B29,0) -> 8156 | D30: =IFERROR('Data Sheet'!C29,0) -> 8212 | E30: =IFERROR('Data Sheet'!D29,0) -> 10001 | F30: =IFERROR('Data Sheet'!E29,0) -> 9801 | G30: =IFERROR('Data Sheet'!F29,0) -> 11198 | H30: =IFERROR('Data Sheet'!G29,0) -> 13238 | I30: =IFERROR('Data Sheet'!H29,0) -> 14604 | J30: =IFERROR('Data Sheet'!I29,0) -> 15898 | ... L30: =IFERROR('Data Sheet'!K29,0) -> 16033
B31: Effective Tax Rate | C31: =IFERROR((C30/C27),0) -> 0.26842192 | D31: =IFERROR((D30/D27),0) -> 0.26892848 | E31: =IFERROR((E30/E27),0) -> 0.26818084 | F31: =IFERROR((F30/F27),0) -> 0.26015289 | G31: =IFERROR((G30/G27),0) -> 0.26752353 | H31: =IFERROR((H30/H27),0) -> 0.27753784 | I31: =IFERROR((I30/I27),0) -> 0.27299748 | J31: =IFERROR((J30/J27),0) -> 0.27141272 | ... L31: =IFERROR((L30/L27),0) -> 0.24420447
B33: Net Profit | C33: =IFERROR(C27-C30,0) -> 22229 | D33: =IFERROR(D27-D30,0) -> 22324 | E33: =IFERROR(E27-E30,0) -> 27291 | F33: =IFERROR(F27-F30,0) -> 27873 | G33: =IFERROR(G27-G30,0) -> 30660 | H33: =IFERROR(H27-H30,0) -> 34460 | I33: =IFERROR(I27-I30,0) -> 38891 | J33: =IFERROR(J27-J30,0) -> 42677 | ... L33: =IFERROR(L27-L30,0) -> 49621
B34: Net Margins | C34: =IFERROR((C33/C6),0) -> 0.18843565 | D34: =IFERROR((D33/D6),0) -> 0.1813426 | E34: =IFERROR((E33/E6),0) -> 0.18633375 | F34: =IFERROR((F33/F6),0) -> 0.17759272 | G34: =IFERROR((G33/G6),0) -> 0.18674967 | H34: =IFERROR((H33/H6),0) -> 0.17970942 | I34: =IFERROR((I33/I6),0) -> 0.17249776 | J34: =IFERROR((J33/J6),0) -> 0.17716164 | ... L34: =IFERROR((L33/L6),0) -> 0.18583183
B36: No of Equity Shares | C36: =IFERROR('Data Sheet'!B93,0) -> 394.09 | D36: =IFERROR('Data Sheet'!C93,0) -> 382.86 | E36: =IFERROR('Data Sheet'!D93,0) -> 375.24 | F36: =IFERROR('Data Sheet'!E93,0) -> 375.24 | G36: =IFERROR('Data Sheet'!F93,0) -> 369.91 | H36: =IFERROR('Data Sheet'!G93,0) -> 365.91 | I36: =IFERROR('Data Sheet'!H93,0) -> 365.91 | J36: =IFERROR('Data Sheet'!I93,0) -> 361.81 | ... L36: =IFERROR('Data Sheet'!K93,0) -> 361.81
B38: Earnings Per Share | C38: =IFERROR(C33/C36,0) -> 56.405897 | D38: =IFERROR(D33/D36,0) -> 58.30852 | E38: =IFERROR(E33/E36,0) -> 72.729453 | F38: =IFERROR(F33/F36,0) -> 74.280461 | G38: =IFERROR(G33/G36,0) -> 82.885026 | H38: =IFERROR(H33/H36,0) -> 94.176164 | I38: =IFERROR(I33/I36,0) -> 106.2857 | J38: =IFERROR(J33/J36,0) -> 117.95417 | ... L38: =IFERROR(L33/L36,0) -> 137.14657
B39: EPS Growth % | D39: =IFERROR((D38/C38-1),0) -> 0.033730923 | E39: =IFERROR((E38/D38-1),0) -> 0.2473212 | F39: =IFERROR((F38/E38-1),0) -> 0.021325712 | G39: =IFERROR((G38/F38-1),0) -> 0.11583888 | H39: =IFERROR((H38/G38-1),0) -> 0.13622651 | I39: =IFERROR((I38/H38-1),0) -> 0.12858387 | J39: =IFERROR((J38/I38-1),0) -> 0.10978407 | K39: =IFERROR((K38/J38-1),0) -> 0.051714038 | L39: =IFERROR((L38/K38-1),0) -> 0.10553872
B41: Dividend Per Share | C41: =IFERROR('Data Sheet'!B31/HistoricalFS!C36,0) -> 23.494633 | D41: =IFERROR('Data Sheet'!C31/HistoricalFS!D36,0) -> 24.943844 | E41: =IFERROR('Data Sheet'!D31/HistoricalFS!E36,0) -> 29.980812 | F41: =IFERROR('Data Sheet'!E31/HistoricalFS!F36,0) -> 72.95331 | G41: =IFERROR('Data Sheet'!F31/HistoricalFS!G36,0) -> 38.009245 | H41: =IFERROR('Data Sheet'!G31/HistoricalFS!H36,0) -> 43.010576 | I41: =IFERROR('Data Sheet'!H31/HistoricalFS!I36,0) -> 115.02829 | J41: =IFERROR('Data Sheet'!I31/HistoricalFS!J36,0) -> 73.038335 | ... L41: =IFERROR('Data Sheet'!K31/HistoricalFS!L36,0) -> 110.05777
B42: Dividend Payout Ratio | C42: =IFERROR(C41/C38,0) -> 0.41652796 | D42: =IFERROR(D41/D38,0) -> 0.42779072 | E42: =IFERROR(E41/E38,0) -> 0.41222381 | F42: =IFERROR(F41/F38,0) -> 0.98213325 | G42: =IFERROR(G41/G38,0) -> 0.45857795 | H42: =IFERROR(H41/H38,0) -> 0.45670342 | I42: =IFERROR(I41/I38,0) -> 1.0822555 | J42: =IFERROR(J41/J38,0) -> 0.61920941 | ... L42: =IFERROR(L41/L38,0) -> 0.80248282
B44: Retained Earnings | C44: =IFERROR(IF(C38>C41,1-C42,0),0) -> 0.58347204 | D44: =IFERROR(IF(D38>D41,1-D42,0),0) -> 0.57220928 | E44: =IFERROR(IF(E38>E41,1-E42,0),0) -> 0.58777619 | F44: =IFERROR(IF(F38>F41,1-F42,0),0) -> 0.017866753 | G44: =IFERROR(IF(G38>G41,1-G42,0),0) -> 0.54142205 | H44: =IFERROR(IF(H38>H41,1-H42,0),0) -> 0.54329658 | I44: =IFERROR(IF(I38>I41,1-I42,0),0) -> 0 | J44: =IFERROR(IF(J38>J41,1-J42,0),0) -> 0.38079059 | ... L44: =IFERROR(IF(L38>L41,1-L42,0),0) -> 0.19751718
A46: # | B46: Balance Sheet
B47: Equity Share Capital | C47: =IFERROR('Data Sheet'!B57,0) -> 197 | D47: =IFERROR('Data Sheet'!C57,0) -> 191 | E47: =IFERROR('Data Sheet'!D57,0) -> 375 | F47: =IFERROR('Data Sheet'!E57,0) -> 375 | G47: =IFERROR('Data Sheet'!F57,0) -> 370 | H47: =IFERROR('Data Sheet'!G57,0) -> 366 | I47: =IFERROR('Data Sheet'!H57,0) -> 366 | J47: =IFERROR('Data Sheet'!I57,0) -> 362 | ... L47: =IFERROR('Data Sheet'!K57,0) -> 362
B48: Reserves | C48: =IFERROR('Data Sheet'!B58,0) -> 86017 | D48: =IFERROR('Data Sheet'!C58,0) -> 84937 | E48: =IFERROR('Data Sheet'!D58,0) -> 89071 | F48: =IFERROR('Data Sheet'!E58,0) -> 83751 | G48: =IFERROR('Data Sheet'!F58,0) -> 86063 | H48: =IFERROR('Data Sheet'!G58,0) -> 88773 | I48: =IFERROR('Data Sheet'!H58,0) -> 90058 | J48: =IFERROR('Data Sheet'!I58,0) -> 90127 | ... L48: =IFERROR('Data Sheet'!K58,0) -> 106878
B49: Borrowings | C49: =IFERROR('Data Sheet'!B59,0) -> 289 | D49: =IFERROR('Data Sheet'!C59,0) -> 247 | E49: =IFERROR('Data Sheet'!D59,0) -> 62 | F49: =IFERROR('Data Sheet'!E59,0) -> 8174 | G49: =IFERROR('Data Sheet'!F59,0) -> 7795 | H49: =IFERROR('Data Sheet'!G59,0) -> 7818 | I49: =IFERROR('Data Sheet'!H59,0) -> 7688 | J49: =IFERROR('Data Sheet'!I59,0) -> 8021 | ... L49: =IFERROR('Data Sheet'!K59,0) -> 11283
B50: Other Liabilities | C50: =IFERROR('Data Sheet'!B60,0) -> 15830 | D50: =IFERROR('Data Sheet'!C60,0) -> 19751 | E50: =IFERROR('Data Sheet'!D60,0) -> 24393 | F50: =IFERROR('Data Sheet'!E60,0) -> 27827 | G50: =IFERROR('Data Sheet'!F60,0) -> 35764 | H50: =IFERROR('Data Sheet'!G60,0) -> 43967 | I50: =IFERROR('Data Sheet'!H60,0) -> 44747 | J50: =IFERROR('Data Sheet'!I60,0) -> 46962 | ... L50: =IFERROR('Data Sheet'!K60,0) -> 62644
B51: Total Liabilities | C51: =IFERROR(SUM(C47:C50),0) -> 102333 | D51: =IFERROR(SUM(D47:D50),0) -> 105126 | E51: =IFERROR(SUM(E47:E50),0) -> 113901 | F51: =IFERROR(SUM(F47:F50),0) -> 120127 | G51: =IFERROR(SUM(G47:G50),0) -> 129992 | H51: =IFERROR(SUM(H47:H50),0) -> 140924 | I51: =IFERROR(SUM(I47:I50),0) -> 142859 | J51: =IFERROR(SUM(J47:J50),0) -> 145472 | ... L51: =IFERROR(SUM(L47:L50),0) -> 181167
B53: Fixed Asset Net Block | C53: =IFERROR('Data Sheet'!B62,0) -> 11701 | D53: =IFERROR('Data Sheet'!C62,0) -> 11973 | E53: =IFERROR('Data Sheet'!D62,0) -> 12290 | F53: =IFERROR('Data Sheet'!E62,0) -> 20928 | G53: =IFERROR('Data Sheet'!F62,0) -> 21021 | H53: =IFERROR('Data Sheet'!G62,0) -> 21298 | I53: =IFERROR('Data Sheet'!H62,0) -> 20515 | J53: =IFERROR('Data Sheet'!I62,0) -> 19604 | ... L53: =IFERROR('Data Sheet'!K62,0) -> 31343
B54: Capital Work in Progress | C54: =IFERROR('Data Sheet'!B63,0) -> 1541 | D54: =IFERROR('Data Sheet'!C63,0) -> 1278 | E54: =IFERROR('Data Sheet'!D63,0) -> 963 | F54: =IFERROR('Data Sheet'!E63,0) -> 906 | G54: =IFERROR('Data Sheet'!F63,0) -> 926 | H54: =IFERROR('Data Sheet'!G63,0) -> 1205 | I54: =IFERROR('Data Sheet'!H63,0) -> 1234 | J54: =IFERROR('Data Sheet'!I63,0) -> 1564 | ... L54: =IFERROR('Data Sheet'!K63,0) -> 2665
B55: Investments | C55: =IFERROR('Data Sheet'!B64,0) -> 41980 | D55: =IFERROR('Data Sheet'!C64,0) -> 36008 | E55: =IFERROR('Data Sheet'!D64,0) -> 29330 | F55: =IFERROR('Data Sheet'!E64,0) -> 26356 | G55: =IFERROR('Data Sheet'!F64,0) -> 29373 | H55: =IFERROR('Data Sheet'!G64,0) -> 30485 | I55: =IFERROR('Data Sheet'!H64,0) -> 37163 | J55: =IFERROR('Data Sheet'!I64,0) -> 31762 | ... L55: =IFERROR('Data Sheet'!K64,0) -> 33988
B56: Other Assets | C56: =IFERROR('Data Sheet'!B65-(SUM('Data Sheet'!B67:B69)),0) -> 20324 | D56: =IFERROR('Data Sheet'!C65-(SUM('Data Sheet'!C67:C69)),0) -> 23737 | E56: =IFERROR('Data Sheet'!D65-(SUM('Data Sheet'!D67:D69)),0) -> 31114 | F56: =IFERROR('Data Sheet'!E65-(SUM('Data Sheet'!E67:E69)),0) -> 31734 | G56: =IFERROR('Data Sheet'!F65-(SUM('Data Sheet'!F67:F69)),0) -> 39256 | H56: =IFERROR('Data Sheet'!G65-(SUM('Data Sheet'!G67:G69)),0) -> 27885 | I56: =IFERROR('Data Sheet'!H65-(SUM('Data Sheet'!H67:H69)),0) -> 22933 | J56: =IFERROR('Data Sheet'!I65-(SUM('Data Sheet'!I67:I69)),0) -> 25651 | ... L56: =IFERROR('Data Sheet'!K65-(SUM('Data Sheet'!K67:K69)),0) -> 32520
B57: Total Non Current Assets | C57: =IFERROR(SUM(C53:C56),0) -> 75546 | D57: =IFERROR(SUM(D53:D56),0) -> 72996 | E57: =IFERROR(SUM(E53:E56),0) -> 73697 | F57: =IFERROR(SUM(F53:F56),0) -> 79924 | G57: =IFERROR(SUM(G53:G56),0) -> 90576 | H57: =IFERROR(SUM(H53:H56),0) -> 80873 | I57: =IFERROR(SUM(I53:I56),0) -> 81845 | J57: =IFERROR(SUM(J53:J56),0) -> 78581 | ... L57: =IFERROR(SUM(L53:L56),0) -> 100516
B59: Receivables | C59: =IFERROR('Data Sheet'!B67,0) -> 22617 | D59: =IFERROR('Data Sheet'!C67,0) -> 24943 | E59: =IFERROR('Data Sheet'!D67,0) -> 27346 | F59: =IFERROR('Data Sheet'!E67,0) -> 30532 | G59: =IFERROR('Data Sheet'!F67,0) -> 30079 | H59: =IFERROR('Data Sheet'!G67,0) -> 41810 | I59: =IFERROR('Data Sheet'!H67,0) -> 49954 | J59: =IFERROR('Data Sheet'!I67,0) -> 53577 | ... L59: =IFERROR('Data Sheet'!K67,0) -> 67714
B60: Inventory | C60: =IFERROR('Data Sheet'!B68,0) -> 21 | D60: =IFERROR('Data Sheet'!C68,0) -> 26 | E60: =IFERROR('Data Sheet'!D68,0) -> 10 | F60: =IFERROR('Data Sheet'!E68,0) -> 5 | G60: =IFERROR('Data Sheet'!F68,0) -> 8 | H60: =IFERROR('Data Sheet'!G68,0) -> 20 | I60: =IFERROR('Data Sheet'!H68,0) -> 28 | J60: =IFERROR('Data Sheet'!I68,0) -> 28 | ... L60: =IFERROR('Data Sheet'!K68,0) -> 29
B61: Cash & Bank | C61: =IFERROR('Data Sheet'!B69,0) -> 4149 | D61: =IFERROR('Data Sheet'!C69,0) -> 7161 | E61: =IFERROR('Data Sheet'!D69,0) -> 12848 | F61: =IFERROR('Data Sheet'!E69,0) -> 9666 | G61: =IFERROR('Data Sheet'!F69,0) -> 9329 | H61: =IFERROR('Data Sheet'!G69,0) -> 18221 | I61: =IFERROR('Data Sheet'!H69,0) -> 11032 | J61: =IFERROR('Data Sheet'!I69,0) -> 13286 | ... L61: =IFERROR('Data Sheet'!K69,0) -> 12908
B62: Total Current Assets | C62: =SUM(C59:C61) -> 26787 | D62: =SUM(D59:D61) -> 32130 | E62: =SUM(E59:E61) -> 40204 | F62: =SUM(F59:F61) -> 40203 | G62: =SUM(G59:G61) -> 39416 | H62: =SUM(H59:H61) -> 60051 | I62: =SUM(I59:I61) -> 61014 | J62: =SUM(J59:J61) -> 66891 | ... L62: =SUM(L59:L61) -> 80651
B64: Total Assets | C64: =IFERROR(C57+C62,0) -> 102333 | D64: =IFERROR(D57+D62,0) -> 105126 | E64: =IFERROR(E57+E62,0) -> 113901 | F64: =IFERROR(F57+F62,0) -> 120127 | G64: =IFERROR(G57+G62,0) -> 129992 | H64: =IFERROR(H57+H62,0) -> 140924 | I64: =IFERROR(I57+I62,0) -> 142859 | J64: =IFERROR(J57+J62,0) -> 145472 | ... L64: =IFERROR(L57+L62,0) -> 181167
B66: Check | C66: =C64=C51 -> TRUE | D66: =D64=D51 -> TRUE | E66: =E64=E51 -> TRUE | F66: =F64=F51 -> TRUE | G66: =G64=G51 -> TRUE | H66: =H64=H51 -> TRUE | I66: =I64=I51 -> TRUE | J66: =J64=J51 -> TRUE | ... L66: =L64=L51 -> TRUE
A68: # | B68: Cash Flow Statements
B69: Operating Activities
B70: Profit from Operations | C70: =IFERROR('Cash Flow Data'!C4,0) -> 33800 | D70: =IFERROR('Cash Flow Data'!D4,0) -> 32885 | E70: =IFERROR('Cash Flow Data'!E4,0) -> 40720 | F70: =IFERROR('Cash Flow Data'!F4,0) -> 42882 | G70: =IFERROR('Cash Flow Data'!G4,0) -> 47031 | H70: =IFERROR('Cash Flow Data'!H4,0) -> 54204 | I70: =IFERROR('Cash Flow Data'!I4,0) -> 59148 | J70: =IFERROR('Cash Flow Data'!J4,0) -> 63709 | ... L70: =IFERROR('Cash Flow Data'!L4,0) -> 68688
B71: Receivables | C71: =IFERROR('Cash Flow Data'!C5,0) -> 680 | D71: =IFERROR('Cash Flow Data'!D5,0) -> -1833 | E71: =IFERROR('Cash Flow Data'!E5,0) -> -2883 | F71: =IFERROR('Cash Flow Data'!F5,0) -> -3295 | G71: =IFERROR('Cash Flow Data'!G5,0) -> 1059 | H71: =IFERROR('Cash Flow Data'!H5,0) -> -5144 | I71: =IFERROR('Cash Flow Data'!I5,0) -> -7683 | J71: =IFERROR('Cash Flow Data'!J5,0) -> -3332 | ... L71: =IFERROR('Cash Flow Data'!L5,0) -> -5248
B72: Inventory | C72: =IFERROR('Cash Flow Data'!C6,0) -> 0 | D72: =IFERROR('Cash Flow Data'!D6,0) -> -5 | E72: =IFERROR('Cash Flow Data'!E6,0) -> 16 | F72: =IFERROR('Cash Flow Data'!F6,0) -> 5 | G72: =IFERROR('Cash Flow Data'!G6,0) -> -3 | H72: =IFERROR('Cash Flow Data'!H6,0) -> -12 | I72: =IFERROR('Cash Flow Data'!I6,0) -> -8 | J72: =IFERROR('Cash Flow Data'!J6,0) -> 0 | ... L72: =IFERROR('Cash Flow Data'!L6,0) -> -8
B73: Payables | C73: =IFERROR('Cash Flow Data'!C7,0) -> -201 | D73: =IFERROR('Cash Flow Data'!D7,0) -> -346 | E73: =IFERROR('Cash Flow Data'!E7,0) -> 1496 | F73: =IFERROR('Cash Flow Data'!F7,0) -> 446 | G73: =IFERROR('Cash Flow Data'!G7,0) -> -93 | H73: =IFERROR('Cash Flow Data'!H7,0) -> 186 | I73: =IFERROR('Cash Flow Data'!I7,0) -> 2036 | J73: =IFERROR('Cash Flow Data'!J7,0) -> -632 | ... L73: =IFERROR('Cash Flow Data'!L7,0) -> -1105
B74: Loan Advances | C74: =IFERROR('Cash Flow Data'!C8,0) -> 0 | D74: =IFERROR('Cash Flow Data'!D8,0) -> 0 | E74: =IFERROR('Cash Flow Data'!E8,0) -> -499 | F74: =IFERROR('Cash Flow Data'!F8,0) -> 0 | G74: =IFERROR('Cash Flow Data'!G8,0) -> -17 | H74: =IFERROR('Cash Flow Data'!H8,0) -> -116 | I74: =IFERROR('Cash Flow Data'!I8,0) -> 261 | J74: =IFERROR('Cash Flow Data'!J8,0) -> -301 | ... L74: =IFERROR('Cash Flow Data'!L8,0) -> 197
B75: Other WC Items | C75: =IFERROR('Cash Flow Data'!C9,0) -> -1110 | D75: =IFERROR('Cash Flow Data'!D9,0) -> 1975 | E75: =IFERROR('Cash Flow Data'!E9,0) -> -299 | F75: =IFERROR('Cash Flow Data'!F9,0) -> -1823 | G75: =IFERROR('Cash Flow Data'!G9,0) -> -83 | H75: =IFERROR('Cash Flow Data'!H9,0) -> 2317 | I75: =IFERROR('Cash Flow Data'!I9,0) -> 1177 | J75: =IFERROR('Cash Flow Data'!J9,0) -> -2617 | ... L75: =IFERROR('Cash Flow Data'!L9,0) -> 3954
B76: Working Capital Changes | C76: =IFERROR(SUM(C71:C75),0) -> -631 | D76: =IFERROR(SUM(D71:D75),0) -> -209 | E76: =IFERROR(SUM(E71:E75),0) -> -2169 | F76: =IFERROR(SUM(F71:F75),0) -> -4667 | G76: =IFERROR(SUM(G71:G75),0) -> 863 | H76: =IFERROR(SUM(H71:H75),0) -> -2769 | I76: =IFERROR(SUM(I71:I75),0) -> -4217 | J76: =IFERROR(SUM(J71:J75),0) -> -6882 | ... L76: =IFERROR(SUM(L71:L75),0) -> -2210
B77: Direct Taxes | C77: =IFERROR('Cash Flow Data'!C11,0) -> -7946 | D77: =IFERROR('Cash Flow Data'!D11,0) -> -7609 | E77: =IFERROR('Cash Flow Data'!E11,0) -> -9958 | F77: =IFERROR('Cash Flow Data'!F11,0) -> -5846 | G77: =IFERROR('Cash Flow Data'!G11,0) -> -9092 | H77: =IFERROR('Cash Flow Data'!H11,0) -> -11486 | I77: =IFERROR('Cash Flow Data'!I11,0) -> -12966 | J77: =IFERROR('Cash Flow Data'!J11,0) -> -12489 | ... L77: =IFERROR('Cash Flow Data'!L11,0) -> -14384
B78: Cash From Operating Activities | C78: =IFERROR(SUM(C70+C76+C77),0) -> 25223 | D78: =IFERROR(SUM(D70+D76+D77),0) -> 25067 | E78: =IFERROR(SUM(E70+E76+E77),0) -> 28593 | F78: =IFERROR(SUM(F70+F76+F77),0) -> 32369 | G78: =IFERROR(SUM(G70+G76+G77),0) -> 38802 | H78: =IFERROR(SUM(H70+H76+H77),0) -> 39949 | I78: =IFERROR(SUM(I70+I76+I77),0) -> 41965 | J78: =IFERROR(SUM(J70+J76+J77),0) -> 44338 | ... L78: =IFERROR(SUM(L70+L76+L77),0) -> 52094
B80: Investing Activities
B81: Fixed Asset Purchased | C81: =IFERROR('Cash Flow Data'!C13,0) -> -1989 | D81: =IFERROR('Cash Flow Data'!D13,0) -> -1862 | E81: =IFERROR('Cash Flow Data'!E13,0) -> -2231 | F81: =IFERROR('Cash Flow Data'!F13,0) -> -3249 | G81: =IFERROR('Cash Flow Data'!G13,0) -> -3176 | H81: =IFERROR('Cash Flow Data'!H13,0) -> -2995 | I81: =IFERROR('Cash Flow Data'!I13,0) -> -3100 | J81: =IFERROR('Cash Flow Data'!J13,0) -> -2674 | ... L81: =IFERROR('Cash Flow Data'!L13,0) -> -4187
B82: Fixed Asset Sold | C82: =IFERROR('Cash Flow Data'!C14,0) -> 36 | D82: =IFERROR('Cash Flow Data'!D14,0) -> 58 | E82: =IFERROR('Cash Flow Data'!E14,0) -> 99 | F82: =IFERROR('Cash Flow Data'!F14,0) -> 161 | G82: =IFERROR('Cash Flow Data'!G14,0) -> 37 | H82: =IFERROR('Cash Flow Data'!H14,0) -> 31 | I82: =IFERROR('Cash Flow Data'!I14,0) -> 37 | J82: =IFERROR('Cash Flow Data'!J14,0) -> 24 | ... L82: =IFERROR('Cash Flow Data'!L14,0) -> 931
B83: Investment Purchased | C83: =IFERROR('Cash Flow Data'!C15,0) -> -121423 | D83: =IFERROR('Cash Flow Data'!D15,0) -> -97473 | E83: =IFERROR('Cash Flow Data'!E15,0) -> -96751 | F83: =IFERROR('Cash Flow Data'!F15,0) -> -80002 | G83: =IFERROR('Cash Flow Data'!G15,0) -> -54462 | H83: =IFERROR('Cash Flow Data'!H15,0) -> -75374 | I83: =IFERROR('Cash Flow Data'!I15,0) -> -129745 | J83: =IFERROR('Cash Flow Data'!J15,0) -> -141011 | ... L83: =IFERROR('Cash Flow Data'!L15,0) -> -151864
B84: Investment Sold | C84: =IFERROR('Cash Flow Data'!C16,0) -> 102798 | D84: =IFERROR('Cash Flow Data'!D16,0) -> 103482 | E84: =IFERROR('Cash Flow Data'!E16,0) -> 104133 | F84: =IFERROR('Cash Flow Data'!F16,0) -> 84089 | G84: =IFERROR('Cash Flow Data'!G16,0) -> 51630 | H84: =IFERROR('Cash Flow Data'!H16,0) -> 73852 | I84: =IFERROR('Cash Flow Data'!I16,0) -> 122687 | J84: =IFERROR('Cash Flow Data'!J16,0) -> 147204 | ... L84: =IFERROR('Cash Flow Data'!L16,0) -> 148023
B85: Interest Received | C85: =IFERROR('Cash Flow Data'!C17,0) -> 1788 | D85: =IFERROR('Cash Flow Data'!D17,0) -> 2623 | E85: =IFERROR('Cash Flow Data'!E17,0) -> 2619 | F85: =IFERROR('Cash Flow Data'!F17,0) -> 3729 | G85: =IFERROR('Cash Flow Data'!G17,0) -> 2730 | H85: =IFERROR('Cash Flow Data'!H17,0) -> 2700 | I85: =IFERROR('Cash Flow Data'!I17,0) -> 3080 | J85: =IFERROR('Cash Flow Data'!J17,0) -> 2990 | ... L85: =IFERROR('Cash Flow Data'!L17,0) -> 3008
B86: Dividend Received | C86: =IFERROR('Cash Flow Data'!C18,0) -> 1 | D86: =IFERROR('Cash Flow Data'!D18,0) -> 9 | E86: =IFERROR('Cash Flow Data'!E18,0) -> 18 | F86: =IFERROR('Cash Flow Data'!F18,0) -> 8 | G86: =IFERROR('Cash Flow Data'!G18,0) -> 8 | H86: =IFERROR('Cash Flow Data'!H18,0) -> 4 | I86: =IFERROR('Cash Flow Data'!I18,0) -> 13 | J86: =IFERROR('Cash Flow Data'!J18,0) -> 26 | ... L86: =IFERROR('Cash Flow Data'!L18,0) -> 84
B87: Acquisition of Companies | C87: =IFERROR('Cash Flow Data'!C19,0) -> 0 | D87: =IFERROR('Cash Flow Data'!D19,0) -> 0 | E87: =IFERROR('Cash Flow Data'!E19,0) -> -50 | F87: =IFERROR('Cash Flow Data'!F19,0) -> 0 | G87: =IFERROR('Cash Flow Data'!G19,0) -> 0 | H87: =IFERROR('Cash Flow Data'!H19,0) -> 0 | I87: =IFERROR('Cash Flow Data'!I19,0) -> 0 | J87: =IFERROR('Cash Flow Data'!J19,0) -> 0 | ... L87: =IFERROR('Cash Flow Data'!L19,0) -> 0
B88: Inter Corporate Deposits | C88: =IFERROR('Cash Flow Data'!C20,0) -> 1619 | D88: =IFERROR('Cash Flow Data'!D20,0) -> -2230 | E88: =IFERROR('Cash Flow Data'!E20,0) -> -2927 | F88: =IFERROR('Cash Flow Data'!F20,0) -> -473 | G88: =IFERROR('Cash Flow Data'!G20,0) -> -3058 | H88: =IFERROR('Cash Flow Data'!H20,0) -> 4879 | I88: =IFERROR('Cash Flow Data'!I20,0) -> 5361 | J88: =IFERROR('Cash Flow Data'!J20,0) -> 846 | ... L88: =IFERROR('Cash Flow Data'!L20,0) -> 0
B89: Other Investing Items | C89: =IFERROR('Cash Flow Data'!C21,0) -> 275 | D89: =IFERROR('Cash Flow Data'!D21,0) -> -1503 | E89: =IFERROR('Cash Flow Data'!E21,0) -> -3265 | F89: =IFERROR('Cash Flow Data'!F21,0) -> 4705 | G89: =IFERROR('Cash Flow Data'!G21,0) -> -1665 | H89: =IFERROR('Cash Flow Data'!H21,0) -> -3835 | I89: =IFERROR('Cash Flow Data'!I21,0) -> 2215 | J89: =IFERROR('Cash Flow Data'!J21,0) -> -1314 | ... L89: =IFERROR('Cash Flow Data'!L21,0) -> -8840
B90: Cash From Investing Activities | C90: =IFERROR(SUM(C81:C89),0) -> -16895 | D90: =IFERROR(SUM(D81:D89),0) -> 3104 | E90: =IFERROR(SUM(E81:E89),0) -> 1645 | F90: =IFERROR(SUM(F81:F89),0) -> 8968 | G90: =IFERROR(SUM(G81:G89),0) -> -7956 | H90: =IFERROR(SUM(H81:H89),0) -> -738 | I90: =IFERROR(SUM(I81:I89),0) -> 548 | J90: =IFERROR(SUM(J81:J89),0) -> 6091 | ... L90: =IFERROR(SUM(L81:L89),0) -> -12845
B92: Financing Activities
B93: Proceeds from Shares | C93: =IFERROR('Cash Flow Data'!C23,0) -> 0 | D93: =IFERROR('Cash Flow Data'!D23,0) -> 0 | E93: =IFERROR('Cash Flow Data'!E23,0) -> 0 | F93: =IFERROR('Cash Flow Data'!F23,0) -> 0 | G93: =IFERROR('Cash Flow Data'!G23,0) -> 0 | H93: =IFERROR('Cash Flow Data'!H23,0) -> 0 | I93: =IFERROR('Cash Flow Data'!I23,0) -> 18 | J93: =IFERROR('Cash Flow Data'!J23,0) -> 425 | ... L93: =IFERROR('Cash Flow Data'!L23,0) -> 0
B94: Proceeds from Borrowings | C94: =IFERROR('Cash Flow Data'!C24,0) -> 87 | D94: =IFERROR('Cash Flow Data'!D24,0) -> 0 | E94: =IFERROR('Cash Flow Data'!E24,0) -> 0 | F94: =IFERROR('Cash Flow Data'!F24,0) -> 0 | G94: =IFERROR('Cash Flow Data'!G24,0) -> 0 | H94: =IFERROR('Cash Flow Data'!H24,0) -> 0 | I94: =IFERROR('Cash Flow Data'!I24,0) -> 0 | J94: =IFERROR('Cash Flow Data'!J24,0) -> 0 | ... L94: =IFERROR('Cash Flow Data'!L24,0) -> 0
B95: Repayment of Borrowings | C95: =IFERROR('Cash Flow Data'!C25,0) -> 0 | D95: =IFERROR('Cash Flow Data'!D25,0) -> -19 | E95: =IFERROR('Cash Flow Data'!E25,0) -> -181 | F95: =IFERROR('Cash Flow Data'!F25,0) -> 0 | G95: =IFERROR('Cash Flow Data'!G25,0) -> 0 | H95: =IFERROR('Cash Flow Data'!H25,0) -> 0 | I95: =IFERROR('Cash Flow Data'!I25,0) -> 0 | J95: =IFERROR('Cash Flow Data'!J25,0) -> 0 | ... L95: =IFERROR('Cash Flow Data'!L25,0) -> 0
B96: Interest paid fin | C96: =IFERROR('Cash Flow Data'!C26,0) -> -20 | D96: =IFERROR('Cash Flow Data'!D26,0) -> -40 | E96: =IFERROR('Cash Flow Data'!E26,0) -> -186 | F96: =IFERROR('Cash Flow Data'!F26,0) -> -924 | G96: =IFERROR('Cash Flow Data'!G26,0) -> -634 | H96: =IFERROR('Cash Flow Data'!H26,0) -> -698 | I96: =IFERROR('Cash Flow Data'!I26,0) -> -779 | J96: =IFERROR('Cash Flow Data'!J26,0) -> -699 | ... L96: =IFERROR('Cash Flow Data'!L26,0) -> -901
B97: Dividend Paid | C97: =IFERROR('Cash Flow Data'!C27,0) -> -10973 | D97: =IFERROR('Cash Flow Data'!D27,0) -> -10760 | E97: =IFERROR('Cash Flow Data'!E27,0) -> -11472 | F97: =IFERROR('Cash Flow Data'!F27,0) -> -37702 | G97: =IFERROR('Cash Flow Data'!G27,0) -> -10907 | H97: =IFERROR('Cash Flow Data'!H27,0) -> -13375 | I97: =IFERROR('Cash Flow Data'!I27,0) -> -41410 | J97: =IFERROR('Cash Flow Data'!J27,0) -> -25218 | ... L97: =IFERROR('Cash Flow Data'!L27,0) -> -39571
B98: Financial Liabilities | C98: =IFERROR('Cash Flow Data'!C28,0) -> -66 | D98: =IFERROR('Cash Flow Data'!D28,0) -> -24 | E98: =IFERROR('Cash Flow Data'!E28,0) -> -13 | F98: =IFERROR('Cash Flow Data'!F28,0) -> -1062 | G98: =IFERROR('Cash Flow Data'!G28,0) -> -1336 | H98: =IFERROR('Cash Flow Data'!H28,0) -> -1417 | I98: =IFERROR('Cash Flow Data'!I28,0) -> -1515 | J98: =IFERROR('Cash Flow Data'!J28,0) -> -1614 | ... L98: =IFERROR('Cash Flow Data'!L28,0) -> -1861
B99: Other Financing Items | C99: =IFERROR('Cash Flow Data'!C29,0) -> -54 | D99: =IFERROR('Cash Flow Data'!D29,0) -> -16042 | E99: =IFERROR('Cash Flow Data'!E29,0) -> -16045 | F99: =IFERROR('Cash Flow Data'!F29,0) -> -227 | G99: =IFERROR('Cash Flow Data'!G29,0) -> -19757 | H99: =IFERROR('Cash Flow Data'!H29,0) -> -18091 | I99: =IFERROR('Cash Flow Data'!I29,0) -> -4192 | J99: =IFERROR('Cash Flow Data'!J29,0) -> -21430 | ... L99: =IFERROR('Cash Flow Data'!L29,0) -> 200
B100: Cash From Financing Activties | C100: =SUM(C93:C99) -> -11026 | D100: =SUM(D93:D99) -> -26885 | E100: =SUM(E93:E99) -> -27897 | F100: =SUM(F93:F99) -> -39915 | G100: =SUM(G93:G99) -> -32634 | H100: =SUM(H93:H99) -> -33581 | I100: =SUM(I93:I99) -> -47878 | J100: =SUM(J93:J99) -> -48536 | ... L100: =SUM(L93:L99) -> -42133
B102: Net Cash Flow | C102: =IFERROR(SUM(C78+C90+C100),0) -> -2698 | D102: =IFERROR(SUM(D78+D90+D100),0) -> 1286 | E102: =IFERROR(SUM(E78+E90+E100),0) -> 2341 | F102: =IFERROR(SUM(F78+F90+F100),0) -> 1422 | G102: =IFERROR(SUM(G78+G90+G100),0) -> -1788 | H102: =IFERROR(SUM(H78+H90+H100),0) -> 5630 | I102: =IFERROR(SUM(I78+I90+I100),0) -> -5365 | J102: =IFERROR(SUM(J78+J90+J100),0) -> 1893 | ... L102: =IFERROR(SUM(L78+L90+L100),0) -> -2884

Sheet Forecasting
B2: ='Data Sheet'!$B$1&" - "&'Data Sheet'!A17&" Forecasting" -> TATA CONSULTANCY SERVICES LTD - Sales Forecasting | G2: ='Data Sheet'!$B$1&" - "&'Data Sheet'!A33&" Forecasting" -> TATA CONSULTANCY SERVICES LTD - EBITDA Forecasting | L2: ='Data Sheet'!$B$1&" - "&HistoricalFS!B38&" Forecasting" -> TATA CONSULTANCY SERVICES LTD - Earnings Per Share Forecasting
B3: Year Weight | C3: Year | D3: Sales | E3: Sales Growth | G3: Year Weight | H3: Year | I3: EBITDA | J3: EBITDA Growth | L3: Year Weight | M3: Year | N3: EPS | O3: EPS Growth
B4: 1 | C4: ='Data Sheet'!B16 -> 42825 | D4: {=TRANSPOSE('Data Sheet'!B17:K17)} -> 117966 | G4: 1 | H4: =C4 -> 42825 | I4: {=TRANSPOSE('Data Sheet'!B33:K33)} -> 36464 | L4: 1 | M4: =H4 -> 42825 | N4: {=TRANSPOSE(HistoricalFS!C38:L38)} -> 56.405897
B5: =B4+1 -> 2 | C5: =C4+365 -> 43190 | D5: 123104 | E5: =D5/D4-1 -> 0.043554923 | G5: =G4+1 -> 2 | H5: =C5 -> 43190 | I5: 36104 | J5: =I5/I4-1 -> -0.0098727512 | L5: =L4+1 -> 2 | M5: =H5 -> 43190 | N5: 58.30852 | O5: =N5/N4-1 -> 0.033730923
B6: =B5+1 -> 3 | C6: =C5+365 -> 43555 | D6: 146463 | E6: =D6/D5-1 -> 0.18975013 | G6: =G5+1 -> 3 | H6: =C6 -> 43555 | I6: 43727 | J6: =I6/I5-1 -> 0.21114004 | L6: =L5+1 -> 3 | M6: =H6 -> 43555 | N6: 72.729453 | O6: =N6/N5-1 -> 0.2473212
B7: =B6+1 -> 4 | C7: =C6+365 -> 43920 | D7: 156949 | E7: =D7/D6-1 -> 0.071594874 | G7: =G6+1 -> 4 | H7: =C7 -> 43920 | I7: 46594 | J7: =I7/I6-1 -> 0.065565898 | L7: =L6+1 -> 4 | M7: =H7 -> 43920 | N7: 74.280461 | O7: =N7/N6-1 -> 0.021325712
B8: =B7+1 -> 5 | C8: =C7+365 -> 44285 | D8: 164177 | E8: =D8/D7-1 -> 0.046053177 | G8: =G7+1 -> 5 | H8: =C8 -> 44285 | I8: 48330 | J8: =I8/I7-1 -> 0.037258016 | L8: =L7+1 -> 5 | M8: =H8 -> 44285 | N8: 82.885026 | O8: =N8/N7-1 -> 0.11583888
B9: =B8+1 -> 6 | C9: =C8+365 -> 44650 | D9: 191754 | E9: =D9/D8-1 -> 0.16797115 | G9: =G8+1 -> 6 | H9: =C9 -> 44650 | I9: 56953 | J9: =I9/I8-1 -> 0.1784192 | L9: =L8+1 -> 6 | M9: =H9 -> 44650 | N9: 94.176164 | O9: =N9/N8-1 -> 0.13622651
B10: =B9+1 -> 7 | C10: =C9+365 -> 45015 | D10: 225458 | E10: =D10/D9-1 -> 0.17576687 | G10: =G9+1 -> 7 | H10: =C10 -> 45015 | I10: 62552 | J10: =I10/I9-1 -> 0.098309132 | L10: =L9+1 -> 7 | M10: =H10 -> 45015 | N10: 106.2857 | O10: =N10/N9-1 -> 0.12858387
B11: =B10+1 -> 8 | C11: =C10+365 -> 45380 | D11: 240893 | E11: =D11/D10-1 -> 0.068460645 | G11: =G10+1 -> 8 | H11: =C11 -> 45380 | I11: 67569 | J11: =I11/I10-1 -> 0.080205269 | L11: =L10+1 -> 8 | M11: =H11 -> 45380 | N11: 117.95417 | O11: =N11/N10-1 -> 0.10978407
B12: =B11+1 -> 9 | C12: =C11+365 -> 45745 | D12: 255324 | E12: =D12/D11-1 -> 0.059906265 | G12: =G11+1 -> 9 | H12: =C12 -> 45745 | I12: 71125 | J12: =I12/I11-1 -> 0.052627684 | L12: =L11+1 -> 9 | M12: =H12 -> 45745 | N12: 124.05406 | O12: =N12/N11-1 -> 0.051714038
B13: =B12+1 -> 10 | C13: =C12+365 -> 46110 | D13: 267021 | E13: =D13/D12-1 -> 0.04581238 | G13: =G12+1 -> 10 | H13: =C13 -> 46110 | I13: 72030 | J13: =I13/I12-1 -> 0.012724077 | L13: =L12+1 -> 10 | M13: =H13 -> 46110 | N13: 137.14657 | O13: =N13/N12-1 -> 0.10553872
B14: =B13+1 -> 11 | C14: =C13+365 -> 46475 | D14: =FORECAST(B14,$D$4:$D$13,$B$4:$B$13) -> 287987.2 | E14: =D14/D13-1 -> 0.078518918 | G14: =G13+1 -> 11 | H14: =C14 -> 46475 | I14: =FORECAST(G14,$I$4:$I$13,$G$4:$G$13) -> 78843.067 | J14: =I14/I13-1 -> 0.094586515 | L14: =L13+1 -> 11 | M14: =H14 -> 46475 | N14: =FORECAST(L14,$N$4:$N$13,$L$4:$L$13) -> 143.09978 | O14: =N14/N13-1 -> 0.04340765
B15: =B14+1 -> 12 | C15: =C14+365 -> 46840 | D15: =FORECAST(B15,$D$4:$D$13,$B$4:$B$13) -> 306001.07 | E15: =D15/D14-1 -> 0.062550949 | G15: =G14+1 -> 12 | H15: =C15 -> 46840 | I15: =FORECAST(G15,$I$4:$I$13,$G$4:$G$13) -> 83333.661 | J15: =I15/I14-1 -> 0.056956104 | L15: =L14+1 -> 12 | M15: =H15 -> 46840 | N15: =FORECAST(L15,$N$4:$N$13,$L$4:$L$13) -> 152.31381 | O15: =N15/N14-1 -> 0.064388863
B16: =B15+1 -> 13 | C16: =C15+365 -> 47205 | D16: =FORECAST(B16,$D$4:$D$13,$B$4:$B$13) -> 324014.95 | E16: =D16/D15-1 -> 0.058868659 | G16: =G15+1 -> 13 | H16: =C16 -> 47205 | I16: =FORECAST(G16,$I$4:$I$13,$G$4:$G$13) -> 87824.255 | J16: =I16/I15-1 -> 0.053886916 | L16: =L15+1 -> 13 | M16: =H16 -> 47205 | N16: =FORECAST(L16,$N$4:$N$13,$L$4:$L$13) -> 161.52784 | O16: =N16/N15-1 -> 0.06049374
B17: =B16+1 -> 14 | C17: =C16+365 -> 47570 | D17: =FORECAST(B17,$D$4:$D$13,$B$4:$B$13) -> 342028.82 | E17: =D17/D16-1 -> 0.055595808 | G17: =G16+1 -> 14 | H17: =C17 -> 47570 | I17: =FORECAST(G17,$I$4:$I$13,$G$4:$G$13) -> 92314.848 | J17: =I17/I16-1 -> 0.051131592 | L17: =L16+1 -> 14 | M17: =H17 -> 47570 | N17: =FORECAST(L17,$N$4:$N$13,$L$4:$L$13) -> 170.74188 | O17: =N17/N16-1 -> 0.057042996
B18: =B17+1 -> 15 | C18: =C17+365 -> 47935 | D18: =FORECAST(B18,$D$4:$D$13,$B$4:$B$13) -> 360042.69 | E18: =D18/D17-1 -> 0.052667705 | G18: =G17+1 -> 15 | H18: =C18 -> 47935 | I18: =FORECAST(G18,$I$4:$I$13,$G$4:$G$13) -> 96805.442 | J18: =I18/I17-1 -> 0.04864433 | L18: =L17+1 -> 15 | M18: =H18 -> 47935 | N18: =FORECAST(L18,$N$4:$N$13,$L$4:$L$13) -> 179.95591 | O18: =N18/N17-1 -> 0.053964688

Sheet Ratio Analysis
B2: ="Ratio Analysis - "&'Data Sheet'!B1 -> Ratio Analysis - TATA CONSULTANCY SERVICES LTD
B3: Years | C3: ='Data Sheet'!B16 -> 42825 | D3: ='Data Sheet'!C16 -> 43190 | E3: ='Data Sheet'!D16 -> 43555 | F3: ='Data Sheet'!E16 -> 43921 | G3: ='Data Sheet'!F16 -> 44286 | H3: ='Data Sheet'!G16 -> 44651 | I3: ='Data Sheet'!H16 -> 45016 | J3: ='Data Sheet'!I16 -> 45382 | ... L3: ='Data Sheet'!K16 -> 46112 | M3: Trend | N3: Mean | O3: Median
B5: Sales Growth | C5: =IFERROR(HistoricalFS!C7,0) -> - | D5: =IFERROR(HistoricalFS!D7,0) -> 0.043554923 | E5: =IFERROR(HistoricalFS!E7,0) -> 0.18975013 | F5: =IFERROR(HistoricalFS!F7,0) -> 0.071594874 | G5: =IFERROR(HistoricalFS!G7,0) -> 0.046053177 | H5: =IFERROR(HistoricalFS!H7,0) -> 0.16797115 | I5: =IFERROR(HistoricalFS!I7,0) -> 0.17576687 | J5: =IFERROR(HistoricalFS!J7,0) -> 0.068460645 | ... L5: =IFERROR(HistoricalFS!L7,0) -> 0.04581238 | N5: =IFERROR(AVERAGE(D5:L5),0) -> 0.096541157 | O5: =IFERROR(MEDIAN(C5:L5),0) -> 0.068460645
B6: EBITDA Growth | C6: - | D6: =IFERROR(HistoricalFS!D18/HistoricalFS!C18-1,0) -> 0.0061103567 | E6: =IFERROR(HistoricalFS!E18/HistoricalFS!D18-1,0) -> 0.21299307 | F6: =IFERROR(HistoricalFS!F18/HistoricalFS!E18-1,0) -> 0.065265766 | G6: =IFERROR(HistoricalFS!G18/HistoricalFS!F18-1,0) -> 0.10522943 | H6: =IFERROR(HistoricalFS!H18/HistoricalFS!G18-1,0) -> 0.14016323 | I6: =IFERROR(HistoricalFS!I18/HistoricalFS!H18-1,0) -> 0.11697999 | J6: =IFERROR(HistoricalFS!J18/HistoricalFS!I18-1,0) -> 0.085031031 | K6: =IFERROR(HistoricalFS!K18/HistoricalFS!J18-1,0) -> 0.048462806 | L6: =IFERROR(HistoricalFS!L18/HistoricalFS!K18-1,0) -> 0.073900024 | N6: =IFERROR(AVERAGE(D6:L6),0) -> 0.094903967 | O6: =IFERROR(MEDIAN(C6:L6),0) -> 0.085031031
B7: EBIT Growth | C7: - | D7: =IFERROR((HistoricalFS!D27+HistoricalFS!D21)/(HistoricalFS!C27+HistoricalFS!C21)-1,0) -> 0.0056218562 | E7: =IFERROR((HistoricalFS!E27+HistoricalFS!E21)/(HistoricalFS!D27+HistoricalFS!D21)-1,0) -> 0.22564404 | F7: =IFERROR((HistoricalFS!F27+HistoricalFS!F21)/(HistoricalFS!E27+HistoricalFS!E21)-1,0) -> 0.029554548 | G7: =IFERROR((HistoricalFS!G27+HistoricalFS!G21)/(HistoricalFS!F27+HistoricalFS!F21)-1,0) -> 0.10096378 | H7: =IFERROR((HistoricalFS!H27+HistoricalFS!H21)/(HistoricalFS!G27+HistoricalFS!G21)-1,0) -> 0.14088716 | I7: =IFERROR((HistoricalFS!I27+HistoricalFS!I21)/(HistoricalFS!H27+HistoricalFS!H21)-1,0) -> 0.11946702 | J7: =IFERROR((HistoricalFS!J27+HistoricalFS!J21)/(HistoricalFS!I27+HistoricalFS!I21)-1,0) -> 0.09358072 | K7: =IFERROR((HistoricalFS!K27+HistoricalFS!K21)/(HistoricalFS!J27+HistoricalFS!J21)-1,0) -> 0.048203124 | L7: =IFERROR((HistoricalFS!L27+HistoricalFS!L21)/(HistoricalFS!K27+HistoricalFS!K21)-1,0) -> 0.07501527 | N7: =IFERROR(AVERAGE(D7:L7),0) -> 0.09321528 | O7: =IFERROR(MEDIAN(C7:L7),0) -> 0.09358072
B8: Net Profit Growth | C8: - | D8: =IFERROR(HistoricalFS!D33/HistoricalFS!C33-1,0) -> 0.0042736965 | E8: =IFERROR(HistoricalFS!E33/HistoricalFS!D33-1,0) -> 0.22249597 | F8: =IFERROR(HistoricalFS!F33/HistoricalFS!E33-1,0) -> 0.021325712 | G8: =IFERROR(HistoricalFS!G33/HistoricalFS!F33-1,0) -> 0.099989237 | H8: =IFERROR(HistoricalFS!H33/HistoricalFS!G33-1,0) -> 0.12393999 | I8: =IFERROR(HistoricalFS!I33/HistoricalFS!H33-1,0) -> 0.12858387 | J8: =IFERROR(HistoricalFS!J33/HistoricalFS!I33-1,0) -> 0.097349001 | K8: =IFERROR(HistoricalFS!K33/HistoricalFS!J33-1,0) -> 0.051714038 | L8: =IFERROR(HistoricalFS!L33/HistoricalFS!K33-1,0) -> 0.10553872 | N8: =IFERROR(AVERAGE(D8:L8),0) -> 0.095023359 | O8: =IFERROR(MEDIAN(C8:L8),0) -> 0.099989237
B9: Dividend Growth | C9: - | D9: =IFERROR(HistoricalFS!D41/HistoricalFS!C41-1,0) -> 0.061682619 | E9: =IFERROR(HistoricalFS!E41/HistoricalFS!D41-1,0) -> 0.20193233 | F9: =IFERROR(HistoricalFS!F41/HistoricalFS!E41-1,0) -> 1.4333333 | G9: =IFERROR(HistoricalFS!G41/HistoricalFS!F41-1,0) -> -0.47899217 | H9: =IFERROR(HistoricalFS!H41/HistoricalFS!G41-1,0) -> 0.13158196 | I9: =IFERROR(HistoricalFS!I41/HistoricalFS!H41-1,0) -> 1.6744186 | J9: =IFERROR(HistoricalFS!J41/HistoricalFS!I41-1,0) -> -0.36504022 | K9: =IFERROR(HistoricalFS!K41/HistoricalFS!J41-1,0) -> 0.7260274 | L9: =IFERROR(HistoricalFS!L41/HistoricalFS!K41-1,0) -> -0.12698413 | N9: =IFERROR(AVERAGE(D9:L9),0) -> 0.36199553 | O9: =IFERROR(MEDIAN(C9:L9),0) -> 0.13158196
B11: Gross Margin | C11: =IFERROR(HistoricalFS!C13,0) -> 0.45462252 | D11: =IFERROR(HistoricalFS!D13,0) -> 0.43941708 | E11: =IFERROR(HistoricalFS!E13,0) -> 0.450537 | F11: =IFERROR(HistoricalFS!F13,0) -> 0.44033412 | G11: =IFERROR(HistoricalFS!G13,0) -> 0.43194235 | H11: =IFERROR(HistoricalFS!H13,0) -> 0.43319044 | I11: =IFERROR(HistoricalFS!I13,0) -> 0.42620799 | J11: =IFERROR(HistoricalFS!J13,0) -> 0.40309183 | ... L11: =IFERROR(HistoricalFS!L13,0) -> 0.40323046 | N11: =IFERROR(AVERAGE(C11:L11),0) -> 0.42661531 | O11: =IFERROR(MEDIAN(C11:L11),0) -> 0.4325664
B12: EBITDA Margin | C12: =IFERROR(HistoricalFS!C19,0) -> 0.27468932 | D12: =IFERROR(HistoricalFS!D19,0) -> 0.26483299 | E12: =IFERROR(HistoricalFS!E19,0) -> 0.27000676 | F12: =IFERROR(HistoricalFS!F19,0) -> 0.26841203 | G12: =IFERROR(HistoricalFS!G19,0) -> 0.28359636 | H12: =IFERROR(HistoricalFS!H19,0) -> 0.27684429 | I12: =IFERROR(HistoricalFS!I19,0) -> 0.26300242 | J12: =IFERROR(HistoricalFS!J19,0) -> 0.26708124 | ... L12: =IFERROR(HistoricalFS!L19,0) -> 0.27129327 | N12: =IFERROR(AVERAGE(C12:L12),0) -> 0.27039563 | O12: =IFERROR(MEDIAN(C12:L12),0) -> 0.2692094
B13: EBIT Margin | C13: =IFERROR((HistoricalFS!C27+HistoricalFS!C21)/HistoricalFS!C6,0) -> 0.25784548 | D13: =IFERROR((HistoricalFS!D27+HistoricalFS!D21)/HistoricalFS!D6,0) -> 0.24847284 | E13: =IFERROR((HistoricalFS!E27+HistoricalFS!E21)/HistoricalFS!E6,0) -> 0.25596908 | F13: =IFERROR((HistoricalFS!F27+HistoricalFS!F21)/HistoricalFS!F6,0) -> 0.24592702 | G13: =IFERROR((HistoricalFS!G27+HistoricalFS!G21)/HistoricalFS!G6,0) -> 0.2588365 | H13: =IFERROR((HistoricalFS!H27+HistoricalFS!H21)/HistoricalFS!H6,0) -> 0.25283436 | I13: =IFERROR((HistoricalFS!I27+HistoricalFS!I21)/HistoricalFS!I6,0) -> 0.24072776 | J13: =IFERROR((HistoricalFS!J27+HistoricalFS!J21)/HistoricalFS!J6,0) -> 0.2463874 | ... L13: =IFERROR((HistoricalFS!L27+HistoricalFS!L21)/HistoricalFS!L6,0) -> 0.25047094 | N13: =IFERROR(AVERAGE(C13:L13),0) -> 0.25011383 | O13: =IFERROR(MEDIAN(C13:L13),0) -> 0.24947189
B14: EBT Margin | C14: =IFERROR(HistoricalFS!C28,0) -> 0.25757422 | D14: =IFERROR(HistoricalFS!D28,0) -> 0.24805043 | E14: =IFERROR(HistoricalFS!E28,0) -> 0.25461721 | F14: =IFERROR(HistoricalFS!F28,0) -> 0.24003976 | G14: =IFERROR(HistoricalFS!G28,0) -> 0.25495654 | H14: =IFERROR(HistoricalFS!H28,0) -> 0.24874579 | I14: =IFERROR(HistoricalFS!I28,0) -> 0.23727257 | J14: =IFERROR(HistoricalFS!J28,0) -> 0.24315775 | ... L14: =IFERROR(HistoricalFS!L28,0) -> 0.24587579 | N14: =IFERROR(AVERAGE(C14:L14),0) -> 0.24708393 | O14: =IFERROR(MEDIAN(C14:L14),0) -> 0.24696311
B15: Net Profit Margin | C15: =IFERROR(HistoricalFS!C34,0) -> 0.18843565 | D15: =IFERROR(HistoricalFS!D34,0) -> 0.1813426 | E15: =IFERROR(HistoricalFS!E34,0) -> 0.18633375 | F15: =IFERROR(HistoricalFS!F34,0) -> 0.17759272 | G15: =IFERROR(HistoricalFS!G34,0) -> 0.18674967 | H15: =IFERROR(HistoricalFS!H34,0) -> 0.17970942 | I15: =IFERROR(HistoricalFS!I34,0) -> 0.17249776 | J15: =IFERROR(HistoricalFS!J34,0) -> 0.17716164 | ... L15: =IFERROR(HistoricalFS!L34,0) -> 0.18583183 | N15: =IFERROR(AVERAGE(C15:L15),0) -> 0.18114474 | O15: =IFERROR(MEDIAN(C15:L15),0) -> 0.18052601
B17: SalesExpense%Sales | C17: =IFERROR(HistoricalFS!C16,0) -> 0.1799332 | D17: =IFERROR(HistoricalFS!D16,0) -> 0.17458409 | E17: =IFERROR(HistoricalFS!E16,0) -> 0.18053024 | F17: =IFERROR(HistoricalFS!F16,0) -> 0.17192209 | G17: =IFERROR(HistoricalFS!G16,0) -> 0.14834599 | H17: =IFERROR(HistoricalFS!H16,0) -> 0.15634615 | I17: =IFERROR(HistoricalFS!I16,0) -> 0.16320556 | J17: =IFERROR(HistoricalFS!J16,0) -> 0.13601059 | ... L17: =IFERROR(HistoricalFS!L16,0) -> 0.13193719 | N17: =IFERROR(AVERAGE(C17:L17),0) -> 0.15621968 | O17: =IFERROR(MEDIAN(C17:L17),0) -> 0.15977586
B18: Depreciation%Sales | C18: =IFERROR(HistoricalFS!C25,0) -> 0.016843836 | D18: =IFERROR(HistoricalFS!D25,0) -> 0.016360151 | E18: =IFERROR(HistoricalFS!E25,0) -> 0.014037675 | F18: =IFERROR(HistoricalFS!F25,0) -> 0.022485011 | G18: =IFERROR(HistoricalFS!G25,0) -> 0.024759863 | H18: =IFERROR(HistoricalFS!H25,0) -> 0.024009929 | I18: =IFERROR(HistoricalFS!I25,0) -> 0.022274659 | J18: =IFERROR(HistoricalFS!J25,0) -> 0.020693835 | ... L18: =IFERROR(HistoricalFS!L25,0) -> 0.020822332 | N18: =IFERROR(AVERAGE(C18:L18),0) -> 0.020281807 | O18: =IFERROR(MEDIAN(C18:L18),0) -> 0.020758084
B19: OperatingIncome%Sales | C19: =IFERROR(HistoricalFS!C13,0) -> 0.45462252 | D19: =IFERROR(HistoricalFS!D13,0) -> 0.43941708 | E19: =IFERROR(HistoricalFS!E13,0) -> 0.450537 | F19: =IFERROR(HistoricalFS!F13,0) -> 0.44033412 | G19: =IFERROR(HistoricalFS!G13,0) -> 0.43194235 | H19: =IFERROR(HistoricalFS!H13,0) -> 0.43319044 | I19: =IFERROR(HistoricalFS!I13,0) -> 0.42620799 | J19: =IFERROR(HistoricalFS!J13,0) -> 0.40309183 | ... L19: =IFERROR(HistoricalFS!L13,0) -> 0.40323046 | N19: =IFERROR(AVERAGE(C19:L19),0) -> 0.42661531 | O19: =IFERROR(MEDIAN(C19:L19),0) -> 0.4325664
B21: Return on Capital Employed | C21: =IFERROR((HistoricalFS!C27+HistoricalFS!C21)/(SUM(HistoricalFS!C47:C49)),0) -> 0.35162942 | D21: =IFERROR((HistoricalFS!D27+HistoricalFS!D21)/(SUM(HistoricalFS!D47:D49)),0) -> 0.35827818 | E21: =IFERROR((HistoricalFS!E27+HistoricalFS!E21)/(SUM(HistoricalFS!E47:E49)),0) -> 0.41884524 | F21: =IFERROR((HistoricalFS!F27+HistoricalFS!F21)/(SUM(HistoricalFS!F47:F49)),0) -> 0.41817985 | G21: =IFERROR((HistoricalFS!G27+HistoricalFS!G21)/(SUM(HistoricalFS!G47:G49)),0) -> 0.4509806 | H21: =IFERROR((HistoricalFS!H27+HistoricalFS!H21)/(SUM(HistoricalFS!H47:H49)),0) -> 0.5000361 | I21: =IFERROR((HistoricalFS!I27+HistoricalFS!I21)/(SUM(HistoricalFS!I47:I49)),0) -> 0.55318412 | J21: =IFERROR((HistoricalFS!J27+HistoricalFS!J21)/(SUM(HistoricalFS!J47:J49)),0) -> 0.60250736 | ... L21: =IFERROR((HistoricalFS!L27+HistoricalFS!L21)/(SUM(HistoricalFS!L47:L49)),0) -> 0.5642871 | N21: =IFERROR(AVERAGE(C21:L21),0) -> 0.48152894 | O21: =IFERROR(MEDIAN(C21:L21),0) -> 0.47550835
B22: Retained Earnings% | C22: =IFERROR(HistoricalFS!C44,0) -> 0.58347204 | D22: =IFERROR(HistoricalFS!D44,0) -> 0.57220928 | E22: =IFERROR(HistoricalFS!E44,0) -> 0.58777619 | F22: =IFERROR(HistoricalFS!F44,0) -> 0.017866753 | G22: =IFERROR(HistoricalFS!G44,0) -> 0.54142205 | H22: =IFERROR(HistoricalFS!H44,0) -> 0.54329658 | I22: =IFERROR(HistoricalFS!I44,0) -> 0 | J22: =IFERROR(HistoricalFS!J44,0) -> 0.38079059 | ... L22: =IFERROR(HistoricalFS!L44,0) -> 0.19751718 | N22: =IFERROR(AVERAGE(C22:L22),0) -> 0.34243507 | O22: =IFERROR(MEDIAN(C22:L22),0) -> 0.46110632
B23: Return on Equity | C23: =IFERROR(HistoricalFS!C33/(SUM(HistoricalFS!C47:C48)),0) -> 0.25783515 | D23: =IFERROR(HistoricalFS!D33/(SUM(HistoricalFS!D47:D48)),0) -> 0.26224039 | E23: =IFERROR(HistoricalFS!E33/(SUM(HistoricalFS!E47:E48)),0) -> 0.30511146 | F23: =IFERROR(HistoricalFS!F33/(SUM(HistoricalFS!F47:F48)),0) -> 0.33132444 | G23: =IFERROR(HistoricalFS!G33/(SUM(HistoricalFS!G47:G48)),0) -> 0.35472563 | H23: =IFERROR(HistoricalFS!H33/(SUM(HistoricalFS!H47:H48)),0) -> 0.38658724 | I23: =IFERROR(HistoricalFS!I33/(SUM(HistoricalFS!I47:I48)),0) -> 0.43009599 | J23: =IFERROR(HistoricalFS!J33/(SUM(HistoricalFS!J47:J48)),0) -> 0.47162639 | ... L23: =IFERROR(HistoricalFS!L33/(SUM(HistoricalFS!L47:L48)),0) -> 0.46270981 | N23: =IFERROR(AVERAGE(C23:L23),0) -> 0.37359363 | O23: =IFERROR(MEDIAN(C23:L23),0) -> 0.37065643
B24: Self Sustained Growth Rate | C24: =IFERROR(C22*C23,0) -> 0.1504396 | D24: =IFERROR(D22*D23,0) -> 0.15005639 | E24: =IFERROR(E22*E23,0) -> 0.17933725 | F24: =IFERROR(F22*F23,0) -> 0.0059196919 | G24: =IFERROR(G22*G23,0) -> 0.19205627 | H24: =IFERROR(H22*H23,0) -> 0.21003152 | I24: =IFERROR(I22*I23,0) -> 0 | J24: =IFERROR(J22*J23,0) -> 0.17959089 | ... L24: =IFERROR(L22*L23,0) -> 0.091393137 | N24: =IFERROR(AVERAGE(C24:L24),0) -> 0.11588248 | O24: =IFERROR(MEDIAN(C24:L24),0) -> 0.15024799
B25: Interest Coverage Ratio | C25: =IFERROR((HistoricalFS!C27+HistoricalFS!C21)/HistoricalFS!C21,0) -> 950.53125 | D25: =IFERROR((HistoricalFS!D27+HistoricalFS!D21)/HistoricalFS!D21,0) -> 588.23077 | E25: =IFERROR((HistoricalFS!E27+HistoricalFS!E21)/HistoricalFS!E21,0) -> 189.34343 | F25: =IFERROR((HistoricalFS!F27+HistoricalFS!F21)/HistoricalFS!F21,0) -> 41.772727 | G25: =IFERROR((HistoricalFS!G27+HistoricalFS!G21)/HistoricalFS!G21,0) -> 66.711146 | H25: =IFERROR((HistoricalFS!H27+HistoricalFS!H21)/HistoricalFS!H21,0) -> 61.839286 | I25: =IFERROR((HistoricalFS!I27+HistoricalFS!I21)/HistoricalFS!I21,0) -> 69.671374 | J25: =IFERROR((HistoricalFS!J27+HistoricalFS!J21)/HistoricalFS!J21,0) -> 76.289203 | ... L25: =IFERROR((HistoricalFS!L27+HistoricalFS!L21)/HistoricalFS!L21,0) -> 54.507742 | N25: =IFERROR(AVERAGE(C25:L25),0) -> 217.70552 | O25: =IFERROR(MEDIAN(C25:L25),0) -> 72.980288
B27: Debtor Turnover Ratio | C27: =IFERROR(HistoricalFS!C6/HistoricalFS!C59,0) -> 5.2158111 | D27: =IFERROR(HistoricalFS!D6/HistoricalFS!D59,0) -> 4.9354127 | E27: =IFERROR(HistoricalFS!E6/HistoricalFS!E59,0) -> 5.3559204 | F27: =IFERROR(HistoricalFS!F6/HistoricalFS!F59,0) -> 5.1404756 | G27: =IFERROR(HistoricalFS!G6/HistoricalFS!G59,0) -> 5.4581934 | H27: =IFERROR(HistoricalFS!H6/HistoricalFS!H59,0) -> 4.5863191 | I27: =IFERROR(HistoricalFS!I6/HistoricalFS!I59,0) -> 4.5133122 | J27: =IFERROR(HistoricalFS!J6/HistoricalFS!J59,0) -> 4.4962017 | ... L27: =IFERROR(HistoricalFS!L6/HistoricalFS!L59,0) -> 3.9433647 | N27: =IFERROR(AVERAGE(C27:L27),0) -> 4.7969165 | O27: =IFERROR(MEDIAN(C27:L27),0) -> 4.7608659
B28: Creditor Turnover Ratio | C28: =IFERROR(HistoricalFS!C6/HistoricalFS!C50,0) -> 7.4520531 | D28: =IFERROR(HistoricalFS!D6/HistoricalFS!D50,0) -> 6.2327983 | E28: =IFERROR(HistoricalFS!E6/HistoricalFS!E50,0) -> 6.0043045 | F28: =IFERROR(HistoricalFS!F6/HistoricalFS!F50,0) -> 5.6401696 | G28: =IFERROR(HistoricalFS!G6/HistoricalFS!G50,0) -> 4.5905659 | H28: =IFERROR(HistoricalFS!H6/HistoricalFS!H50,0) -> 4.3613164 | I28: =IFERROR(HistoricalFS!I6/HistoricalFS!I50,0) -> 5.0385054 | J28: =IFERROR(HistoricalFS!J6/HistoricalFS!J50,0) -> 5.1295303 | ... L28: =IFERROR(HistoricalFS!L6/HistoricalFS!L50,0) -> 4.2625152 | N28: =IFERROR(AVERAGE(C28:L28),0) -> 5.3396517 | O28: =IFERROR(MEDIAN(C28:L28),0) -> 5.0840178
B29: Inventory Turnover | C29: =IFERROR(HistoricalFS!C6/HistoricalFS!C60,0) -> 5617.4286 | D29: =IFERROR(HistoricalFS!D6/HistoricalFS!D60,0) -> 4734.7692 | E29: =IFERROR(HistoricalFS!E6/HistoricalFS!E60,0) -> 14646.3 | F29: =IFERROR(HistoricalFS!F6/HistoricalFS!F60,0) -> 31389.8 | G29: =IFERROR(HistoricalFS!G6/HistoricalFS!G60,0) -> 20522.125 | H29: =IFERROR(HistoricalFS!H6/HistoricalFS!H60,0) -> 9587.7 | I29: =IFERROR(HistoricalFS!I6/HistoricalFS!I60,0) -> 8052.0714 | J29: =IFERROR(HistoricalFS!J6/HistoricalFS!J60,0) -> 8603.3214 | ... L29: =IFERROR(HistoricalFS!L6/HistoricalFS!L60,0) -> 9207.6207 | N29: =IFERROR(AVERAGE(C29:L29),0) -> 12451.942 | O29: =IFERROR(MEDIAN(C29:L29),0) -> 9397.6603
B30: Fixed Asset Turnover | C30: =IFERROR(HistoricalFS!C6/HistoricalFS!C53,0) -> 10.081702 | D30: =IFERROR(HistoricalFS!D6/HistoricalFS!D53,0) -> 10.281801 | E30: =IFERROR(HistoricalFS!E6/HistoricalFS!E53,0) -> 11.91725 | F30: =IFERROR(HistoricalFS!F6/HistoricalFS!F53,0) -> 7.4994744 | G30: =IFERROR(HistoricalFS!G6/HistoricalFS!G53,0) -> 7.8101422 | H30: =IFERROR(HistoricalFS!H6/HistoricalFS!H53,0) -> 9.0033806 | I30: =IFERROR(HistoricalFS!I6/HistoricalFS!I53,0) -> 10.98991 | J30: =IFERROR(HistoricalFS!J6/HistoricalFS!J53,0) -> 12.287951 | ... L30: =IFERROR(HistoricalFS!L6/HistoricalFS!L53,0) -> 8.5193185 | N30: =IFERROR(AVERAGE(C30:L30),0) -> 9.9466452 | O30: =IFERROR(MEDIAN(C30:L30),0) -> 10.181752
B31: Capital Turnover Ratio | C31: =IFERROR(HistoricalFS!C6/(SUM(HistoricalFS!C47:C48)),0) -> 1.3682929 | D31: =IFERROR(HistoricalFS!D6/(SUM(HistoricalFS!D47:D48)),0) -> 1.4461047 | E31: =IFERROR(HistoricalFS!E6/(SUM(HistoricalFS!E47:E48)),0) -> 1.6374461 | F31: =IFERROR(HistoricalFS!F6/(SUM(HistoricalFS!F47:F48)),0) -> 1.865642 | G31: =IFERROR(HistoricalFS!G6/(SUM(HistoricalFS!G47:G48)),0) -> 1.8994713 | H31: =IFERROR(HistoricalFS!H6/(SUM(HistoricalFS!H47:H48)),0) -> 2.1511796 | I31: =IFERROR(HistoricalFS!I6/(SUM(HistoricalFS!I47:I48)),0) -> 2.4933425 | J31: =IFERROR(HistoricalFS!J6/(SUM(HistoricalFS!J47:J48)),0) -> 2.6621247 | ... L31: =IFERROR(HistoricalFS!L6/(SUM(HistoricalFS!L47:L48)),0) -> 2.4899385 | N31: =IFERROR(AVERAGE(C31:L31),0) -> 2.0708084 | O31: =IFERROR(MEDIAN(C31:L31),0) -> 2.0253254
B33: Debtor Days | C33: =IFERROR(365/C27,0) -> 69.979528 | D33: =IFERROR(365/D27,0) -> 73.955314 | E33: =IFERROR(365/E27,0) -> 68.148884 | F33: =IFERROR(365/F27,0) -> 71.005104 | G33: =IFERROR(365/G27,0) -> 66.871943 | H33: =IFERROR(365/H27,0) -> 79.58452 | I33: =IFERROR(365/I27,0) -> 80.87187 | J33: =IFERROR(365/J27,0) -> 81.179632 | ... L33: =IFERROR(365/L27,0) -> 92.560548 | N33: =IFERROR(AVERAGE(C33:L33),0) -> 76.856692 | O33: =IFERROR(MEDIAN(C33:L33),0) -> 76.769917
B34: Payable Days | C34: =IFERROR(365/C28,0) -> 48.979791 | D34: =IFERROR(365/D28,0) -> 58.561176 | E34: =IFERROR(365/E28,0) -> 60.789722 | F34: =IFERROR(365/F28,0) -> 64.714366 | G34: =IFERROR(365/G28,0) -> 79.510894 | H34: =IFERROR(365/H28,0) -> 83.690327 | I34: =IFERROR(365/I28,0) -> 72.442118 | J34: =IFERROR(365/J28,0) -> 71.156613 | ... L34: =IFERROR(365/L28,0) -> 85.630194 | N34: =IFERROR(AVERAGE(C34:L34),0) -> 70.338744 | O34: =IFERROR(MEDIAN(C34:L34),0) -> 71.799365
B35: Inventory Days | C35: =IFERROR(365/C29,0) -> 0.064976349 | D35: =IFERROR(365/D29,0) -> 0.07708929 | E35: =IFERROR(365/E29,0) -> 0.02492097 | F35: =IFERROR(365/F29,0) -> 0.011627981 | G35: =IFERROR(365/G29,0) -> 0.017785683 | H35: =IFERROR(365/H29,0) -> 0.03806961 | I35: =IFERROR(365/I29,0) -> 0.045329951 | J35: =IFERROR(365/J29,0) -> 0.042425475 | ... L35: =IFERROR(365/L29,0) -> 0.039641077 | N35: =IFERROR(AVERAGE(C35:L35),0) -> 0.039188707 | O35: =IFERROR(MEDIAN(C35:L35),0) -> 0.038855343
B36: Cash Conversion Cycle (in Days) | C36: =IFERROR(SUM(C33,C35)-C34,0) -> 21.064714 | D36: =IFERROR(SUM(D33,D35)-D34,0) -> 15.471228 | E36: =IFERROR(SUM(E33,E35)-E34,0) -> 7.3840834 | F36: =IFERROR(SUM(F33,F35)-F34,0) -> 6.3023657 | G36: =IFERROR(SUM(G33,G35)-G34,0) -> -12.621165 | H36: =IFERROR(SUM(H33,H35)-H34,0) -> -4.0677378 | I36: =IFERROR(SUM(I33,I35)-I34,0) -> 8.4750818 | J36: =IFERROR(SUM(J33,J35)-J34,0) -> 10.065444 | ... L36: =IFERROR(SUM(L33,L35)-L34,0) -> 6.9699949 | N36: =IFERROR(AVERAGE(C36:L36),0) -> 6.5571362 | O36: =IFERROR(MEDIAN(C36:L36),0) -> 7.1770391
B38: CFO/Sales | C38: =IFERROR(HistoricalFS!C78/HistoricalFS!C6,0) -> 0.21381585 | D38: =IFERROR(HistoricalFS!D78/HistoricalFS!D6,0) -> 0.20362458 | E38: =IFERROR(HistoricalFS!E78/HistoricalFS!E6,0) -> 0.19522337 | F38: =IFERROR(HistoricalFS!F78/HistoricalFS!F6,0) -> 0.20623897 | G38: =IFERROR(HistoricalFS!G78/HistoricalFS!G6,0) -> 0.23634248 | H38: =IFERROR(HistoricalFS!H78/HistoricalFS!H6,0) -> 0.20833464 | I38: =IFERROR(HistoricalFS!I78/HistoricalFS!I6,0) -> 0.18613223 | J38: =IFERROR(HistoricalFS!J78/HistoricalFS!J6,0) -> 0.18405682 | ... L38: =IFERROR(HistoricalFS!L78/HistoricalFS!L6,0) -> 0.19509327 | N38: =IFERROR(AVERAGE(C38:L38),0) -> 0.20204149 | O38: =IFERROR(MEDIAN(C38:L38),0) -> 0.19942397
B39: CFO/Total Assets | C39: =IFERROR(HistoricalFS!C78/HistoricalFS!C64,0) -> 0.24647963 | D39: =IFERROR(HistoricalFS!D78/HistoricalFS!D64,0) -> 0.2384472 | E39: =IFERROR(HistoricalFS!E78/HistoricalFS!E64,0) -> 0.25103379 | F39: =IFERROR(HistoricalFS!F78/HistoricalFS!F64,0) -> 0.26945649 | G39: =IFERROR(HistoricalFS!G78/HistoricalFS!G64,0) -> 0.29849529 | H39: =IFERROR(HistoricalFS!H78/HistoricalFS!H64,0) -> 0.28347904 | I39: =IFERROR(HistoricalFS!I78/HistoricalFS!I64,0) -> 0.29375118 | J39: =IFERROR(HistoricalFS!J78/HistoricalFS!J64,0) -> 0.30478718 | ... L39: =IFERROR(HistoricalFS!L78/HistoricalFS!L64,0) -> 0.28754685 | N39: =IFERROR(AVERAGE(C39:L39),0) -> 0.27817547 | O39: =IFERROR(MEDIAN(C39:L39),0) -> 0.28551294
B40: CFO/Total Debt | C40: =IFERROR(HistoricalFS!C78/HistoricalFS!C49,0) -> 87.276817 | D40: =IFERROR(HistoricalFS!D78/HistoricalFS!D49,0) -> 101.48583 | E40: =IFERROR(HistoricalFS!E78/HistoricalFS!E49,0) -> 461.17742 | F40: =IFERROR(HistoricalFS!F78/HistoricalFS!F49,0) -> 3.9599951 | G40: =IFERROR(HistoricalFS!G78/HistoricalFS!G49,0) -> 4.9778063 | H40: =IFERROR(HistoricalFS!H78/HistoricalFS!H49,0) -> 5.1098746 | I40: =IFERROR(HistoricalFS!I78/HistoricalFS!I49,0) -> 5.4585068 | J40: =IFERROR(HistoricalFS!J78/HistoricalFS!J49,0) -> 5.5277397 | ... L40: =IFERROR(HistoricalFS!L78/HistoricalFS!L49,0) -> 4.6170345 | N40: =IFERROR(AVERAGE(C40:L40),0) -> 68.479843 | O40: =IFERROR(MEDIAN(C40:L40),0) -> 5.3329587

Sheet Common Size Statement
B2: ="Common Size Income Statement - "&'Data Sheet'!$B$1 -> Common Size Income Statement - TATA CONSULTANCY SERVICES LTD
B4: Particulars | C4: ='Data Sheet'!B16 -> 42825 | D4: ='Data Sheet'!C16 -> 43190 | E4: ='Data Sheet'!D16 -> 43555 | F4: ='Data Sheet'!E16 -> 43921 | G4: ='Data Sheet'!F16 -> 44286 | H4: ='Data Sheet'!G16 -> 44651 | I4: ='Data Sheet'!H16 -> 45016 | J4: ='Data Sheet'!I16 -> 45382 | ... L4: ='Data Sheet'!K16 -> 46112
B6: ='Data Sheet'!A17 -> Sales | C6: =IFERROR('Data Sheet'!B17/'Data Sheet'!B17,0) -> 1 | D6: =IFERROR('Data Sheet'!C17/'Data Sheet'!C17,0) -> 1 | E6: =IFERROR('Data Sheet'!D17/'Data Sheet'!D17,0) -> 1 | F6: =IFERROR('Data Sheet'!E17/'Data Sheet'!E17,0) -> 1 | G6: =IFERROR('Data Sheet'!F17/'Data Sheet'!F17,0) -> 1 | H6: =IFERROR('Data Sheet'!G17/'Data Sheet'!G17,0) -> 1 | I6: =IFERROR('Data Sheet'!H17/'Data Sheet'!H17,0) -> 1 | J6: =IFERROR('Data Sheet'!I17/'Data Sheet'!I17,0) -> 1 | ... L6: =IFERROR('Data Sheet'!K17/'Data Sheet'!K17,0) -> 1
B7: ='Data Sheet'!A18 -> Raw Material Cost | C7: =IFERROR('Data Sheet'!B18/'Data Sheet'!B$17,0) -> 0.00079683977 | D7: =IFERROR('Data Sheet'!C18/'Data Sheet'!C$17,0) -> 0.00069859631 | E7: =IFERROR('Data Sheet'!D18/'Data Sheet'!D$17,0) -> 0.00027310652 | F7: =IFERROR('Data Sheet'!E18/'Data Sheet'!E$17,0) -> 0.00011468694 | G7: =IFERROR('Data Sheet'!F18/'Data Sheet'!F$17,0) -> 8.527382e-05 | H7: =IFERROR('Data Sheet'!G18/'Data Sheet'!G$17,0) -> 0.00015123544 | I7: =IFERROR('Data Sheet'!H18/'Data Sheet'!H$17,0) -> 0.00016411039 | J7: =IFERROR('Data Sheet'!I18/'Data Sheet'!I$17,0) -> 0.00017435127 | ... L7: =IFERROR('Data Sheet'!K18/'Data Sheet'!K$17,0) -> 0.00016103602
B8: ='Data Sheet'!A19 -> Change in Inventory | C8: =IFERROR('Data Sheet'!B19/'Data Sheet'!B$17,0) -> 8.4770188e-06 | D8: =IFERROR('Data Sheet'!C19/'Data Sheet'!C$17,0) -> 0 | E8: =IFERROR('Data Sheet'!D19/'Data Sheet'!D$17,0) -> 0 | F8: =IFERROR('Data Sheet'!E19/'Data Sheet'!E$17,0) -> 0 | G8: =IFERROR('Data Sheet'!F19/'Data Sheet'!F$17,0) -> 0 | H8: =IFERROR('Data Sheet'!G19/'Data Sheet'!G$17,0) -> 0 | I8: =IFERROR('Data Sheet'!H19/'Data Sheet'!H$17,0) -> 0 | J8: =IFERROR('Data Sheet'!I19/'Data Sheet'!I$17,0) -> 0 | ... L8: =IFERROR('Data Sheet'!K19/'Data Sheet'!K$17,0) -> 0
B9: ='Data Sheet'!A20 -> Power and Fuel | C9: =IFERROR('Data Sheet'!B20/'Data Sheet'!B$17,0) -> 0 | D9: =IFERROR('Data Sheet'!C20/'Data Sheet'!C$17,0) -> 0 | E9: =IFERROR('Data Sheet'!D20/'Data Sheet'!D$17,0) -> 0 | F9: =IFERROR('Data Sheet'!E20/'Data Sheet'!E$17,0) -> 0 | G9: =IFERROR('Data Sheet'!F20/'Data Sheet'!F$17,0) -> 0 | H9: =IFERROR('Data Sheet'!G20/'Data Sheet'!G$17,0) -> 0 | I9: =IFERROR('Data Sheet'!H20/'Data Sheet'!H$17,0) -> 0 | J9: =IFERROR('Data Sheet'!I20/'Data Sheet'!I$17,0) -> 0 | ... L9: =IFERROR('Data Sheet'!K20/'Data Sheet'!K$17,0) -> 0
B10: ='Data Sheet'!A21 -> Other Mfr. Exp | C10: =IFERROR('Data Sheet'!B21/'Data Sheet'!B$17,0) -> 0.023015106 | D10: =IFERROR('Data Sheet'!C21/'Data Sheet'!C$17,0) -> 0.021234079 | E10: =IFERROR('Data Sheet'!D21/'Data Sheet'!D$17,0) -> 0.015225688 | F10: =IFERROR('Data Sheet'!E21/'Data Sheet'!E$17,0) -> 0.012023014 | G10: =IFERROR('Data Sheet'!F21/'Data Sheet'!F$17,0) -> 0.0088197494 | H10: =IFERROR('Data Sheet'!G21/'Data Sheet'!G$17,0) -> 0.0059138271 | I10: =IFERROR('Data Sheet'!H21/'Data Sheet'!H$17,0) -> 0.0081789069 | J10: =IFERROR('Data Sheet'!I21/'Data Sheet'!I$17,0) -> 0.015193468 | ... L10: =IFERROR('Data Sheet'!K21/'Data Sheet'!K$17,0) -> 0.016313324
B11: ='Data Sheet'!A22 -> Employee Cost | C11: =IFERROR('Data Sheet'!B22/'Data Sheet'!B$17,0) -> 0.52236238 | D11: =IFERROR('Data Sheet'!C22/'Data Sheet'!C$17,0) -> 0.53934884 | E11: =IFERROR('Data Sheet'!D22/'Data Sheet'!D$17,0) -> 0.53423732 | F11: =IFERROR('Data Sheet'!E22/'Data Sheet'!E$17,0) -> 0.54764286 | G11: =IFERROR('Data Sheet'!F22/'Data Sheet'!F$17,0) -> 0.5592379 | H11: =IFERROR('Data Sheet'!G22/'Data Sheet'!G$17,0) -> 0.56089573 | I11: =IFERROR('Data Sheet'!H22/'Data Sheet'!H$17,0) -> 0.56561311 | J11: =IFERROR('Data Sheet'!I22/'Data Sheet'!I$17,0) -> 0.5817147 | ... L11: =IFERROR('Data Sheet'!K22/'Data Sheet'!K$17,0) -> 0.58045622
B12: ='Data Sheet'!A23 -> Selling and admin | C12: =IFERROR('Data Sheet'!B23/'Data Sheet'!B$17,0) -> 0.13895529 | D12: =IFERROR('Data Sheet'!C23/'Data Sheet'!C$17,0) -> 0.13653496 | E12: =IFERROR('Data Sheet'!D23/'Data Sheet'!D$17,0) -> 0.13919556 | F12: =IFERROR('Data Sheet'!E23/'Data Sheet'!E$17,0) -> 0.13078771 | G12: =IFERROR('Data Sheet'!F23/'Data Sheet'!F$17,0) -> 0.11159907 | H12: =IFERROR('Data Sheet'!G23/'Data Sheet'!G$17,0) -> 0.12092055 | I12: =IFERROR('Data Sheet'!H23/'Data Sheet'!H$17,0) -> 0.12824118 | J12: =IFERROR('Data Sheet'!I23/'Data Sheet'!I$17,0) -> 0.10025613 | ... L12: =IFERROR('Data Sheet'!K23/'Data Sheet'!K$17,0) -> 0.091505912
B13: ='Data Sheet'!A24 -> Other Expenses | C13: =IFERROR('Data Sheet'!B24/'Data Sheet'!B$17,0) -> 0.040977909 | D13: =IFERROR('Data Sheet'!C24/'Data Sheet'!C$17,0) -> 0.038049129 | E13: =IFERROR('Data Sheet'!D24/'Data Sheet'!D$17,0) -> 0.041334672 | F13: =IFERROR('Data Sheet'!E24/'Data Sheet'!E$17,0) -> 0.041134381 | G13: =IFERROR('Data Sheet'!F24/'Data Sheet'!F$17,0) -> 0.036746926 | H13: =IFERROR('Data Sheet'!G24/'Data Sheet'!G$17,0) -> 0.035425597 | I13: =IFERROR('Data Sheet'!H24/'Data Sheet'!H$17,0) -> 0.034964384 | J13: =IFERROR('Data Sheet'!I24/'Data Sheet'!I$17,0) -> 0.035754464 | ... L13: =IFERROR('Data Sheet'!K24/'Data Sheet'!K$17,0) -> 0.040431277
B14: ='Data Sheet'!A25 -> Other Income | C14: =IFERROR('Data Sheet'!B25/'Data Sheet'!B$17,0) -> 0.035781496 | D14: =IFERROR('Data Sheet'!C25/'Data Sheet'!C$17,0) -> 0.029584741 | E14: =IFERROR('Data Sheet'!D25/'Data Sheet'!D$17,0) -> 0.029434055 | F14: =IFERROR('Data Sheet'!E25/'Data Sheet'!E$17,0) -> 0.029257912 | G14: =IFERROR('Data Sheet'!F25/'Data Sheet'!F$17,0) -> 0.011670331 | H14: =IFERROR('Data Sheet'!G25/'Data Sheet'!G$17,0) -> 0.020953931 | I14: =IFERROR('Data Sheet'!H25/'Data Sheet'!H$17,0) -> 0.015297749 | J14: =IFERROR('Data Sheet'!I25/'Data Sheet'!I$17,0) -> 0.014379828 | ... L14: =IFERROR('Data Sheet'!K25/'Data Sheet'!K$17,0) -> -0.00046438295
B15: ='Data Sheet'!A26 -> Depreciation | C15: =IFERROR('Data Sheet'!B26/'Data Sheet'!B$17,0) -> 0.016843836 | D15: =IFERROR('Data Sheet'!C26/'Data Sheet'!C$17,0) -> 0.016360151 | E15: =IFERROR('Data Sheet'!D26/'Data Sheet'!D$17,0) -> 0.014037675 | F15: =IFERROR('Data Sheet'!E26/'Data Sheet'!E$17,0) -> 0.022485011 | G15: =IFERROR('Data Sheet'!F26/'Data Sheet'!F$17,0) -> 0.024759863 | H15: =IFERROR('Data Sheet'!G26/'Data Sheet'!G$17,0) -> 0.024009929 | I15: =IFERROR('Data Sheet'!H26/'Data Sheet'!H$17,0) -> 0.022274659 | J15: =IFERROR('Data Sheet'!I26/'Data Sheet'!I$17,0) -> 0.020693835 | ... L15: =IFERROR('Data Sheet'!K26/'Data Sheet'!K$17,0) -> 0.020822332
B16: ='Data Sheet'!A27 -> Interest | C16: =IFERROR('Data Sheet'!B27/'Data Sheet'!B$17,0) -> 0.0002712646 | D16: =IFERROR('Data Sheet'!C27/'Data Sheet'!C$17,0) -> 0.00042240707 | E16: =IFERROR('Data Sheet'!D27/'Data Sheet'!D$17,0) -> 0.0013518773 | F16: =IFERROR('Data Sheet'!E27/'Data Sheet'!E$17,0) -> 0.0058872627 | G16: =IFERROR('Data Sheet'!F27/'Data Sheet'!F$17,0) -> 0.0038799588 | H16: =IFERROR('Data Sheet'!G27/'Data Sheet'!G$17,0) -> 0.0040885718 | I16: =IFERROR('Data Sheet'!H27/'Data Sheet'!H$17,0) -> 0.003455189 | J16: =IFERROR('Data Sheet'!I27/'Data Sheet'!I$17,0) -> 0.0032296497 | ... L16: =IFERROR('Data Sheet'!K27/'Data Sheet'!K$17,0) -> 0.0045951442
B17: ='Data Sheet'!A28 -> Profit before tax | C17: =IFERROR('Data Sheet'!B28/'Data Sheet'!B$17,0) -> 0.29256735 | D17: =IFERROR('Data Sheet'!C28/'Data Sheet'!C$17,0) -> 0.27693657 | E17: =IFERROR('Data Sheet'!D28/'Data Sheet'!D$17,0) -> 0.28377816 | F17: =IFERROR('Data Sheet'!E28/'Data Sheet'!E$17,0) -> 0.26918298 | G17: =IFERROR('Data Sheet'!F28/'Data Sheet'!F$17,0) -> 0.2665416 | H17: =IFERROR('Data Sheet'!G28/'Data Sheet'!G$17,0) -> 0.26954848 | I17: =IFERROR('Data Sheet'!H28/'Data Sheet'!H$17,0) -> 0.25240621 | J17: =IFERROR('Data Sheet'!I28/'Data Sheet'!I$17,0) -> 0.25736323 | ... L17: =IFERROR('Data Sheet'!K28/'Data Sheet'!K$17,0) -> 0.24525037
B18: ='Data Sheet'!A29 -> Tax | C18: =IFERROR('Data Sheet'!B29/'Data Sheet'!B$17,0) -> 0.069138565 | D18: =IFERROR('Data Sheet'!C29/'Data Sheet'!C$17,0) -> 0.066707824 | E18: =IFERROR('Data Sheet'!D29/'Data Sheet'!D$17,0) -> 0.068283457 | F18: =IFERROR('Data Sheet'!E29/'Data Sheet'!E$17,0) -> 0.062447037 | G18: =IFERROR('Data Sheet'!F29/'Data Sheet'!F$17,0) -> 0.068206874 | H18: =IFERROR('Data Sheet'!G29/'Data Sheet'!G$17,0) -> 0.06903637 | I18: =IFERROR('Data Sheet'!H29/'Data Sheet'!H$17,0) -> 0.064774814 | J18: =IFERROR('Data Sheet'!I29/'Data Sheet'!I$17,0) -> 0.065996106 | ... L18: =IFERROR('Data Sheet'!K29/'Data Sheet'!K$17,0) -> 0.060043967
... B20: ='Data Sheet'!A31 -> Dividend Amount | C20: =IFERROR('Data Sheet'!B31/'Data Sheet'!B$17,0) -> 0.078488717 | D20: =IFERROR('Data Sheet'!C31/'Data Sheet'!C$17,0) -> 0.077576683 | E20: =IFERROR('Data Sheet'!D31/'Data Sheet'!D$17,0) -> 0.076811208 | F20: =IFERROR('Data Sheet'!E31/'Data Sheet'!E$17,0) -> 0.17441972 | G20: =IFERROR('Data Sheet'!F31/'Data Sheet'!F$17,0) -> 0.08563928 | H20: =IFERROR('Data Sheet'!G31/'Data Sheet'!G$17,0) -> 0.082073907 | I20: =IFERROR('Data Sheet'!H31/'Data Sheet'!H$17,0) -> 0.18668666 | J20: =IFERROR('Data Sheet'!I31/'Data Sheet'!I$17,0) -> 0.10970016 | ... L20: =IFERROR('Data Sheet'!K31/'Data Sheet'!K$17,0) -> 0.14912685
B21: ='Data Sheet'!A33 -> EBITDA | C21: =IFERROR('Data Sheet'!B33/'Data Sheet'!B$17,0) -> 0.30910601 | D21: =IFERROR('Data Sheet'!C33/'Data Sheet'!C$17,0) -> 0.29328048 | E21: =IFERROR('Data Sheet'!D33/'Data Sheet'!D$17,0) -> 0.29855322 | F21: =IFERROR('Data Sheet'!E33/'Data Sheet'!E$17,0) -> 0.29687351 | G21: =IFERROR('Data Sheet'!F33/'Data Sheet'!F$17,0) -> 0.29437741 | H21: =IFERROR('Data Sheet'!G33/'Data Sheet'!G$17,0) -> 0.29701075 | I21: =IFERROR('Data Sheet'!H33/'Data Sheet'!H$17,0) -> 0.27744414 | J21: =IFERROR('Data Sheet'!I33/'Data Sheet'!I$17,0) -> 0.28049383 | ... L21: =IFERROR('Data Sheet'!K33/'Data Sheet'!K$17,0) -> 0.26975406
B23: ="Common Size Balance Sheet - "&'Data Sheet'!$B$1 -> Common Size Balance Sheet - TATA CONSULTANCY SERVICES LTD
B25: Particulars | C25: =C4 -> 42825 | D25: =D4 -> 43190 | E25: =E4 -> 43555 | F25: =F4 -> 43921 | G25: =G4 -> 44286 | H25: =H4 -> 44651 | I25: =I4 -> 45016 | J25: =J4 -> 45382 | ... L25: =L4 -> 46112
B27: Total Liabilities | C27: =IFERROR('Data Sheet'!B61/'Data Sheet'!B$61,0) -> 1 | D27: =IFERROR('Data Sheet'!C61/'Data Sheet'!C$61,0) -> 1 | E27: =IFERROR('Data Sheet'!D61/'Data Sheet'!D$61,0) -> 1 | F27: =IFERROR('Data Sheet'!E61/'Data Sheet'!E$61,0) -> 1 | G27: =IFERROR('Data Sheet'!F61/'Data Sheet'!F$61,0) -> 1 | H27: =IFERROR('Data Sheet'!G61/'Data Sheet'!G$61,0) -> 1 | I27: =IFERROR('Data Sheet'!H61/'Data Sheet'!H$61,0) -> 1 | J27: =IFERROR('Data Sheet'!I61/'Data Sheet'!I$61,0) -> 1 | ... L27: =IFERROR('Data Sheet'!K61/'Data Sheet'!K$61,0) -> 1
B28: ='Data Sheet'!A57 -> Equity Share Capital | C28: =IFERROR('Data Sheet'!B57/'Data Sheet'!B$61,0) -> 0.0019250877 | D28: =IFERROR('Data Sheet'!C57/'Data Sheet'!C$61,0) -> 0.0018168674 | E28: =IFERROR('Data Sheet'!D57/'Data Sheet'!D$61,0) -> 0.0032923328 | F28: =IFERROR('Data Sheet'!E57/'Data Sheet'!E$61,0) -> 0.0031216962 | G28: =IFERROR('Data Sheet'!F57/'Data Sheet'!F$61,0) -> 0.002846329 | H28: =IFERROR('Data Sheet'!G57/'Data Sheet'!G$61,0) -> 0.0025971446 | I28: =IFERROR('Data Sheet'!H57/'Data Sheet'!H$61,0) -> 0.0025619667 | J28: =IFERROR('Data Sheet'!I57/'Data Sheet'!I$61,0) -> 0.0024884514 | ... L28: =IFERROR('Data Sheet'!K57/'Data Sheet'!K$61,0) -> 0.0019981564
B29: ='Data Sheet'!A58 -> Reserves | C29: =IFERROR('Data Sheet'!B58/'Data Sheet'!B$61,0) -> 0.84055974 | D29: =IFERROR('Data Sheet'!C58/'Data Sheet'!C$61,0) -> 0.80795426 | E29: =IFERROR('Data Sheet'!D58/'Data Sheet'!D$61,0) -> 0.78200367 | F29: =IFERROR('Data Sheet'!E58/'Data Sheet'!E$61,0) -> 0.69718714 | G29: =IFERROR('Data Sheet'!F58/'Data Sheet'!F$61,0) -> 0.66206382 | H29: =IFERROR('Data Sheet'!G58/'Data Sheet'!G$61,0) -> 0.62993528 | I29: =IFERROR('Data Sheet'!H58/'Data Sheet'!H$61,0) -> 0.6303978 | J29: =IFERROR('Data Sheet'!I58/'Data Sheet'!I$61,0) -> 0.61954878 | ... L29: =IFERROR('Data Sheet'!K58/'Data Sheet'!K$61,0) -> 0.58994188
B30: ='Data Sheet'!A59 -> Borrowings | C30: =IFERROR('Data Sheet'!B59/'Data Sheet'!B$61,0) -> 0.0028241134 | D30: =IFERROR('Data Sheet'!C59/'Data Sheet'!C$61,0) -> 0.0023495615 | E30: =IFERROR('Data Sheet'!D59/'Data Sheet'!D$61,0) -> 0.00054433236 | F30: =IFERROR('Data Sheet'!E59/'Data Sheet'!E$61,0) -> 0.068044653 | G30: =IFERROR('Data Sheet'!F59/'Data Sheet'!F$61,0) -> 0.059965229 | H30: =IFERROR('Data Sheet'!G59/'Data Sheet'!G$61,0) -> 0.055476711 | I30: =IFERROR('Data Sheet'!H59/'Data Sheet'!H$61,0) -> 0.0538153 | J30: =IFERROR('Data Sheet'!I59/'Data Sheet'!I$61,0) -> 0.055137758 | ... L30: =IFERROR('Data Sheet'!K59/'Data Sheet'!K$61,0) -> 0.062279554
B31: ='Data Sheet'!A60 -> Other Liabilities | C31: =IFERROR('Data Sheet'!B60/'Data Sheet'!B$61,0) -> 0.15469106 | D31: =IFERROR('Data Sheet'!C60/'Data Sheet'!C$61,0) -> 0.18787931 | E31: =IFERROR('Data Sheet'!D60/'Data Sheet'!D$61,0) -> 0.21415966 | F31: =IFERROR('Data Sheet'!E60/'Data Sheet'!E$61,0) -> 0.23164651 | G31: =IFERROR('Data Sheet'!F60/'Data Sheet'!F$61,0) -> 0.27512462 | H31: =IFERROR('Data Sheet'!G60/'Data Sheet'!G$61,0) -> 0.31199086 | I31: =IFERROR('Data Sheet'!H60/'Data Sheet'!H$61,0) -> 0.31322493 | J31: =IFERROR('Data Sheet'!I60/'Data Sheet'!I$61,0) -> 0.32282501 | ... L31: =IFERROR('Data Sheet'!K60/'Data Sheet'!K$61,0) -> 0.34578041
B33: Total Assets | C33: =IFERROR('Data Sheet'!B76/'Data Sheet'!B$76,0) -> 1 | D33: =IFERROR('Data Sheet'!C76/'Data Sheet'!C$76,0) -> 1 | E33: =IFERROR('Data Sheet'!D76/'Data Sheet'!D$76,0) -> 1 | F33: =IFERROR('Data Sheet'!E76/'Data Sheet'!E$76,0) -> 1 | G33: =IFERROR('Data Sheet'!F76/'Data Sheet'!F$76,0) -> 1 | H33: =IFERROR('Data Sheet'!G76/'Data Sheet'!G$76,0) -> 1 | I33: =IFERROR('Data Sheet'!H76/'Data Sheet'!H$76,0) -> 1 | J33: =IFERROR('Data Sheet'!I76/'Data Sheet'!I$76,0) -> 1 | ... L33: =IFERROR('Data Sheet'!K76/'Data Sheet'!K$76,0) -> 1
B34: ='Data Sheet'!A62 -> Net Block | C34: =IFERROR('Data Sheet'!B62/'Data Sheet'!B$76,0) -> 0.11434239 | D34: =IFERROR('Data Sheet'!C62/'Data Sheet'!C$76,0) -> 0.1138919 | E34: =IFERROR('Data Sheet'!D62/'Data Sheet'!D$76,0) -> 0.10790072 | F34: =IFERROR('Data Sheet'!E62/'Data Sheet'!E$76,0) -> 0.17421562 | G34: =IFERROR('Data Sheet'!F62/'Data Sheet'!F$76,0) -> 0.16170995 | H34: =IFERROR('Data Sheet'!G62/'Data Sheet'!G$76,0) -> 0.15113111 | I34: =IFERROR('Data Sheet'!H62/'Data Sheet'!H$76,0) -> 0.14360313 | J34: =IFERROR('Data Sheet'!I62/'Data Sheet'!I$76,0) -> 0.13476133 | ... L34: =IFERROR('Data Sheet'!K62/'Data Sheet'!K$76,0) -> 0.17300612
B35: ='Data Sheet'!A63 -> Capital Work in Progress | C35: =IFERROR('Data Sheet'!B63/'Data Sheet'!B$76,0) -> 0.015058681 | D35: =IFERROR('Data Sheet'!C63/'Data Sheet'!C$76,0) -> 0.01215684 | E35: =IFERROR('Data Sheet'!D63/'Data Sheet'!D$76,0) -> 0.0084547107 | F35: =IFERROR('Data Sheet'!E63/'Data Sheet'!E$76,0) -> 0.007542018 | G35: =IFERROR('Data Sheet'!F63/'Data Sheet'!F$76,0) -> 0.0071235153 | H35: =IFERROR('Data Sheet'!G63/'Data Sheet'!G$76,0) -> 0.0085507082 | I35: =IFERROR('Data Sheet'!H63/'Data Sheet'!H$76,0) -> 0.0086378877 | J35: =IFERROR('Data Sheet'!I63/'Data Sheet'!I$76,0) -> 0.01075121 | ... L35: =IFERROR('Data Sheet'!K63/'Data Sheet'!K$76,0) -> 0.014710185
B36: ='Data Sheet'!A64 -> Investments | C36: =IFERROR('Data Sheet'!B64/'Data Sheet'!B$76,0) -> 0.41022935 | D36: =IFERROR('Data Sheet'!C64/'Data Sheet'!C$76,0) -> 0.34252231 | E36: =IFERROR('Data Sheet'!D64/'Data Sheet'!D$76,0) -> 0.25750432 | F36: =IFERROR('Data Sheet'!E64/'Data Sheet'!E$76,0) -> 0.21940113 | G36: =IFERROR('Data Sheet'!F64/'Data Sheet'!F$76,0) -> 0.22596006 | H36: =IFERROR('Data Sheet'!G64/'Data Sheet'!G$76,0) -> 0.21632227 | I36: =IFERROR('Data Sheet'!H64/'Data Sheet'!H$76,0) -> 0.26013762 | J36: =IFERROR('Data Sheet'!I64/'Data Sheet'!I$76,0) -> 0.21833755 | ... L36: =IFERROR('Data Sheet'!K64/'Data Sheet'!K$76,0) -> 0.18760591
B37: ='Data Sheet'!A65 -> Other Assets | C37: =IFERROR('Data Sheet'!B65/'Data Sheet'!B$76,0) -> 0.46036958 | D37: =IFERROR('Data Sheet'!C65/'Data Sheet'!C$76,0) -> 0.53142895 | E37: =IFERROR('Data Sheet'!D65/'Data Sheet'!D$76,0) -> 0.62614024 | F37: =IFERROR('Data Sheet'!E65/'Data Sheet'!E$76,0) -> 0.59884123 | G37: =IFERROR('Data Sheet'!F65/'Data Sheet'!F$76,0) -> 0.60520647 | H37: =IFERROR('Data Sheet'!G65/'Data Sheet'!G$76,0) -> 0.62399591 | I37: =IFERROR('Data Sheet'!H65/'Data Sheet'!H$76,0) -> 0.58762136 | J37: =IFERROR('Data Sheet'!I65/'Data Sheet'!I$76,0) -> 0.63614991 | ... L37: =IFERROR('Data Sheet'!K65/'Data Sheet'!K$76,0) -> 0.62467778
B38: ='Data Sheet'!A67 -> Receivables | C38: =IFERROR('Data Sheet'!B67/'Data Sheet'!B$76,0) -> 0.22101375 | D38: =IFERROR('Data Sheet'!C67/'Data Sheet'!C$76,0) -> 0.23726766 | E38: =IFERROR('Data Sheet'!D67/'Data Sheet'!D$76,0) -> 0.24008569 | F38: =IFERROR('Data Sheet'!E67/'Data Sheet'!E$76,0) -> 0.25416434 | G38: =IFERROR('Data Sheet'!F67/'Data Sheet'!F$76,0) -> 0.23139116 | H38: =IFERROR('Data Sheet'!G67/'Data Sheet'!G$76,0) -> 0.29668474 | I38: =IFERROR('Data Sheet'!H67/'Data Sheet'!H$76,0) -> 0.34967345 | J38: =IFERROR('Data Sheet'!I67/'Data Sheet'!I$76,0) -> 0.36829768 | ... L38: =IFERROR('Data Sheet'!K67/'Data Sheet'!K$76,0) -> 0.37376564
B39: ='Data Sheet'!A68 -> Inventory | C39: =IFERROR('Data Sheet'!B68/'Data Sheet'!B$76,0) -> 0.00020521239 | D39: =IFERROR('Data Sheet'!C68/'Data Sheet'!C$76,0) -> 0.00024732226 | E39: =IFERROR('Data Sheet'!D68/'Data Sheet'!D$76,0) -> 8.7795542e-05 | F39: =IFERROR('Data Sheet'!E68/'Data Sheet'!E$76,0) -> 4.1622616e-05 | G39: =IFERROR('Data Sheet'!F68/'Data Sheet'!F$76,0) -> 6.1542249e-05 | H39: =IFERROR('Data Sheet'!G68/'Data Sheet'!G$76,0) -> 0.00014192047 | I39: =IFERROR('Data Sheet'!H68/'Data Sheet'!H$76,0) -> 0.00019599745 | J39: =IFERROR('Data Sheet'!I68/'Data Sheet'!I$76,0) -> 0.0001924769 | ... L39: =IFERROR('Data Sheet'!K68/'Data Sheet'!K$76,0) -> 0.0001600733
B40: ='Data Sheet'!A69 -> Cash & Bank | C40: =IFERROR('Data Sheet'!B69/'Data Sheet'!B$76,0) -> 0.040544106 | D40: =IFERROR('Data Sheet'!C69/'Data Sheet'!C$76,0) -> 0.068118258 | E40: =IFERROR('Data Sheet'!D69/'Data Sheet'!D$76,0) -> 0.11279971 | F40: =IFERROR('Data Sheet'!E69/'Data Sheet'!E$76,0) -> 0.080464841 | G40: =IFERROR('Data Sheet'!F69/'Data Sheet'!F$76,0) -> 0.071765955 | H40: =IFERROR('Data Sheet'!G69/'Data Sheet'!G$76,0) -> 0.12929664 | I40: =IFERROR('Data Sheet'!H69/'Data Sheet'!H$76,0) -> 0.077222996 | J40: =IFERROR('Data Sheet'!I69/'Data Sheet'!I$76,0) -> 0.09133029 | ... L40: =IFERROR('Data Sheet'!K69/'Data Sheet'!K$76,0) -> 0.071249179

Sheet Data>

Sheet Data Sheet
A1: COMPANY NAME | B1: TATA CONSULTANCY SERVICES LTD | E1: =IF(B2<>B3, "A NEW VERSION OF THE WORKSHEET IS AVAILABLE", "")
A2: LATEST VERSION | B2: 2.1 | E2: PLEASE DO NOT MAKE ANY CHANGES TO THIS SHEET
A3: CURRENT VERSION | B3: 2.1
A5: META
A6: Number of shares | B6: =IF(B9>0, B9/B8, 0) -> 361.80875
A7: Face Value | B7: 1
A8: Current Price | B8: 2581.5
A9: Market Capitalization | B9: 934009.29
A15: PROFIT & LOSS
A16: Report Date | B16: 42825 | C16: 43190 | D16: 43555 | E16: 43921 | F16: 44286 | G16: 44651 | H16: 45016 | I16: 45382 | J16: 45747 | K16: 46112
A17: Sales | B17: 117966 | C17: 123104 | D17: 146463 | E17: 156949 | F17: 164177 | G17: 191754 | H17: 225458 | I17: 240893 | J17: 255324 | K17: 267021
A18: Raw Material Cost | B18: 94 | C18: 86 | D18: 40 | E18: 18 | F18: 14 | G18: 29 | H18: 37 | I18: 42 | J18: 49 | K18: 43
A19: Change in Inventory | B19: 1
A20: Power and Fuel
A21: Other Mfr. Exp | B21: 2715 | C21: 2614 | D21: 2230 | E21: 1887 | F21: 1448 | G21: 1134 | H21: 1844 | I21: 3660 | J21: 11599 | K21: 4356
A22: Employee Cost | B22: 61621 | C22: 66396 | D22: 78246 | E22: 85952 | F22: 91814 | G22: 107554 | H22: 127522 | I22: 140131 | J22: 145788 | K22: 154994
A23: Selling and admin | B23: 16392 | C23: 16808 | D23: 20387 | E23: 20527 | F23: 18322 | G23: 23187 | H23: 28913 | I23: 24151 | J23: 20729 | K23: 24434
A24: Other Expenses | B24: 4834 | C24: 4684 | D24: 6054 | E24: 6456 | F24: 6033 | G24: 6793 | H24: 7883 | I24: 8613 | J24: 9752 | K24: 10796
A25: Other Income | B25: 4221 | C25: 3642 | D25: 4311 | E25: 4592 | F25: 1916 | G25: 4018 | H25: 3449 | I25: 3464 | J25: 3962 | K25: -124
A26: Depreciation | B26: 1987 | C26: 2014 | D26: 2056 | E26: 3529 | F26: 4065 | G26: 4604 | H26: 5022 | I26: 4985 | J26: 5242 | K26: 5560
A27: Interest | B27: 32 | C27: 52 | D27: 198 | E27: 924 | F27: 637 | G27: 784 | H27: 779 | I27: 778 | J27: 796 | K27: 1227
A28: Profit before tax | B28: 34513 | C28: 34092 | D28: 41563 | E28: 42248 | F28: 43760 | G28: 51687 | H28: 56907 | I28: 61997 | J28: 65331 | K28: 65487
A29: Tax | B29: 8156 | C29: 8212 | D29: 10001 | E29: 9801 | F29: 11198 | G29: 13238 | H29: 14604 | I29: 15898 | J29: 16534 | K29: 16033
A30: Net profit | B30: 26289 | C30: 25826 | D30: 31472 | E30: 32340 | F30: 32430 | G30: 38327 | H30: 42147 | I30: 45908 | J30: 48553 | K30: 49210
A31: Dividend Amount | B31: 9259 | C31: 9550 | D31: 11250 | E31: 27375 | F31: 14060 | G31: 15738 | H31: 42090 | I31: 26426 | J31: 45612 | K31: 39820
A33: EBITDA | B33: =B30+B29+B27+B26 -> 36464 | C33: =C30+C29+C27+C26 -> 36104 | D33: =D30+D29+D27+D26 -> 43727 | E33: =E30+E29+E27+E26 -> 46594 | F33: =F30+F29+F27+F26 -> 48330 | G33: =G30+G29+G27+G26 -> 56953 | H33: =H30+H29+H27+H26 -> 62552 | I33: =I30+I29+I27+I26 -> 67569 | ... K33: =K30+K29+K27+K26 -> 72030
A40: Quarters
A41: Report Date | B41: 45291 | C41: 45382 | D41: 45473 | E41: 45565 | F41: 45657 | G41: 45747 | H41: 45838 | I41: 45930 | J41: 46022 | K41: 46112
A42: Sales | B42: 60583 | C42: 61237 | D42: 62613 | E42: 64259 | F42: 63973 | G42: 64479 | H42: 63437 | I42: 65799 | J42: 67087 | K42: 70698
A43: Expenses | B43: 44195 | C43: 44073 | D43: 45951 | E43: 47528 | F43: 46939 | G43: 47499 | H43: 46562 | I43: 47821 | J43: 48818 | K43: 51422
A44: Other Income | B44: -96 | C44: 1157 | D44: 962 | E44: 729 | F44: 1243 | G44: 1028 | H44: 1660 | I44: -268 | J44: -2273 | K44: 757
A45: Depreciation | B45: 1233 | C45: 1246 | D45: 1220 | E45: 1266 | F45: 1377 | G45: 1379 | H45: 1361 | I45: 1413 | J45: 1380 | K45: 1406
A46: Interest | B46: 230 | C46: 226 | D46: 173 | E46: 162 | F46: 234 | G46: 227 | H46: 195 | I46: 229 | J46: 538 | K46: 265
A47: Profit before tax | B47: 14829 | C47: 16849 | D47: 16231 | E47: 16032 | F47: 16666 | G47: 16402 | H47: 16979 | I47: 16068 | J47: 14078 | K47: 18362
A48: Tax | B48: 3732 | C48: 4347 | D48: 4126 | E48: 4077 | F48: 4222 | G48: 4109 | H48: 4160 | I48: 3937 | J48: 3358 | K48: 4578
A49: Net profit | B49: 11058 | C49: 12434 | D49: 12040 | E49: 11909 | F49: 12380 | G49: 12224 | H49: 12760 | I49: 12075 | J49: 10657 | K49: 13718
A50: Operating Profit | B50: 16388 | C50: 17164 | D50: 16662 | E50: 16731 | F50: 17034 | G50: 16980 | H50: 16875 | I50: 17978 | J50: 18269 | K50: 19276
A51: EBITDA | B51: =B49+B48+B46+B45 -> 16253 | C51: =C49+C48+C46+C45 -> 18253 | D51: =D49+D48+D46+D45 -> 17559 | E51: =E49+E48+E46+E45 -> 17414 | F51: =F49+F48+F46+F45 -> 18213 | G51: =G49+G48+G46+G45 -> 17939 | H51: =H49+H48+H46+H45 -> 18476 | I51: =I49+I48+I46+I45 -> 17654 | ... K51: =K49+K48+K46+K45 -> 19967
A55: BALANCE SHEET
A56: Report Date | B56: 42825 | C56: 43190 | D56: 43555 | E56: 43921 | F56: 44286 | G56: 44651 | H56: 45016 | I56: 45382 | J56: 45747 | K56: 46112
A57: Equity Share Capital | B57: 197 | C57: 191 | D57: 375 | E57: 375 | F57: 370 | G57: 366 | H57: 366 | I57: 362 | J57: 362 | K57: 362
A58: Reserves | B58: 86017 | C58: 84937 | D58: 89071 | E58: 83751 | F58: 86063 | G58: 88773 | H58: 90058 | I58: 90127 | J58: 94394 | K58: 106878
A59: Borrowings | B59: 289 | C59: 247 | D59: 62 | E59: 8174 | F59: 7795 | G59: 7818 | H59: 7688 | I59: 8021 | J59: 9392 | K59: 11283
A60: Other Liabilities | B60: 15830 | C60: 19751 | D60: 24393 | E60: 27827 | F60: 35764 | G60: 43967 | H60: 44747 | I60: 46962 | J60: 54501 | K60: 62644
A61: Total | B61: 102333 | C61: 105126 | D61: 113901 | E61: 120127 | F61: 129992 | G61: 140924 | H61: 142859 | I61: 145472 | J61: 158649 | K61: 181167
A62: Net Block | B62: 11701 | C62: 11973 | D62: 12290 | E62: 20928 | F62: 21021 | G62: 21298 | H62: 20515 | I62: 19604 | J62: 23053 | K62: 31343
A63: Capital Work in Progress | B63: 1541 | C63: 1278 | D63: 963 | E63: 906 | F63: 926 | G63: 1205 | H63: 1234 | I63: 1564 | J63: 1546 | K63: 2665
A64: Investments | B64: 41980 | C64: 36008 | D64: 29330 | E64: 26356 | F64: 29373 | G64: 30485 | H64: 37163 | I64: 31762 | J64: 30964 | K64: 33988
A65: Other Assets | B65: 47111 | C65: 55867 | D65: 71318 | E65: 71937 | F65: 78672 | G65: 87936 | H65: 83947 | I65: 92542 | J65: 103086 | K65: 113171
A66: Total | B66: 102333 | C66: 105126 | D66: 113901 | E66: 120127 | F66: 129992 | G66: 140924 | H66: 142859 | I66: 145472 | J66: 158649 | K66: 181167
A67: Receivables | B67: 22617 | C67: 24943 | D67: 27346 | E67: 30532 | F67: 30079 | G67: 41810 | H67: 49954 | I67: 53577 | J67: 59046 | K67: 67714
... A70: No. of Equity Shares | B70: 1970427941 | C70: 1914287591 | D70: 3752384706 | E70: 3752384706 | F70: 3699051373 | G70: 3659051373 | H70: 3659051373 | I70: 3618087518 | J70: 3618087518 | K70: 3618087518
A71: New Bonus Shares
A72: Face value | B72: 1 | C72: 1 | D72: 1 | E72: 1 | F72: 1 | G72: 1 | H72: 1 | I72: 1 | J72: 1 | K72: 1
A74: Other Asset | B74: =B65-SUM(B67:B69) -> 20324 | C74: =C65-SUM(C67:C69) -> 23737 | D74: =D65-SUM(D67:D69) -> 31114 | E74: =E65-SUM(E67:E69) -> 31734 | F74: =F65-SUM(F67:F69) -> 39256 | G74: =G65-SUM(G67:G69) -> 27885 | H74: =H65-SUM(H67:H69) -> 22933 | I74: =I65-SUM(I67:I69) -> 25651 | ... K74: =K65-SUM(K67:K69) -> 32520
A76: Total Asset | B76: =B61 -> 102333 | C76: =C61 -> 105126 | D76: =D61 -> 113901 | E76: =E61 -> 120127 | F76: =F61 -> 129992 | G76: =G61 -> 140924 | H76: =H61 -> 142859 | I76: =I61 -> 145472 | ... K76: =K61 -> 181167
A80: CASH FLOW:
A81: Report Date | B81: 42825 | C81: 43190 | D81: 43555 | E81: 43921 | F81: 44286 | G81: 44651 | H81: 45016 | I81: 45382 | J81: 45747 | K81: 46112
A82: Cash from Operating Activity | B82: 25223 | C82: 25067 | D82: 28593 | E82: 32369 | F82: 38802 | G82: 39949 | H82: 41965 | I82: 44338 | J82: 48908 | K82: 52094
A83: Cash from Investing Activity | B83: -16895 | C83: 3104 | D83: 1645 | E83: 8968 | F83: -7956 | G83: -738 | H83: 548 | I83: 6091 | J83: -2144 | K83: -11886
A84: Cash from Financing Activity | B84: -11026 | C84: -26885 | D84: -27897 | E84: -39915 | F84: -32634 | G84: -33581 | H84: -47878 | I84: -48536 | J84: -47438 | K84: -42133
A85: Net Cash Flow | B85: -2698 | C85: 1286 | D85: 2341 | E85: 1422 | F85: -1788 | G85: 5630 | H85: -5365 | I85: 1893 | J85: -674 | K85: -1925
A90: PRICE: | B90: 1215.9 | C90: 1424.58 | D90: 2001.65 | E90: 1826.1 | F90: 3177.85 | G90: 3739.95 | H90: 3205.9 | I90: 3876.3 | J90: 3606.15 | K90: 2358.9
A92: DERIVED:
A93: Adjusted Equity Shares in Cr | B93: 394.09 | C93: 382.86 | D93: 375.24 | E93: 375.24 | F93: 369.91 | G93: 365.91 | H93: 365.91 | I93: 361.81 | J93: 361.81 | K93: 361.81

Sheet Cash Flow Data
C2: 42795 | D2: 43160 | E2: 43525 | F2: 43891 | G2: 44256 | H2: 44621 | I2: 44986 | J2: 45352 | K2: 45717 | L2: 46082
B3: Cash from Operating Activity - | C3: =C4+C10+C11 -> 25223 | D3: =D4+D10+D11 -> 25067 | E3: =E4+E10+E11 -> 28593 | F3: =F4+F10+F11 -> 32369 | G3: =G4+G10+G11 -> 38802 | H3: =H4+H10+H11 -> 39949 | I3: =I4+I10+I11 -> 41965 | J3: =J4+J10+J11 -> 44338 | ... L3: =L4+L10+L11 -> 52094
B4: Profit from operations | C4: 33800 | D4: 32885 | E4: 40720 | F4: 42882 | G4: 47031 | H4: 54204 | I4: 59148 | J4: 63709 | K4: 67853 | L4: 68688
B5: Receivables | C5: 680 | D5: -1833 | E5: -2883 | F5: -3295 | G5: 1059 | H5: -5144 | I5: -7683 | J5: -3332 | K5: -5228 | L5: -5248
B6: Inventory | C6: 0 | D6: -5 | E6: 16 | F6: 5 | G6: -3 | H6: -12 | I6: -8 | J6: 0 | K6: 7 | L6: -8
B7: Payables | C7: -201 | D7: -346 | E7: 1496 | F7: 446 | G7: -93 | H7: 186 | I7: 2036 | J7: -632 | K7: 3718 | L7: -1105
B8: Loans Advances | C8: 0 | D8: 0 | E8: -499 | F8: 0 | G8: -17 | H8: -116 | I8: 261 | J8: -301 | K8: -738 | L8: 197
B9: Other WC items | C9: -1110 | D9: 1975 | E9: -299 | F9: -1823 | G9: -83 | H9: 2317 | I9: 1177 | J9: -2617 | K9: -1118 | L9: 3954
B10: Working capital changes | C10: =SUM(C5:C9) -> -631 | D10: =SUM(D5:D9) -> -209 | E10: =SUM(E5:E9) -> -2169 | F10: =SUM(F5:F9) -> -4667 | G10: =SUM(G5:G9) -> 863 | H10: =SUM(H5:H9) -> -2769 | I10: =SUM(I5:I9) -> -4217 | J10: =SUM(J5:J9) -> -6882 | ... L10: =SUM(L5:L9) -> -2210
B11: Direct taxes | C11: -7946 | D11: -7609 | E11: -9958 | F11: -5846 | G11: -9092 | H11: -11486 | I11: -12966 | J11: -12489 | K11: -15586 | L11: -14384
B12: Cash from Investing Activity - | C12: -16895 | D12: 3104 | E12: 1645 | F12: 8968 | G12: -7956 | H12: -738 | I12: 548 | J12: 6091 | K12: -2144 | L12: -12845
B13: Fixed assets purchased | C13: -1989 | D13: -1862 | E13: -2231 | F13: -3249 | G13: -3176 | H13: -2995 | I13: -3100 | J13: -2674 | K13: -3937 | L13: -4187
B14: Fixed assets sold | C14: 36 | D14: 58 | E14: 99 | F14: 161 | G14: 37 | H14: 31 | I14: 37 | J14: 24 | K14: 23 | L14: 931
B15: Investments purchased | C15: -121423 | D15: -97473 | E15: -96751 | F15: -80002 | G15: -54462 | H15: -75374 | I15: -129745 | J15: -141011 | K15: -145962 | L15: -151864
B16: Investments sold | C16: 102798 | D16: 103482 | E16: 104133 | F16: 84089 | G16: 51630 | H16: 73852 | I16: 122687 | J16: 147204 | K16: 147695 | L16: 148023
B17: Interest received | C17: 1788 | D17: 2623 | E17: 2619 | F17: 3729 | G17: 2730 | H17: 2700 | I17: 3080 | J17: 2990 | K17: 3056 | L17: 3008
B18: Dividends received | C18: 1 | D18: 9 | E18: 18 | F18: 8 | G18: 8 | H18: 4 | I18: 13 | J18: 26 | K18: 40 | L18: 84
B19: Acquisition of companies | C19: 0 | D19: 0 | E19: -50 | F19: 0 | G19: 0 | H19: 0 | I19: 0 | J19: 0 | K19: 0 | L19: 0
B20: Inter corporate deposits | C20: 1619 | D20: -2230 | E20: -2927 | F20: -473 | G20: -3058 | H20: 4879 | I20: 5361 | J20: 846 | K20: 170 | L20: 0
B21: Other investing items | C21: 275 | D21: -1503 | E21: -3265 | F21: 4705 | G21: -1665 | H21: -3835 | I21: 2215 | J21: -1314 | K21: -3229 | L21: -8840
B22: Cash from Financing Activity - | C22: -11026 | D22: -26885 | E22: -27897 | F22: -39915 | G22: -32634 | H22: -33581 | I22: -47878 | J22: -48536 | K22: -47438 | L22: -42133
... B30: Net Cash Flow | C30: -2698 | D30: 1286 | E30: 2341 | F30: 1422 | G30: -1788 | H30: 5630 | I30: -5365 | J30: 1893 | K30: -674 | L30: -2884
